Workbook
Name IQ_CH: 110000
Name IQ_CQ: 5000
Name IQ_CY: 10000
Name IQ_DAILY: 500000
Name IQ_FH: 100000
Name IQ_FQ: 500
Name IQ_FY: 1000
Name IQ_LTM: 2000
Name IQ_MONTH: 15000
Name IQ_NTM: 6000
Name IQ_WEEK: 50000
Name IQ_YTD: 3000

Sheet Input Sheet
B3: Please provide the below inputs
B5: Name of the company | C5: Mankind Pharma Ltd
B7: WACC Inputs
B8: Country | C8: India
B9: Local Currency 10Y Government Bond Yield | C9: 0.0637
B10: =C8&"'s"&" Moodys Soveriegn Rating" -> India's Moodys Soveriegn Rating | C10: =VLOOKUP(C8,'Damodaran Data'!C5:E161,3,FALSE) -> Baa3
B11: Credit default spread as per Dr Damodaran | C11: =VLOOKUP(C8,'Damodaran Data'!C5:F161,4,FALSE) -> 0.0216
B12: Implied US Equity Risk Premium | C12: 0.0384
B13: Asset Beta | C13: =WACC!G77 -> 0.53918512
B14: Asset Beta Variation (+/-) | C14: 0.05
B15: Debt to Equity Ratio | C15: ='Assumptions Working'!I818 -> 0.59187826
B16: Debt to Capital (Gearing) | C16: ='Assumptions Working'!I819 -> 0.36800801
B17: Marginal Tax Rate | C17: 0.25
B18: Company Credit Rating Available ? | C18: No
B19: Company is Large Firm or Small Firm ? | C19: Large | G19: Large
B20: Provide Credit Rating | C20: A1/A+ | G20: Small
B21: Interest Coverage Ratio | C21: ='3StatementModel'!H30/('3StatementModel'!H34*-1) -> 4.7295296
B22: ICR based Corporate Default Spread | C22: =IF(C19="Large",VLOOKUP('Input Sheet'!C21,'Damodaran Data'!H6:K21,4,TRUE),VLOOKUP(C21,'Damodaran Data'!M6:P21,4,TRUE)) -> 0.0085
B23: Small Size Premium | C23: 0.056
B24: Asset Specific Risk Premium | C24: 0

Sheet ControlSheet 
B2: ='Input Sheet'!C5 -> Mankind Pharma Ltd
B3: Control Sheet | R3: Management Case
I4: Current Case | K4: 1 | R4: Base Case
R5: Worst Case
E8: Actual | J8: Explicit Forecast Period | O8: Maturity Period
B9: In INR Crores unless stated otherwise | E9: 2021 | F9: =E9+1 -> 2022 | G9: =F9+1 -> 2023 | H9: =G9+1 -> 2024 | I9: =H9+1 -> 2025 | J9: =I9+1 -> 2026 | K9: =J9+1 -> 2027 | L9: =K9+1 -> 2028 | M9: =L9+1 -> 2029 | ... S9: =R9+1 -> 2035
B11: Assumptions
A13: # | B13: Revenue
B15: Revenue - yoy % growth | K15: =J16-(($J$16-$N$16)/($N$9-$J$9)) -> 0.165
B16: Management Case | E16: ='Income Stmt'!E9 -> 0.059951905 | F16: ='Income Stmt'!F9 -> 0.2502703 | G16: ='Income Stmt'!G9 -> 0.12438104 | H16: ='Income Stmt'!H9 -> 0.18119364 | I16: ='Income Stmt'!I9 -> 0.18115784 | J16: 0.18 | K16: =J16-(($J$16-$N$16)/($N$9-$J$9)) -> 0.165 | L16: =K16-(($J$16-$N$16)/($N$9-$J$9)) -> 0.15 | M16: =L16-(($J$16-$N$16)/($N$9-$J$9)) -> 0.135 | N16: 0.12 | O16: 0.12 | P16: 0.12 | Q16: 0.12 | R16: 0.12 | S16: 0.12
B17: Base Case | E17: =E16 -> 0.059951905 | F17: =F16 -> 0.2502703 | G17: =G16 -> 0.12438104 | H17: =H16 -> 0.18119364 | I17: =I16 -> 0.18115784 | J17: 0.2 | K17: =J17-(($J$17-$N$17)/($N$9-$J$9)) -> 0.18 | L17: =K17-(($J$17-$N$17)/($N$9-$J$9)) -> 0.16 | M17: =L17-(($J$17-$N$17)/($N$9-$J$9)) -> 0.14 | N17: 0.12 | O17: 0.12 | P17: 0.12 | Q17: 0.12 | R17: 0.12 | S17: 0.12
B18: Down Case | E18: =E17 -> 0.059951905 | F18: =F17 -> 0.2502703 | G18: =G17 -> 0.12438104 | H18: =H17 -> 0.18119364 | I18: =I17 -> 0.18115784 | J18: 0.14 | K18: =J18-(($J$18-$N$18)/($N$9-$J$9)) -> 0.13 | L18: =K18-(($J$18-$N$18)/($N$9-$J$9)) -> 0.12 | M18: =L18-(($J$18-$N$18)/($N$9-$J$9)) -> 0.11 | N18: 0.1 | O18: 0.1 | P18: 0.1 | Q18: 0.1 | R18: 0.1 | S18: 0.1
B19: ="Current Case - "&CHOOSE($K$4,B16,B17,B18) -> Current Case - Management Case | J19: =CHOOSE($K$4,J16,J17,J18) -> 0.18 | K19: =CHOOSE($K$4,K16,K17,K18) -> 0.165 | L19: =CHOOSE($K$4,L16,L17,L18) -> 0.15 | M19: =CHOOSE($K$4,M16,M17,M18) -> 0.135 | N19: =CHOOSE($K$4,N16,N17,N18) -> 0.12 | O19: =CHOOSE($K$4,O16,O17,O18) -> 0.12 | P19: =CHOOSE($K$4,P16,P17,P18) -> 0.12 | Q19: =CHOOSE($K$4,Q16,Q17,Q18) -> 0.12 | ... S19: =CHOOSE($K$4,S16,S17,S18) -> 0.12
A21: # | B21: COGS
B23: Gross Margin%
B24: Management Case | E24: ='Income Stmt'!E21 -> 0.71390772 | F24: ='Income Stmt'!F21 -> 0.68878606 | G24: ='Income Stmt'!G21 -> 0.66699076 | H24: ='Income Stmt'!H21 -> 0.68942759 | I24: ='Income Stmt'!I21 -> 0.68419431 | J24: 0.66 | K24: =J24-(($J$24-$N$24)/($N$9-$J$9)) -> 0.666 | L24: =K24-(($J$24-$N$24)/($N$9-$J$9)) -> 0.672 | M24: =L24-(($J$24-$N$24)/($N$9-$J$9)) -> 0.678 | N24: 0.684 | O24: 0.684 | P24: 0.684 | Q24: 0.684 | R24: 0.684 | S24: 0.684
B25: Base Case | E25: =E24 -> 0.71390772 | F25: =F24 -> 0.68878606 | G25: =G24 -> 0.66699076 | H25: =H24 -> 0.68942759 | I25: =I24 -> 0.68419431 | J25: 0.68 | K25: =J25-(($J$25-$N$25)/($N$9-$J$9)) -> 0.665 | L25: =K25-(($J$25-$N$25)/($N$9-$J$9)) -> 0.65 | M25: =L25-(($J$25-$N$25)/($N$9-$J$9)) -> 0.635 | N25: 0.62 | O25: 0.62 | P25: 0.62 | Q25: 0.62 | R25: 0.62 | S25: 0.62
B26: Down Case | E26: =E25 -> 0.71390772 | F26: =F25 -> 0.68878606 | G26: =G25 -> 0.66699076 | H26: =H25 -> 0.68942759 | I26: =I25 -> 0.68419431 | J26: 0.65 | K26: =J26-(($J$26-$N$26)/($N$9-$J$9)) -> 0.604975 | L26: =K26-(($J$26-$N$26)/($N$9-$J$9)) -> 0.55995 | M26: =L26-(($J$26-$N$26)/($N$9-$J$9)) -> 0.514925 | N26: 0.4699 | O26: 0.4699 | P26: 0.4699 | Q26: 0.4699 | R26: 0.4699 | S26: 0.4699
B27: ="Current Case - "&CHOOSE($K$4,B24,B25,B26) -> Current Case - Management Case | J27: =CHOOSE($K$4,J24,J25,J26) -> 0.66 | K27: =CHOOSE($K$4,K24,K25,K26) -> 0.666 | L27: =CHOOSE($K$4,L24,L25,L26) -> 0.672 | M27: =CHOOSE($K$4,M24,M25,M26) -> 0.678 | N27: =CHOOSE($K$4,N24,N25,N26) -> 0.684 | O27: =CHOOSE($K$4,O24,O25,O26) -> 0.684 | P27: =CHOOSE($K$4,P24,P25,P26) -> 0.684 | Q27: =CHOOSE($K$4,Q24,Q25,Q26) -> 0.684 | ... S27: =CHOOSE($K$4,S24,S25,S26) -> 0.684
B29: Current Case - COGS % Sales | E29: =1-E26 -> 0.28609228 | F29: =1-F26 -> 0.31121394 | G29: =1-G26 -> 0.33300924 | H29: =1-H26 -> 0.31057241 | I29: =1-I26 -> 0.31580569 | J29: =1-J27 -> 0.34 | K29: =1-K27 -> 0.334 | L29: =1-L27 -> 0.328 | M29: =1-M27 -> 0.322 | N29: =1-N27 -> 0.316 | O29: =1-O27 -> 0.316 | P29: =1-P27 -> 0.316 | Q29: =1-Q27 -> 0.316 | ... S29: =1-S27 -> 0.316
A32: # | B32: Selling , General & Administration (SG&A)
B34: Employee Benefit Expense % Revenue
B35: Management Case | E35: ='Assumptions Working'!E355 -> 0.22747159 | F35: ='Assumptions Working'!F355 -> 0.20825914 | G35: ='Assumptions Working'!G355 -> 0.21926564 | H35: ='Assumptions Working'!H355 -> 0.22010156 | I35: ='Assumptions Working'!I355 -> 0.2205292 | J35: 0.22 | K35: 0.22 | L35: 0.22 | M35: 0.22 | N35: 0.22 | O35: 0.22 | P35: 0.22 | Q35: 0.22 | R35: 0.22 | S35: 0.22
B36: Base Case | E36: =E35 -> 0.22747159 | F36: =F35 -> 0.20825914 | G36: =G35 -> 0.21926564 | H36: =H35 -> 0.22010156 | I36: =I35 -> 0.2205292 | J36: 0.22 | K36: 0.22 | L36: 0.22 | M36: 0.22 | N36: 0.22 | O36: 0.22 | P36: 0.22 | Q36: 0.22 | R36: 0.22 | S36: 0.22
B37: Down Case | E37: =E36 -> 0.22747159 | F37: =F36 -> 0.20825914 | G37: =G36 -> 0.21926564 | H37: =H36 -> 0.22010156 | I37: =I36 -> 0.2205292 | J37: 0.22 | K37: 0.22 | L37: 0.22 | M37: 0.22 | N37: 0.22 | O37: 0.22 | P37: 0.22 | Q37: 0.22 | R37: 0.22 | S37: 0.22
B38: ="Current Case - "&CHOOSE($K$4,B35,B36,B37) -> Current Case - Management Case | J38: =CHOOSE($K$4,J35,J36,J37) -> 0.22 | K38: =CHOOSE($K$4,K35,K36,K37) -> 0.22 | L38: =CHOOSE($K$4,L35,L36,L37) -> 0.22 | M38: =CHOOSE($K$4,M35,M36,M37) -> 0.22 | N38: =CHOOSE($K$4,N35,N36,N37) -> 0.22 | O38: =CHOOSE($K$4,O35,O36,O37) -> 0.22 | P38: =CHOOSE($K$4,P35,P36,P37) -> 0.22 | Q38: =CHOOSE($K$4,Q35,Q36,Q37) -> 0.22 | ... S38: =CHOOSE($K$4,S35,S36,S37) -> 0.22
B40: Advertising & Sales Promotion Expense % Revenue
B41: Management Case | E41: ='Assumptions Working'!E358 -> 0.061977235 | F41: ='Assumptions Working'!F358 -> 0.058029532 | G41: ='Assumptions Working'!G358 -> 0.042707407 | H41: ='Assumptions Working'!H358 -> 0.058433031 | I41: ='Assumptions Working'!I358 -> 0.061849758 | J41: 0.058 | K41: 0.058 | L41: 0.058 | M41: 0.058 | N41: 0.058 | O41: 0.058 | P41: 0.058 | Q41: 0.058 | R41: 0.058 | S41: 0.058
B42: Base Case | E42: =E41 -> 0.061977235 | F42: =F41 -> 0.058029532 | G42: =G41 -> 0.042707407 | H42: =H41 -> 0.058433031 | I42: =I41 -> 0.061849758 | J42: 0.058 | K42: 0.058 | L42: 0.058 | M42: 0.058 | N42: 0.058 | O42: 0.058 | P42: 0.058 | Q42: 0.058 | R42: 0.058 | S42: 0.058
B43: Down Case | E43: =E42 -> 0.061977235 | F43: =F42 -> 0.058029532 | G43: =G42 -> 0.042707407 | H43: =H42 -> 0.058433031 | I43: =I42 -> 0.061849758 | J43: 0.058 | K43: 0.058 | L43: 0.058 | M43: 0.058 | N43: 0.058 | O43: 0.058 | P43: 0.058 | Q43: 0.058 | R43: 0.058 | S43: 0.058
B44: ="Current Case - "&CHOOSE($K$4,B41,B42,B43) -> Current Case - Management Case | J44: =CHOOSE($K$4,J41,J42,J43) -> 0.058 | K44: =CHOOSE($K$4,K41,K42,K43) -> 0.058 | L44: =CHOOSE($K$4,L41,L42,L43) -> 0.058 | M44: =CHOOSE($K$4,M41,M42,M43) -> 0.058 | N44: =CHOOSE($K$4,N41,N42,N43) -> 0.058 | O44: =CHOOSE($K$4,O41,O42,O43) -> 0.058 | P44: =CHOOSE($K$4,P41,P42,P43) -> 0.058 | Q44: =CHOOSE($K$4,Q41,Q42,Q43) -> 0.058 | ... S44: =CHOOSE($K$4,S41,S42,S43) -> 0.058
B46: Travelling and conveyance Expense % Revenue
B47: Management Case | E47: ='Assumptions Working'!E361 -> 0.043445441 | F47: ='Assumptions Working'!F361 -> 0.046020364 | G47: ='Assumptions Working'!G361 -> 0.056694748 | H47: ='Assumptions Working'!H361 -> 0.036614267 | I47: ='Assumptions Working'!I361 -> 0.037765217 | J47: 0.046 | K47: 0.046 | L47: 0.046 | M47: 0.046 | N47: 0.046 | O47: 0.046 | P47: 0.046 | Q47: 0.046 | R47: 0.046 | S47: 0.046
B48: Base Case | E48: =E47 -> 0.043445441 | F48: =F47 -> 0.046020364 | G48: =G47 -> 0.056694748 | H48: =H47 -> 0.036614267 | I48: =I47 -> 0.037765217 | J48: 0.046 | K48: 0.046 | L48: 0.046 | M48: 0.046 | N48: 0.046 | O48: 0.046 | P48: 0.046 | Q48: 0.046 | R48: 0.046 | S48: 0.046
B49: Down Case | E49: =E48 -> 0.043445441 | F49: =F48 -> 0.046020364 | G49: =G48 -> 0.056694748 | H49: =H48 -> 0.036614267 | I49: =I48 -> 0.037765217 | J49: 0.046 | K49: 0.046 | L49: 0.046 | M49: 0.046 | N49: 0.046 | O49: 0.046 | P49: 0.046 | Q49: 0.046 | R49: 0.046 | S49: 0.046
B50: ="Current Case - "&CHOOSE($K$4,B47,B48,B49) -> Current Case - Management Case | J50: =CHOOSE($K$4,J47,J48,J49) -> 0.046 | K50: =CHOOSE($K$4,K47,K48,K49) -> 0.046 | L50: =CHOOSE($K$4,L47,L48,L49) -> 0.046 | M50: =CHOOSE($K$4,M47,M48,M49) -> 0.046 | N50: =CHOOSE($K$4,N47,N48,N49) -> 0.046 | O50: =CHOOSE($K$4,O47,O48,O49) -> 0.046 | P50: =CHOOSE($K$4,P47,P48,P49) -> 0.046 | Q50: =CHOOSE($K$4,Q47,Q48,Q49) -> 0.046 | ... S50: =CHOOSE($K$4,S47,S48,S49) -> 0.046
B52: Other Operating Expense % Revenue
B53: Management Case | E53: ='Assumptions Working'!E364 -> 0.059441846 | F53: ='Assumptions Working'!F364 -> 0.065664253 | G53: ='Assumptions Working'!G364 -> 0.070768529 | H53: ='Assumptions Working'!H364 -> 0.077786834 | I53: ='Assumptions Working'!I364 -> 0.087900385 | J53: 0.066 | K53: 0.066 | L53: 0.066 | M53: 0.066 | N53: 0.066 | O53: 0.066 | P53: 0.066 | Q53: 0.066 | R53: 0.066 | S53: 0.066
B54: Base Case | E54: =E53 -> 0.059441846 | F54: =F53 -> 0.065664253 | G54: =G53 -> 0.070768529 | H54: =H53 -> 0.077786834 | I54: =I53 -> 0.087900385 | J54: 0.066 | K54: 0.066 | L54: 0.066 | M54: 0.066 | N54: 0.066 | O54: 0.066 | P54: 0.066 | Q54: 0.066 | R54: 0.066 | S54: 0.066
B55: Down Case | E55: =E54 -> 0.059441846 | F55: =F54 -> 0.065664253 | G55: =G54 -> 0.070768529 | H55: =H54 -> 0.077786834 | I55: =I54 -> 0.087900385 | J55: 0.066 | K55: 0.066 | L55: 0.066 | M55: 0.066 | N55: 0.066 | O55: 0.066 | P55: 0.066 | Q55: 0.066 | R55: 0.066 | S55: 0.066
B56: ="Current Case - "&CHOOSE($K$4,B53,B54,B55) -> Current Case - Management Case | J56: =CHOOSE($K$4,J53,J54,J55) -> 0.066 | K56: =CHOOSE($K$4,K53,K54,K55) -> 0.066 | L56: =CHOOSE($K$4,L53,L54,L55) -> 0.066 | M56: =CHOOSE($K$4,M53,M54,M55) -> 0.066 | N56: =CHOOSE($K$4,N53,N54,N55) -> 0.066 | O56: =CHOOSE($K$4,O53,O54,O55) -> 0.066 | P56: =CHOOSE($K$4,P53,P54,P55) -> 0.066 | Q56: =CHOOSE($K$4,Q53,Q54,Q55) -> 0.066 | ... S56: =CHOOSE($K$4,S53,S54,S55) -> 0.066
B58: Other Misc SG&A Expenses % Revenue
B59: Management Case | E59: ='Assumptions Working'!E367 -> 0.055244509 | F59: ='Assumptions Working'!F367 -> 0.055161275 | G59: ='Assumptions Working'!G367 -> 0.060322297 | H59: ='Assumptions Working'!H367 -> 0.051193531 | I59: ='Assumptions Working'!I367 -> 0.058908823 | J59: 0.055 | K59: 0.055 | L59: 0.055 | M59: 0.055 | N59: 0.055 | O59: 0.055 | P59: 0.055 | Q59: 0.055 | R59: 0.055 | S59: 0.055
B60: Base Case | E60: =E59 -> 0.055244509 | F60: =F59 -> 0.055161275 | G60: =G59 -> 0.060322297 | H60: =H59 -> 0.051193531 | I60: =I59 -> 0.058908823 | J60: 0.055 | K60: 0.055 | L60: 0.055 | M60: 0.055 | N60: 0.055 | O60: 0.055 | P60: 0.055 | Q60: 0.055 | R60: 0.055 | S60: 0.055
B61: Down Case | E61: =E60 -> 0.055244509 | F61: =F60 -> 0.055161275 | G61: =G60 -> 0.060322297 | H61: =H60 -> 0.051193531 | I61: =I60 -> 0.058908823 | J61: 0.055 | K61: 0.055 | L61: 0.055 | M61: 0.055 | N61: 0.055 | O61: 0.055 | P61: 0.055 | Q61: 0.055 | R61: 0.055 | S61: 0.055
B62: ="Current Case - "&CHOOSE($K$4,B59,B60,B61) -> Current Case - Management Case | J62: =CHOOSE($K$4,J59,J60,J61) -> 0.055 | K62: =CHOOSE($K$4,K59,K60,K61) -> 0.055 | L62: =CHOOSE($K$4,L59,L60,L61) -> 0.055 | M62: =CHOOSE($K$4,M59,M60,M61) -> 0.055 | N62: =CHOOSE($K$4,N59,N60,N61) -> 0.055 | O62: =CHOOSE($K$4,O59,O60,O61) -> 0.055 | P62: =CHOOSE($K$4,P59,P60,P61) -> 0.055 | Q62: =CHOOSE($K$4,Q59,Q60,Q61) -> 0.055 | ... S62: =CHOOSE($K$4,S59,S60,S61) -> 0.055
B64: Total SG&A Expenses % Revenue | E64: =E59+E53+E47+E41 -> 0.22010903 | F64: =F59+F53+F47+F41 -> 0.22487542 | G64: =G59+G53+G47+G41 -> 0.23049298 | H64: =H59+H53+H47+H41 -> 0.22402766 | I64: =I59+I53+I47+I41 -> 0.24642418 | J64: =J59+J53+J47+J41 -> 0.225 | K64: =K59+K53+K47+K41 -> 0.225 | L64: =L59+L53+L47+L41 -> 0.225 | ... S64: =S59+S53+S47+S41 -> 0.225
A66: # | B66: Non Current Asset
B68: Fixed Assets
B70: Right if use Assets Growth %
B71: Management Case | J71: 0 | K71: 0 | L71: 0 | M71: 0 | N71: 0 | O71: 0 | P71: 0 | Q71: 0 | R71: 0 | S71: 0
B72: Best Case | J72: 0 | K72: 0 | L72: 0 | M72: 0 | N72: 0 | O72: 0 | P72: 0 | Q72: 0 | R72: 0 | S72: 0
B73: Down Case | J73: 0 | K73: 0 | L73: 0 | M73: 0 | N73: 0 | O73: 0 | P73: 0 | Q73: 0 | R73: 0 | S73: 0
B74: ="Current Case - "&CHOOSE($K$4,B71,B72,B73) -> Current Case - Management Case | J74: =CHOOSE($K$4,J71,J72,J73) -> 0 | K74: =CHOOSE($K$4,K71,K72,K73) -> 0 | L74: =CHOOSE($K$4,L71,L72,L73) -> 0 | M74: =CHOOSE($K$4,M71,M72,M73) -> 0 | N74: =CHOOSE($K$4,N71,N72,N73) -> 0 | O74: =CHOOSE($K$4,O71,O72,O73) -> 0 | P74: =CHOOSE($K$4,P71,P72,P73) -> 0 | Q74: =CHOOSE($K$4,Q71,Q72,Q73) -> 0 | ... S74: =CHOOSE($K$4,S71,S72,S73) -> 0
B76: Capital Work in progress % Net Fixed Assets
B77: Management Case | J77: 0 | K77: 0 | L77: 0 | M77: 0 | N77: 0 | O77: 0 | P77: 0 | Q77: 0 | R77: 0 | S77: 0
B78: Best Case | J78: 0 | K78: 0 | L78: 0 | M78: 0 | N78: 0 | O78: 0 | P78: 0 | Q78: 0 | R78: 0 | S78: 0
B79: Down Case | J79: 0 | K79: 0 | L79: 0 | M79: 0 | N79: 0 | O79: 0 | P79: 0 | Q79: 0 | R79: 0 | S79: 0
B80: ="Current Case - "&CHOOSE($K$4,B77,B78,B79) -> Current Case - Management Case | J80: =CHOOSE($K$4,J77,J78,J79) -> 0 | K80: =CHOOSE($K$4,K77,K78,K79) -> 0 | L80: =CHOOSE($K$4,L77,L78,L79) -> 0 | M80: =CHOOSE($K$4,M77,M78,M79) -> 0 | N80: =CHOOSE($K$4,N77,N78,N79) -> 0 | O80: =CHOOSE($K$4,O77,O78,O79) -> 0 | P80: =CHOOSE($K$4,P77,P78,P79) -> 0 | Q80: =CHOOSE($K$4,Q77,Q78,Q79) -> 0 | ... S80: =CHOOSE($K$4,S77,S78,S79) -> 0
B82: Intangible Non Current Asset
B84: Intangible Asset (Excluding Goodwill) Growth %
B85: Management Case | J85: 0.032 | K85: 0.031 | L85: 0.02 | M85: 0.02 | N85: 0.02 | O85: 0.02 | P85: 0.02 | Q85: 0.02 | R85: 0.02 | S85: 0.02
B86: Best Case | J86: 0.032 | K86: 0.031 | L86: 0.02 | M86: 0.02 | N86: 0.02 | O86: 0.02 | P86: 0.02 | Q86: 0.02 | R86: 0.02 | S86: 0.02
B87: Down Case | J87: 0.032 | K87: 0.031 | L87: 0.02 | M87: 0.02 | N87: 0.02 | O87: 0.02 | P87: 0.02 | Q87: 0.02 | R87: 0.02 | S87: 0.02
B88: ="Current Case - "&CHOOSE($K$4,B85,B86,B87) -> Current Case - Management Case | J88: =CHOOSE($K$4,J85,J86,J87) -> 0.032 | K88: =CHOOSE($K$4,K85,K86,K87) -> 0.031 | L88: =CHOOSE($K$4,L85,L86,L87) -> 0.02 | M88: =CHOOSE($K$4,M85,M86,M87) -> 0.02 | N88: =CHOOSE($K$4,N85,N86,N87) -> 0.02 | O88: =CHOOSE($K$4,O85,O86,O87) -> 0.02 | P88: =CHOOSE($K$4,P85,P86,P87) -> 0.02 | Q88: =CHOOSE($K$4,Q85,Q86,Q87) -> 0.02 | ... S88: =CHOOSE($K$4,S85,S86,S87) -> 0.02
B90: Goodwill Growth %
B91: Management Case | J91: 0 | K91: 0 | L91: 0 | M91: 0 | N91: 0 | O91: 0 | P91: 0 | Q91: 0 | R91: 0 | S91: 0
B92: Best Case | J92: 0 | K92: 0 | L92: 0 | M92: 0 | N92: 0 | O92: 0 | P92: 0 | Q92: 0 | R92: 0 | S92: 0
B93: Down Case | J93: 0 | K93: 0 | L93: 0 | M93: 0 | N93: 0 | O93: 0 | P93: 0 | Q93: 0 | R93: 0 | S93: 0
B94: ="Current Case - "&CHOOSE($K$4,B91,B92,B93) -> Current Case - Management Case | J94: =CHOOSE($K$4,J91,J92,J93) -> 0 | K94: =CHOOSE($K$4,K91,K92,K93) -> 0 | L94: =CHOOSE($K$4,L91,L92,L93) -> 0 | M94: =CHOOSE($K$4,M91,M92,M93) -> 0 | N94: =CHOOSE($K$4,N91,N92,N93) -> 0 | O94: =CHOOSE($K$4,O91,O92,O93) -> 0 | P94: =CHOOSE($K$4,P91,P92,P93) -> 0 | Q94: =CHOOSE($K$4,Q91,Q92,Q93) -> 0 | ... S94: =CHOOSE($K$4,S91,S92,S93) -> 0
B96: Non-Current Financial Asset Growth %
B97: Management Case | J97: 0 | K97: 0 | L97: 0 | M97: 0 | N97: 0 | O97: 0 | P97: 0 | Q97: 0 | R97: 0 | S97: 0
B98: Best Case | J98: 0 | K98: 0 | L98: 0 | M98: 0 | N98: 0 | O98: 0 | P98: 0 | Q98: 0 | R98: 0 | S98: 0
B99: Down Case | J99: 0 | K99: 0 | L99: 0 | M99: 0 | N99: 0 | O99: 0 | P99: 0 | Q99: 0 | R99: 0 | S99: 0
B100: ="Current Case - "&CHOOSE($K$4,B97,B98,B99) -> Current Case - Management Case | J100: =CHOOSE($K$4,J97,J98,J99) -> 0 | K100: =CHOOSE($K$4,K97,K98,K99) -> 0 | L100: =CHOOSE($K$4,L97,L98,L99) -> 0 | M100: =CHOOSE($K$4,M97,M98,M99) -> 0 | N100: =CHOOSE($K$4,N97,N98,N99) -> 0 | O100: =CHOOSE($K$4,O97,O98,O99) -> 0 | P100: =CHOOSE($K$4,P97,P98,P99) -> 0 | Q100: =CHOOSE($K$4,Q97,Q98,Q99) -> 0 | ... S100: =CHOOSE($K$4,S97,S98,S99) -> 0
B102: Other Non-Current Asset Growth %
B103: Management Case | J103: 0 | K103: 0 | L103: 0 | M103: 0 | N103: 0 | O103: 0 | P103: 0 | Q103: 0 | R103: 0 | S103: 0
B104: Best Case | J104: 0 | K104: 0 | L104: 0 | M104: 0 | N104: 0 | O104: 0 | P104: 0 | Q104: 0 | R104: 0 | S104: 0
B105: Down Case | J105: 0 | K105: 0 | L105: 0 | M105: 0 | N105: 0 | O105: 0 | P105: 0 | Q105: 0 | R105: 0 | S105: 0
B106: ="Current Case - "&CHOOSE($K$4,B103,B104,B105) -> Current Case - Management Case | J106: =CHOOSE($K$4,J103,J104,J105) -> 0 | K106: =CHOOSE($K$4,K103,K104,K105) -> 0 | L106: =CHOOSE($K$4,L103,L104,L105) -> 0 | M106: =CHOOSE($K$4,M103,M104,M105) -> 0 | N106: =CHOOSE($K$4,N103,N104,N105) -> 0 | O106: =CHOOSE($K$4,O103,O104,O105) -> 0 | P106: =CHOOSE($K$4,P103,P104,P105) -> 0 | Q106: =CHOOSE($K$4,Q103,Q104,Q105) -> 0 | ... S106: =CHOOSE($K$4,S103,S104,S105) -> 0
B108: Income Tax Asset Growth %
B109: Management Case | J109: 0 | K109: 0 | L109: 0 | M109: 0 | N109: 0 | O109: 0 | P109: 0 | Q109: 0 | R109: 0 | S109: 0
B110: Best Case | J110: 0 | K110: 0 | L110: 0 | M110: 0 | N110: 0 | O110: 0 | P110: 0 | Q110: 0 | R110: 0 | S110: 0
B111: Down Case | J111: 0 | K111: 0 | L111: 0 | M111: 0 | N111: 0 | O111: 0 | P111: 0 | Q111: 0 | R111: 0 | S111: 0
B112: ="Current Case - "&CHOOSE($K$4,B109,B110,B111) -> Current Case - Management Case | J112: =CHOOSE($K$4,J109,J110,J111) -> 0 | K112: =CHOOSE($K$4,K109,K110,K111) -> 0 | L112: =CHOOSE($K$4,L109,L110,L111) -> 0 | M112: =CHOOSE($K$4,M109,M110,M111) -> 0 | N112: =CHOOSE($K$4,N109,N110,N111) -> 0 | O112: =CHOOSE($K$4,O109,O110,O111) -> 0 | P112: =CHOOSE($K$4,P109,P110,P111) -> 0 | Q112: =CHOOSE($K$4,Q109,Q110,Q111) -> 0 | ... S112: =CHOOSE($K$4,S109,S110,S111) -> 0
B114: Deffered Tax Asset Growth %
B115: Management Case | J115: 0 | K115: 0 | L115: 0 | M115: 0 | N115: 0 | O115: 0 | P115: 0 | Q115: 0 | R115: 0 | S115: 0
B116: Best Case | J116: 0 | K116: 0 | L116: 0 | M116: 0 | N116: 0 | O116: 0 | P116: 0 | Q116: 0 | R116: 0 | S116: 0
B117: Down Case | J117: 0 | K117: 0 | L117: 0 | M117: 0 | N117: 0 | O117: 0 | P117: 0 | Q117: 0 | R117: 0 | S117: 0
B118: ="Current Case - "&CHOOSE($K$4,B115,B116,B117) -> Current Case - Management Case | J118: =CHOOSE($K$4,J115,J116,J117) -> 0 | K118: =CHOOSE($K$4,K115,K116,K117) -> 0 | L118: =CHOOSE($K$4,L115,L116,L117) -> 0 | M118: =CHOOSE($K$4,M115,M116,M117) -> 0 | N118: =CHOOSE($K$4,N115,N116,N117) -> 0 | O118: =CHOOSE($K$4,O115,O116,O117) -> 0 | P118: =CHOOSE($K$4,P115,P116,P117) -> 0 | Q118: =CHOOSE($K$4,Q115,Q116,Q117) -> 0 | ... S118: =CHOOSE($K$4,S115,S116,S117) -> 0
B120: Intangible Asset Under development Growth %
B121: Management Case | J121: 0 | K121: 0 | L121: 0 | M121: 0 | N121: 0 | O121: 0 | P121: 0 | Q121: 0 | R121: 0 | S121: 0
B122: Best Case | J122: 0 | K122: 0 | L122: 0 | M122: 0 | N122: 0 | O122: 0 | P122: 0 | Q122: 0 | R122: 0 | S122: 0
B123: Down Case | J123: 0 | K123: 0 | L123: 0 | M123: 0 | N123: 0 | O123: 0 | P123: 0 | Q123: 0 | R123: 0 | S123: 0
B124: ="Current Case - "&CHOOSE($K$4,B121,B122,B123) -> Current Case - Management Case | J124: =CHOOSE($K$4,J121,J122,J123) -> 0 | K124: =CHOOSE($K$4,K121,K122,K123) -> 0 | L124: =CHOOSE($K$4,L121,L122,L123) -> 0 | M124: =CHOOSE($K$4,M121,M122,M123) -> 0 | N124: =CHOOSE($K$4,N121,N122,N123) -> 0 | O124: =CHOOSE($K$4,O121,O122,O123) -> 0 | P124: =CHOOSE($K$4,P121,P122,P123) -> 0 | Q124: =CHOOSE($K$4,Q121,Q122,Q123) -> 0 | ... S124: =CHOOSE($K$4,S121,S122,S123) -> 0
B126: Investments in associates Growth %
B127: Management Case | J127: 0 | K127: 0 | L127: 0 | M127: 0 | N127: 0 | O127: 0 | P127: 0 | Q127: 0 | R127: 0 | S127: 0
B128: Best Case | J128: 0 | K128: 0 | L128: 0 | M128: 0 | N128: 0 | O128: 0 | P128: 0 | Q128: 0 | R128: 0 | S128: 0
B129: Down Case | J129: 0 | K129: 0 | L129: 0 | M129: 0 | N129: 0 | O129: 0 | P129: 0 | Q129: 0 | R129: 0 | S129: 0
B130: ="Current Case - "&CHOOSE($K$4,B127,B128,B129) -> Current Case - Management Case | J130: =CHOOSE($K$4,J127,J128,J129) -> 0 | K130: =CHOOSE($K$4,K127,K128,K129) -> 0 | L130: =CHOOSE($K$4,L127,L128,L129) -> 0 | M130: =CHOOSE($K$4,M127,M128,M129) -> 0 | N130: =CHOOSE($K$4,N127,N128,N129) -> 0 | O130: =CHOOSE($K$4,O127,O128,O129) -> 0 | P130: =CHOOSE($K$4,P127,P128,P129) -> 0 | Q130: =CHOOSE($K$4,Q127,Q128,Q129) -> 0 | ... S130: =CHOOSE($K$4,S127,S128,S129) -> 0
...

Sheet Schedules
B2: ='Input Sheet'!C5 -> Mankind Pharma Ltd
B3: Schedules
I4: Current Case | K4: 1
E8: Actual | J8: Explicit Forecast Period | O8: Maturity Period
B9: In INR Crores unless stated otherwise | E9: ='ControlSheet '!E9 -> 2021 | F9: ='ControlSheet '!F9 -> 2022 | G9: ='ControlSheet '!G9 -> 2023 | H9: ='ControlSheet '!H9 -> 2024 | I9: ='ControlSheet '!I9 -> 2025 | J9: ='ControlSheet '!J9 -> 2026 | K9: ='ControlSheet '!K9 -> 2027 | L9: ='ControlSheet '!L9 -> 2028 | ... S9: ='ControlSheet '!S9 -> 2035
A11: # | B11: Revenue Schedules
B13: Revenue | E13: ='Income Stmt'!E7 -> 6223.8982 | F13: ='Income Stmt'!F7 -> 7781.5551 | G13: ='Income Stmt'!G7 -> 8749.433 | H13: ='Income Stmt'!H7 -> 10334.775 | I13: ='Income Stmt'!I7 -> 12207 | J13: =I13*(1+J15) -> 14404.26 | K13: =J13*(1+K15) -> 16780.963 | L13: =K13*(1+L15) -> 19298.107 | M13: =L13*(1+M15) -> 21903.352 | N13: =M13*(1+N15) -> 24531.754 | O13: =N13*(1+O15) -> 27475.565 | P13: =O13*(1+P15) -> 30772.632 | Q13: =P13*(1+Q15) -> 34465.348 | ... S13: =R13*(1+S15) -> 43233.333
B15: Growth YoY% | F15: =F13/E13-1 -> 0.2502703 | G15: =G13/F13-1 -> 0.12438104 | H15: =H13/G13-1 -> 0.18119364 | I15: =I13/H13-1 -> 0.18115784 | J15: ='ControlSheet '!J19 -> 0.18 | K15: ='ControlSheet '!K19 -> 0.165 | L15: ='ControlSheet '!L19 -> 0.15 | M15: ='ControlSheet '!M19 -> 0.135 | N15: ='ControlSheet '!N19 -> 0.12 | O15: ='ControlSheet '!O19 -> 0.12 | P15: ='ControlSheet '!P19 -> 0.12 | Q15: ='ControlSheet '!Q19 -> 0.12 | ... S15: ='ControlSheet '!S19 -> 0.12
A17: # | B17: COGS Schedules
B20: COGS | E20: ='Income Stmt'!E18*-1 -> 1780.6092 | F20: ='Income Stmt'!F18*-1 -> 2421.7284 | G20: ='Income Stmt'!G18*-1 -> 2913.642 | H20: ='Income Stmt'!H18*-1 -> 3209.6959 | I20: ='Income Stmt'!I18*-1 -> 3855.04 | J20: =J13*J22 -> 4897.4484 | K20: =K13*K22 -> 5604.8416 | L20: =L13*L22 -> 6329.7792 | M20: =M13*M22 -> 7052.8793 | N20: =N13*N22 -> 7752.0343 | O20: =O13*O22 -> 8682.2784 | P20: =P13*P22 -> 9724.1518 | Q20: =Q13*Q22 -> 10891.05 | ... S20: =S13*S22 -> 13661.733
B22: COGS % Sales | E22: =E20/E13 -> 0.28609228 | F22: =F20/F13 -> 0.31121394 | G22: =G20/G13 -> 0.33300924 | H22: =H20/H13 -> 0.31057241 | I22: =I20/I13 -> 0.31580569 | J22: ='ControlSheet '!J29 -> 0.34 | K22: ='ControlSheet '!K29 -> 0.334 | L22: ='ControlSheet '!L29 -> 0.328 | M22: ='ControlSheet '!M29 -> 0.322 | N22: ='ControlSheet '!N29 -> 0.316 | O22: ='ControlSheet '!O29 -> 0.316 | P22: ='ControlSheet '!P29 -> 0.316 | Q22: ='ControlSheet '!Q29 -> 0.316 | ... S22: ='ControlSheet '!S29 -> 0.316
A24: # | B24: SG&A (Excluding Depreciation & Interest Expenses) Schedule
B26: Employee Benefit Expense
B28: =B26 -> Employee Benefit Expense | E28: ='Assumptions Working'!E354 -> 1415.76 | F28: ='Assumptions Working'!F354 -> 1620.58 | G28: ='Assumptions Working'!G354 -> 1918.45 | H28: ='Assumptions Working'!H354 -> 2274.7 | I28: ='Assumptions Working'!I354 -> 2692 | J28: =J$13*J29 -> 3168.9372 | K28: =K$13*K29 -> 3691.8118 | L28: =L$13*L29 -> 4245.5836 | M28: =M$13*M29 -> 4818.7374 | N28: =N$13*N29 -> 5396.9859 | O28: =O$13*O29 -> 6044.6242 | P28: =P$13*P29 -> 6769.9791 | Q28: =Q$13*Q29 -> 7582.3766 | ... S28: =S$13*S29 -> 9511.3332
B29: =B28&" % Revenue" -> Employee Benefit Expense % Revenue | E29: ='Assumptions Working'!E355 -> 0.22747159 | F29: ='Assumptions Working'!F355 -> 0.20825914 | G29: ='Assumptions Working'!G355 -> 0.21926564 | H29: ='Assumptions Working'!H355 -> 0.22010156 | I29: ='Assumptions Working'!I355 -> 0.2205292 | J29: ='ControlSheet '!J38 -> 0.22 | K29: ='ControlSheet '!K38 -> 0.22 | L29: ='ControlSheet '!L38 -> 0.22 | M29: ='ControlSheet '!M38 -> 0.22 | N29: ='ControlSheet '!N38 -> 0.22 | O29: ='ControlSheet '!O38 -> 0.22 | P29: ='ControlSheet '!P38 -> 0.22 | Q29: ='ControlSheet '!Q38 -> 0.22 | ... S29: ='ControlSheet '!S38 -> 0.22
B31: Advertising & Sales Promotion Expense
B33: =B31 -> Advertising & Sales Promotion Expense | E33: ='Assumptions Working'!E357 -> 385.74 | F33: ='Assumptions Working'!F357 -> 451.56 | G33: ='Assumptions Working'!G357 -> 373.6656 | H33: ='Assumptions Working'!H357 -> 603.8922 | I33: ='Assumptions Working'!I357 -> 755 | J33: =J$13*J34 -> 835.44708 | K33: =K$13*K34 -> 973.29585 | L33: =L$13*L34 -> 1119.2902 | M33: =M$13*M34 -> 1270.3944 | N33: =N$13*N34 -> 1422.8417 | O33: =O$13*O34 -> 1593.5827 | P33: =P$13*P34 -> 1784.8127 | Q33: =Q$13*Q34 -> 1998.9902 | ... S33: =S$13*S34 -> 2507.5333
B34: =B33&" % Revenue" -> Advertising & Sales Promotion Expense % Revenue | E34: ='Assumptions Working'!E358 -> 0.061977235 | F34: ='Assumptions Working'!F358 -> 0.058029532 | G34: ='Assumptions Working'!G358 -> 0.042707407 | H34: ='Assumptions Working'!H358 -> 0.058433031 | I34: ='Assumptions Working'!I358 -> 0.061849758 | J34: ='ControlSheet '!J44 -> 0.058 | K34: ='ControlSheet '!K44 -> 0.058 | L34: ='ControlSheet '!L44 -> 0.058 | M34: ='ControlSheet '!M44 -> 0.058 | N34: ='ControlSheet '!N44 -> 0.058 | O34: ='ControlSheet '!O44 -> 0.058 | P34: ='ControlSheet '!P44 -> 0.058 | Q34: ='ControlSheet '!Q44 -> 0.058 | ... S34: ='ControlSheet '!S44 -> 0.058
B36: Travelling and conveyance Expense
B38: =B36 -> Travelling and conveyance Expense | E38: ='Assumptions Working'!E360 -> 270.4 | F38: ='Assumptions Working'!F360 -> 358.11 | G38: ='Assumptions Working'!G360 -> 496.0469 | H38: ='Assumptions Working'!H360 -> 378.4002 | I38: ='Assumptions Working'!I360 -> 461 | J38: =J$13*J39 -> 662.59596 | K38: =K$13*K39 -> 771.92429 | L38: =L$13*L39 -> 887.71294 | M38: =M$13*M39 -> 1007.5542 | N38: =N$13*N39 -> 1128.4607 | O38: =O$13*O39 -> 1263.876 | P38: =P$13*P39 -> 1415.5411 | Q38: =Q$13*Q39 -> 1585.406 | ... S38: =S$13*S39 -> 1988.7333
B39: =B38&" % Revenue" -> Travelling and conveyance Expense % Revenue | E39: ='Assumptions Working'!E361 -> 0.043445441 | F39: ='Assumptions Working'!F361 -> 0.046020364 | G39: ='Assumptions Working'!G361 -> 0.056694748 | H39: ='Assumptions Working'!H361 -> 0.036614267 | I39: ='Assumptions Working'!I361 -> 0.037765217 | J39: ='ControlSheet '!J50 -> 0.046 | K39: ='ControlSheet '!K50 -> 0.046 | L39: ='ControlSheet '!L50 -> 0.046 | M39: ='ControlSheet '!M50 -> 0.046 | N39: ='ControlSheet '!N50 -> 0.046 | O39: ='ControlSheet '!O50 -> 0.046 | P39: ='ControlSheet '!P50 -> 0.046 | Q39: ='ControlSheet '!Q50 -> 0.046 | ... S39: ='ControlSheet '!S50 -> 0.046
B41: Other Operating Expense
B43: =B41 -> Other Operating Expense | E43: ='Assumptions Working'!E363 -> 369.96 | F43: ='Assumptions Working'!F363 -> 510.97 | G43: ='Assumptions Working'!G363 -> 619.1845 | H43: ='Assumptions Working'!H363 -> 803.9094 | I43: ='Assumptions Working'!I363 -> 1073 | J43: =J$13*J44 -> 950.68116 | K43: =K$13*K44 -> 1107.5436 | L43: =L$13*L44 -> 1273.6751 | M43: =M$13*M44 -> 1445.6212 | N43: =N$13*N44 -> 1619.0958 | O43: =O$13*O44 -> 1813.3873 | P43: =P$13*P44 -> 2030.9937 | Q43: =Q$13*Q44 -> 2274.713 | ... S43: =S$13*S44 -> 2853.4
B44: =B43&" % Revenue" -> Other Operating Expense % Revenue | E44: ='Assumptions Working'!E364 -> 0.059441846 | F44: ='Assumptions Working'!F364 -> 0.065664253 | G44: ='Assumptions Working'!G364 -> 0.070768529 | H44: ='Assumptions Working'!H364 -> 0.077786834 | I44: ='Assumptions Working'!I364 -> 0.087900385 | J44: ='ControlSheet '!J56 -> 0.066 | K44: ='ControlSheet '!K56 -> 0.066 | L44: ='ControlSheet '!L56 -> 0.066 | M44: ='ControlSheet '!M56 -> 0.066 | N44: ='ControlSheet '!N56 -> 0.066 | O44: ='ControlSheet '!O56 -> 0.066 | P44: ='ControlSheet '!P56 -> 0.066 | Q44: ='ControlSheet '!Q56 -> 0.066 | ... S44: ='ControlSheet '!S56 -> 0.066
B46: Other Misc SG&A Expenses
B48: =B46 -> Other Misc SG&A Expenses | E48: ='Assumptions Working'!E366 -> 343.8362 | F48: ='Assumptions Working'!F366 -> 429.2405 | G48: ='Assumptions Working'!G366 -> 527.7859 | H48: ='Assumptions Working'!H366 -> 529.0736 | I48: ='Assumptions Working'!I366 -> 719.1 | J48: =J$13*J49 -> 792.2343 | K48: =K$13*K49 -> 922.95296 | L48: =L$13*L49 -> 1061.3959 | M48: =M$13*M49 -> 1204.6844 | N48: =N$13*N49 -> 1349.2465 | O48: =O$13*O49 -> 1511.156 | P48: =P$13*P49 -> 1692.4948 | Q48: =Q$13*Q49 -> 1895.5941 | ... S48: =S$13*S49 -> 2377.8333
B49: =B48&" % Revenue" -> Other Misc SG&A Expenses % Revenue | E49: ='Assumptions Working'!E367 -> 0.055244509 | F49: ='Assumptions Working'!F367 -> 0.055161275 | G49: ='Assumptions Working'!G367 -> 0.060322297 | H49: ='Assumptions Working'!H367 -> 0.051193531 | I49: ='Assumptions Working'!I367 -> 0.058908823 | J49: ='ControlSheet '!J62 -> 0.055 | K49: ='ControlSheet '!K62 -> 0.055 | L49: ='ControlSheet '!L62 -> 0.055 | M49: ='ControlSheet '!M62 -> 0.055 | N49: ='ControlSheet '!N62 -> 0.055 | O49: ='ControlSheet '!O62 -> 0.055 | P49: ='ControlSheet '!P62 -> 0.055 | Q49: ='ControlSheet '!Q62 -> 0.055 | ... S49: ='ControlSheet '!S62 -> 0.055
B50: ="Total " &B46 -> Total Other Misc SG&A Expenses | J50: =SUM(J48:J49) -> 792.2893 | K50: =SUM(K48:K49) -> 923.00796 | L50: =SUM(L48:L49) -> 1061.4509 | M50: =SUM(M48:M49) -> 1204.7394 | N50: =SUM(N48:N49) -> 1349.3015 | O50: =SUM(O48:O49) -> 1511.211 | P50: =SUM(P48:P49) -> 1692.5498 | Q50: =SUM(Q48:Q49) -> 1895.6491 | ... S50: =SUM(S48:S49) -> 2377.8883
B52: Total SG&A ( Excluding Depreciation & Interest Expense) | E52: =E48+E43+E38+E33+E28 -> 2785.6962 | F52: =F48+F43+F38+F33+F28 -> 3370.4605 | G52: =G48+G43+G38+G33+G28 -> 3935.1329 | H52: =H48+H43+H38+H33+H28 -> 4589.9754 | I52: =I48+I43+I38+I33+I28 -> 5700.1 | J52: =J48+J43+J38+J33+J28 -> 6409.8957 | K52: =K48+K43+K38+K33+K28 -> 7467.5285 | L52: =L48+L43+L38+L33+L28 -> 8587.6578 | ... S52: =S48+S43+S38+S33+S28 -> 19238.833
B53: Total SG&A % Sales | E53: =E52/E13 -> 0.44758062 | F53: =F52/F13 -> 0.43313457 | G53: =G52/G13 -> 0.44975862 | H53: =H52/H13 -> 0.44412922 | I53: =I52/I13 -> 0.46695339 | J53: =J52/J13 -> 0.445 | K53: =K52/K13 -> 0.445 | L53: =L52/L13 -> 0.445 | ... S53: =S52/S13 -> 0.445
A55: # | B55: Non Current Asset Schedule
B57: Property , Plants & Equipments
B59: Opening PP&E | J59: ='Balance Sheet'!I7 -> 2740.6305 | K59: =J62 -> 3216.7203 | L59: =K62 -> 3712.1631 | M59: =L62 -> 4363.6545 | N59: =M62 -> 4987.4966 | O59: =N62 -> 5559.1252 | P59: =O62 -> 6179.3793 | Q59: =P62 -> 6854.0939 | R59: =Q62 -> 7589.8042 | S59: =R62 -> 8393.8298
B60: Add: Capex During the Year | J60: ='Assumptions Working'!C685 -> 652.91502 | K60: ='Assumptions Working'!D685 -> 717.086 | L60: =(L13-K13)*'Assumptions Working'!E686 -> 931.34344 | M60: =(M13-L13)*'Assumptions Working'!F686 -> 963.94046 | N60: =(N13-M13)*'Assumptions Working'!G686 -> 972.50882 | O60: =(O13-N13)*'Assumptions Working'!$G$686 -> 1089.2099 | P60: =(P13-O13)*'Assumptions Working'!$G$686 -> 1219.9151 | Q60: =(Q13-P13)*'Assumptions Working'!$G$686 -> 1366.3049 | R60: =(R13-Q13)*'Assumptions Working'!$G$686 -> 1530.2615 | S60: =(S13-R13)*'Assumptions Working'!$G$686 -> 1713.8928
B61: Less: Depreciation | I61: =('Income Stmt'!I37*-1)/(SUM('Balance Sheet'!I7,'Balance Sheet'!I9,'Balance Sheet'!I11))*'Balance Sheet'!I7 -> 136.01806 | J61: =I61+(J60/$C$117) -> 176.82525 | K61: =J61+(K60/$C$117) -> 221.64313 | L61: =K61+(L60/$C$117) -> 279.85209 | M61: =L61+(M60/$C$117) -> 340.09837 | N61: =M61+(N60/$C$117) -> 400.88017 | O61: =N61+(O60/$C$117) -> 468.95579 | P61: =O61+(P60/$C$117) -> 545.20048 | Q61: =P61+(Q60/$C$117) -> 630.59454 | ... S61: =R61+(S60/$C$117) -> 833.35418
B62: Closing PP&E | I62: 2741 | J62: =J59+J60-J61 -> 3216.7203 | K62: =K59+K60-K61 -> 3712.1631 | L62: =L59+L60-L61 -> 4363.6545 | M62: =M59+M60-M61 -> 4987.4966 | N62: =N59+N60-N61 -> 5559.1252 | O62: =O59+O60-O61 -> 6179.3793 | P62: =P59+P60-P61 -> 6854.0939 | Q62: =Q59+Q60-Q61 -> 7589.8042 | ... S62: =S59+S60-S61 -> 9274.3685
B63: YoY Growth % | J63: =J62/I62-1 -> 0.17355719 | K63: =K62/J62-1 -> 0.15402112 | L63: =L62/K62-1 -> 0.17550181 | M63: =M62/L62-1 -> 0.14296322 | N63: =N62/M62-1 -> 0.11461234 | O63: =O62/N62-1 -> 0.11157405 | P63: =P62/O62-1 -> 0.10918808 | Q63: =Q62/P62-1 -> 0.10733882 | ... S63: =S62/R62-1 -> 0.10490309
B65: Right of Use Asset
B66: =B65 -> Right of Use Asset | E66: ='Balance Sheet'!E9 -> 0 | F66: ='Balance Sheet'!F9 -> 67.3571 | G66: ='Balance Sheet'!G9 -> 114.3647 | H66: ='Balance Sheet'!H9 -> 119.0613 | I66: ='Balance Sheet'!I9 -> 167.25 | J66: =I66*(1+J72) -> 167.25 | K66: =J69 -> 158.94935 | L66: =K69 -> 150.6487 | M66: =L69 -> 142.34804 | N66: =M69 -> 134.04739 | O66: =N69 -> 125.74674 | P66: =O69 -> 117.44609 | Q66: =P69 -> 109.14543 | R66: =Q69 -> 100.84478 | S66: =R69 -> 92.544128
B67: Addition During the Year | J67: =I66*(J72) -> 0 | K67: =J66*(K72) -> 0 | L67: =K66*(L72) -> 0 | M67: =L66*(M72) -> 0 | N67: =M66*(N72) -> 0 | O67: =N66*(O72) -> 0 | P67: =O66*(P72) -> 0 | Q67: =P66*(Q72) -> 0 | ... S67: =R66*(S72) -> 0
B68: Less: Depreciation | I68: =('Income Stmt'!I37*-1)/(SUM('Balance Sheet'!I7,'Balance Sheet'!I9,'Balance Sheet'!I11))*'Balance Sheet'!I9 -> 8.3006525 | J68: =I68+J67/$C$117 -> 8.3006525 | K68: =J68+K67/$C$117 -> 8.3006525 | L68: =K68+L67/$C$117 -> 8.3006525 | M68: =L68+M67/$C$117 -> 8.3006525 | N68: =M68+N67/$C$117 -> 8.3006525 | O68: =N68+O67/$C$117 -> 8.3006525 | P68: =O68+P67/$C$117 -> 8.3006525 | Q68: =P68+Q67/$C$117 -> 8.3006525 | ... S68: =R68+S67/$C$117 -> 8.3006525
B69: Closing PP&E | J69: =J66+J67-J68 -> 158.94935 | K69: =K66+K67-K68 -> 150.6487 | L69: =L66+L67-L68 -> 142.34804 | M69: =M66+M67-M68 -> 134.04739 | N69: =N66+N67-N68 -> 125.74674 | O69: =O66+O67-O68 -> 117.44609 | P69: =P66+P67-P68 -> 109.14543 | Q69: =Q66+Q67-Q68 -> 100.84478 | ... S69: =S66+S67-S68 -> 84.243475
B70: YoY Growth % | J70: ='ControlSheet '!J74 -> 0 | K70: =K69/J69-1 -> -0.052221998 | L70: =L69/K69-1 -> -0.055099398 | M70: =M69/L69-1 -> -0.058312375 | N70: =N69/M69-1 -> -0.061923268 | O70: =O69/N69-1 -> -0.066010877 | P70: =P69/O69-1 -> -0.07067628 | Q70: =Q69/P69-1 -> -0.076051304 | R70: =R69/Q69-1 -> -0.082311176 | S70: =S69/R69-1 -> -0.089693994
B72: YoY Growth % | G72: =G66/F66-1 -> 0.69788634 | H72: =H66/G66-1 -> 0.041066868 | I72: =I66/H66-1 -> 0.40473857 | J72: ='ControlSheet '!J74 -> 0 | K72: ='ControlSheet '!K74 -> 0 | L72: ='ControlSheet '!L74 -> 0 | M72: ='ControlSheet '!M74 -> 0 | N72: ='ControlSheet '!N74 -> 0 | O72: ='ControlSheet '!O74 -> 0 | P72: ='ControlSheet '!P74 -> 0 | Q72: ='ControlSheet '!Q74 -> 0 | ... S72: ='ControlSheet '!S74 -> 0
B74: Capital Work in Progress
B75: =B74 -> Capital Work in Progress | E75: ='Balance Sheet'!E8 -> 371.6162 | F75: ='Balance Sheet'!F8 -> 669.8734 | G75: ='Balance Sheet'!G8 -> 493.192 | H75: ='Balance Sheet'!H8 -> 207.0939 | I75: ='Balance Sheet'!I8 -> 306.13 | J75: 0 | K75: 0 | L75: 0 | M75: 0 | N75: 0 | O75: 0 | P75: 0 | Q75: 0 | R75: 0 | S75: 0
B76: YoY Growth % | J76: ='ControlSheet '!J80 -> 0 | K76: ='ControlSheet '!K80 -> 0 | L76: ='ControlSheet '!L80 -> 0 | M76: ='ControlSheet '!M80 -> 0 | N76: ='ControlSheet '!N80 -> 0 | O76: ='ControlSheet '!O80 -> 0 | P76: ='ControlSheet '!P80 -> 0 | Q76: ='ControlSheet '!Q80 -> 0 | ... S76: ='ControlSheet '!S80 -> 0
B78: Intangible Assets (Excluding Goodwill)
B79: =B78 -> Intangible Assets (Excluding Goodwill) | E79: ='Balance Sheet'!E11 -> 18.4286 | F79: ='Balance Sheet'!F11 -> 1842.6152 | G79: ='Balance Sheet'!G11 -> 1701.4633 | H79: ='Balance Sheet'!H11 -> 1588.3397 | I79: ='Balance Sheet'!I11 -> 9604.66 | J79: =I79 -> 9604.66 | K79: =J82 -> 9127.9787 | L79: =K82 -> 8651.2974 | M79: =L82 -> 8174.6162 | N79: =M82 -> 7697.9349 | O79: =N82 -> 7221.2536 | P79: =O82 -> 6744.5723 | Q79: =P82 -> 6267.891 | R79: =Q82 -> 5791.2097 | S79: =R82 -> 5314.5285
B80: Addition During the Year | J80: 0 | K80: =J80 -> 0 | L80: =K80 -> 0 | M80: =L80 -> 0 | N80: =M80 -> 0 | O80: =N80 -> 0 | P80: =O80 -> 0 | Q80: =P80 -> 0 | R80: =Q80 -> 0 | S80: =R80 -> 0
B81: Less: Depreciation | I81: =('Income Stmt'!I37*-1)/(SUM('Balance Sheet'!I7,'Balance Sheet'!I9,'Balance Sheet'!I11))*'Balance Sheet'!I11 -> 476.68128 | J81: =I81+(J80/$C$117) -> 476.68128 | K81: =J81+(K80/$C$117) -> 476.68128 | L81: =K81+(L80/$C$117) -> 476.68128 | M81: =L81+(M80/$C$117) -> 476.68128 | N81: =M81+(N80/$C$117) -> 476.68128 | O81: =N81+(O80/$C$117) -> 476.68128 | P81: =O81+(P80/$C$117) -> 476.68128 | Q81: =P81+(Q80/$C$117) -> 476.68128 | ... S81: =R81+(S80/$C$117) -> 476.68128
B82: Closing Intangible Assets | J82: =J79+J80-J81 -> 9127.9787 | K82: =K79+K80-K81 -> 8651.2974 | L82: =L79+L80-L81 -> 8174.6162 | M82: =M79+M80-M81 -> 7697.9349 | N82: =N79+N80-N81 -> 7221.2536 | O82: =O79+O80-O81 -> 6744.5723 | P82: =P79+P80-P81 -> 6267.891 | Q82: =Q79+Q80-Q81 -> 5791.2097 | ... S82: =S79+S80-S81 -> 4837.8472
B83: YoY Growth % | J83: ='ControlSheet '!J88 -> 0.032 | K83: ='ControlSheet '!K88 -> 0.031 | L83: ='ControlSheet '!L88 -> 0.02 | M83: ='ControlSheet '!M88 -> 0.02 | N83: ='ControlSheet '!N88 -> 0.02 | O83: ='ControlSheet '!O88 -> 0.02 | P83: ='ControlSheet '!P88 -> 0.02 | Q83: ='ControlSheet '!Q88 -> 0.02 | ... S83: ='ControlSheet '!S88 -> 0.02
B85: YoY Growth % | F85: =F79/E79-1 -> 98.986716 | G85: =G79/F79-1 -> -0.076604111 | H85: =H79/G79-1 -> -0.066486065 | I85: =I79/H79-1 -> 5.046981 | J85: ='ControlSheet '!J88 -> 0.032 | K85: ='ControlSheet '!K88 -> 0.031 | L85: ='ControlSheet '!L88 -> 0.02 | M85: ='ControlSheet '!M88 -> 0.02 | N85: ='ControlSheet '!N88 -> 0.02 | O85: ='ControlSheet '!O88 -> 0.02 | P85: ='ControlSheet '!P88 -> 0.02 | Q85: ='ControlSheet '!Q88 -> 0.02 | ... S85: ='ControlSheet '!S88 -> 0.02
B87: Goodwill
B88: =B87 -> Goodwill | E88: ='Balance Sheet'!E10 -> 20.4422 | F88: ='Balance Sheet'!F10 -> 20.4422 | G88: ='Balance Sheet'!G10 -> 20.0225 | H88: ='Balance Sheet'!H10 -> 20.0225 | I88: ='Balance Sheet'!I10 -> 6492 | J88: =I88*(1+J89) -> 6492 | K88: =J88*(1+K89) -> 6492 | L88: =K88*(1+L89) -> 6492 | M88: =L88*(1+M89) -> 6492 | N88: =M88*(1+N89) -> 6492 | O88: =N88*(1+O89) -> 6492 | P88: =O88*(1+P89) -> 6492 | Q88: =P88*(1+Q89) -> 6492 | ... S88: =R88*(1+S89) -> 6492
B89: YoY Growth % | F89: =F88/E88-1 -> 0 | G89: =G88/F88-1 -> -0.020531058 | H89: =H88/G88-1 -> 0 | I89: =I88/H88-1 -> 323.23524 | J89: ='ControlSheet '!J94 -> 0 | K89: ='ControlSheet '!K94 -> 0 | L89: ='ControlSheet '!L94 -> 0 | M89: ='ControlSheet '!M94 -> 0 | N89: ='ControlSheet '!N94 -> 0 | O89: ='ControlSheet '!O94 -> 0 | P89: ='ControlSheet '!P94 -> 0 | Q89: ='ControlSheet '!Q94 -> 0 | ... S89: ='ControlSheet '!S94 -> 0
B91: Non Current Financial Asset
B92: =B91 -> Non Current Financial Asset | E92: ='Balance Sheet'!E15 -> 68.019 | F92: ='Balance Sheet'!F15 -> 95.6446 | G92: ='Balance Sheet'!G15 -> 205.0883 | H92: ='Balance Sheet'!H15 -> 155.3354 | I92: ='Balance Sheet'!I15 -> 360.57 | J92: =I92*(1+J93) -> 360.57 | K92: =J92*(1+K93) -> 360.57 | L92: =K92*(1+L93) -> 360.57 | M92: =L92*(1+M93) -> 360.57 | N92: =M92*(1+N93) -> 360.57 | O92: =N92*(1+O93) -> 360.57 | P92: =O92*(1+P93) -> 360.57 | Q92: =P92*(1+Q93) -> 360.57 | ... S92: =R92*(1+S93) -> 360.57
B93: YoY Growth % | F93: =F92/E92-1 -> 0.40614534 | G93: =G92/F92-1 -> 1.1442747 | H93: =H92/G92-1 -> -0.24259258 | I93: =I92/H92-1 -> 1.3212352 | J93: ='ControlSheet '!J100 -> 0 | K93: ='ControlSheet '!K100 -> 0 | L93: ='ControlSheet '!L100 -> 0 | M93: ='ControlSheet '!M100 -> 0 | N93: ='ControlSheet '!N100 -> 0 | O93: ='ControlSheet '!O100 -> 0 | P93: ='ControlSheet '!P100 -> 0 | Q93: ='ControlSheet '!Q100 -> 0 | ... S93: ='ControlSheet '!S100 -> 0
B95: Other Non Current Asset
B96: =B95 -> Other Non Current Asset | E96: ='Balance Sheet'!E20 -> 96.6766 | F96: ='Balance Sheet'!F20 -> 74.1843 | G96: ='Balance Sheet'!G20 -> 73.355 | H96: ='Balance Sheet'!H20 -> 66.2811 | I96: ='Balance Sheet'!I20 -> 92.26 | J96: =I96*(1+J97) -> 92.26 | K96: =J96*(1+K97) -> 92.26 | L96: =K96*(1+L97) -> 92.26 | M96: =L96*(1+M97) -> 92.26 | N96: =M96*(1+N97) -> 92.26 | O96: =N96*(1+O97) -> 92.26 | P96: =O96*(1+P97) -> 92.26 | Q96: =P96*(1+Q97) -> 92.26 | ... S96: =R96*(1+S97) -> 92.26
B97: % Revenue | E97: =E96/E13 -> 0.015533127 | F97: =F96/F13 -> 0.0095333515 | G97: =G96/G13 -> 0.0083839719 | H97: =H96/H13 -> 0.0064134055 | I97: =I96/I13 -> 0.0075579585 | J97: ='ControlSheet '!J106 -> 0 | K97: ='ControlSheet '!K106 -> 0 | L97: ='ControlSheet '!L106 -> 0 | M97: ='ControlSheet '!M106 -> 0 | N97: ='ControlSheet '!N106 -> 0 | O97: ='ControlSheet '!O106 -> 0 | P97: ='ControlSheet '!P106 -> 0 | Q97: ='ControlSheet '!Q106 -> 0 | ... S97: ='ControlSheet '!S106 -> 0
B99: Income Tax Asset
B100: =B99 -> Income Tax Asset | E100: ='Balance Sheet'!E21 -> 55.6056 | F100: ='Balance Sheet'!F21 -> 79.8242 | G100: ='Balance Sheet'!G21 -> 102.5153 | H100: ='Balance Sheet'!H21 -> 81.9839 | I100: ='Balance Sheet'!I21 -> 189.49 | J100: =I100*(1+J101) -> 189.49 | K100: =J100*(1+K101) -> 189.49 | L100: =K100*(1+L101) -> 189.49 | M100: =L100*(1+M101) -> 189.49 | N100: =M100*(1+N101) -> 189.49 | O100: =N100*(1+O101) -> 189.49 | P100: =O100*(1+P101) -> 189.49 | Q100: =P100*(1+Q101) -> 189.49 | ... S100: =R100*(1+S101) -> 189.49
B101: YoY Growth % | F101: =F100/E100-1 -> 0.43554246 | G101: =G100/F100-1 -> 0.28426342 | H101: =H100/G100-1 -> -0.20027645 | I101: =I100/H100-1 -> 1.3113075 | J101: ='ControlSheet '!J112 -> 0 | K101: ='ControlSheet '!K112 -> 0 | L101: ='ControlSheet '!L112 -> 0 | M101: ='ControlSheet '!M112 -> 0 | N101: ='ControlSheet '!N112 -> 0 | O101: ='ControlSheet '!O112 -> 0 | P101: ='ControlSheet '!P112 -> 0 | Q101: ='ControlSheet '!Q112 -> 0 | ... S101: ='ControlSheet '!S112 -> 0
B103: Deferred Tax Asset
B104: =B103 -> Deferred Tax Asset | E104: ='Balance Sheet'!E22 -> 49.011 | F104: ='Balance Sheet'!F22 -> 39.2862 | G104: ='Balance Sheet'!G22 -> 29.7769 | H104: ='Balance Sheet'!H22 -> 80.3975 | I104: ='Balance Sheet'!I22 -> 107.89 | J104: =I104*(1+J105) -> 107.89 | K104: =J104*(1+K105) -> 107.89 | L104: =K104*(1+L105) -> 107.89 | M104: =L104*(1+M105) -> 107.89 | N104: =M104*(1+N105) -> 107.89 | O104: =N104*(1+O105) -> 107.89 | P104: =O104*(1+P105) -> 107.89 | Q104: =P104*(1+Q105) -> 107.89 | ... S104: =R104*(1+S105) -> 107.89
B105: YoY Growth % | F105: =F104/E104-1 -> -0.19842076 | G105: =G104/F104-1 -> -0.24205192 | H105: =H104/G104-1 -> 1.6999956 | I105: =I104/H104-1 -> 0.34195715 | J105: ='ControlSheet '!J118 -> 0 | K105: ='ControlSheet '!K118 -> 0 | L105: ='ControlSheet '!L118 -> 0 | M105: ='ControlSheet '!M118 -> 0 | N105: ='ControlSheet '!N118 -> 0 | O105: ='ControlSheet '!O118 -> 0 | P105: ='ControlSheet '!P118 -> 0 | Q105: ='ControlSheet '!Q118 -> 0 | ... S105: ='ControlSheet '!S118 -> 0
B107: Intangible Assets Under Development
B108: =B107 -> Intangible Assets Under Development | E108: ='Balance Sheet'!E12 -> 0.3336 | F108: ='Balance Sheet'!F12 -> 31.5979 | G108: ='Balance Sheet'!G12 -> 56.9536 | H108: ='Balance Sheet'!H12 -> 74.6992 | I108: ='Balance Sheet'!I12 -> 519.54 | J108: =I108*(1+J109) -> 519.54 | K108: =J108*(1+K109) -> 519.54 | L108: =K108*(1+L109) -> 519.54 | M108: =L108*(1+M109) -> 519.54 | N108: =M108*(1+N109) -> 519.54 | O108: =N108*(1+O109) -> 519.54 | P108: =O108*(1+P109) -> 519.54 | Q108: =P108*(1+Q109) -> 519.54 | ... S108: =R108*(1+S109) -> 519.54
B109: YoY Growth % | F109: =F108/E108-1 -> 93.717926 | G109: =G108/F108-1 -> 0.8024489 | H109: =H108/G108-1 -> 0.31157995 | I109: =I108/H108-1 -> 5.9550946 | J109: ='ControlSheet '!J124 -> 0 | K109: ='ControlSheet '!K124 -> 0 | L109: ='ControlSheet '!L124 -> 0 | M109: ='ControlSheet '!M124 -> 0 | N109: ='ControlSheet '!N124 -> 0 | O109: ='ControlSheet '!O124 -> 0 | P109: ='ControlSheet '!P124 -> 0 | Q109: ='ControlSheet '!Q124 -> 0 | ... S109: ='ControlSheet '!S124 -> 0
B111: Investments in associates
B112: =B111 -> Investments in associates | E112: ='Balance Sheet'!E13 -> 165.7868 | F112: ='Balance Sheet'!F13 -> 167.7428 | G112: ='Balance Sheet'!G13 -> 181.4112 | H112: ='Balance Sheet'!H13 -> 189.2814 | I112: ='Balance Sheet'!I13 -> 190.9 | J112: =I112*(1+J113) -> 190.9 | K112: =J112*(1+K113) -> 190.9 | L112: =K112*(1+L113) -> 190.9 | M112: =L112*(1+M113) -> 190.9 | N112: =M112*(1+N113) -> 190.9 | O112: =N112*(1+O113) -> 190.9 | P112: =O112*(1+P113) -> 190.9 | Q112: =P112*(1+Q113) -> 190.9 | ... S112: =R112*(1+S113) -> 190.9
B113: YoY Growth % | F113: =F112/E112-1 -> 0.011798286 | G113: =G112/F112-1 -> 0.081484272 | H113: =H112/G112-1 -> 0.043383209 | I113: =I112/H112-1 -> 0.0085512892 | J113: ='ControlSheet '!J130 -> 0 | K113: ='ControlSheet '!K130 -> 0 | L113: ='ControlSheet '!L130 -> 0 | M113: ='ControlSheet '!M130 -> 0 | N113: ='ControlSheet '!N130 -> 0 | O113: ='ControlSheet '!O130 -> 0 | P113: ='ControlSheet '!P130 -> 0 | Q113: ='ControlSheet '!Q130 -> 0 | ... S113: ='ControlSheet '!S130 -> 0
A115: # | B115: Depreciation Schedule
C117: 16
B119: Total Depreciation | J119: =SUM(J61,J68,J81) -> 661.80719 | K119: =SUM(K61,K68,K81) -> 706.62506 | L119: =SUM(L61,L68,L81) -> 764.83403 | M119: =SUM(M61,M68,M81) -> 825.08031 | N119: =SUM(N61,N68,N81) -> 885.86211 | O119: =SUM(O61,O68,O81) -> 953.93773 | P119: =SUM(P61,P68,P81) -> 1030.1824 | Q119: =SUM(Q61,Q68,Q81) -> 1115.5765 | ... S119: =SUM(S61,S68,S81) -> 1318.3361
B120: Total Net Depreciable Fixed Assets | J120: =SUM(J62,J69,J82) -> 12503.648 | K120: =SUM(K62,K69,K82) -> 12514.109 | L120: =SUM(L62,L69,L82) -> 12680.619 | M120: =SUM(M62,M69,M82) -> 12819.479 | N120: =SUM(N62,N69,N82) -> 12906.126 | O120: =SUM(O62,O69,O82) -> 13041.398 | P120: =SUM(P62,P69,P82) -> 13231.13 | Q120: =SUM(Q62,Q69,Q82) -> 13481.859 | ... S120: =SUM(S62,S69,S82) -> 14196.459
B122: Depreciation % Sales | J122: =J119/J13 -> 0.04594524 | K122: =K119/K13 -> 0.042108732 | L122: =L119/L13 -> 0.039632593 | M122: =M119/M13 -> 0.037669135 | N122: =N119/N13 -> 0.036110834 | O122: =O119/O13 -> 0.034719495 | P122: =P119/P13 -> 0.033477228 | Q122: =Q119/Q13 -> 0.03236806 | ... S122: =S119/S13 -> 0.030493511
B123: Depreciation % Net Fixed Assets | J123: =J119/J120 -> 0.052929127 | K123: =K119/K120 -> 0.056466269 | L123: =L119/L120 -> 0.060315198 | M123: =M119/M120 -> 0.064361455 | N123: =N119/N120 -> 0.068638888 | O123: =O119/O120 -> 0.073146893 | P123: =P119/P120 -> 0.0778605 | Q123: =Q119/Q120 -> 0.082746489 | ... S123: =S119/S120 -> 0.092863728
B125: =I9 -> 2025 | I125: =SUM(I61,I81) -> 612.69935 | J125: =I125 -> 612.69935 | K125: =J125 -> 612.69935 | L125: =K125 -> 612.69935 | M125: =L125 -> 612.69935 | N125: =M125 -> 612.69935 | O125: =N125 -> 612.69935 | P125: =O125 -> 612.69935 | Q125: =P125 -> 612.69935 | ... S125: =R125 -> 612.69935
B126: =B125+1 -> 2026 | J126: =J119-J125 -> 49.107841 | K126: =J126 -> 49.107841 | L126: =K126 -> 49.107841 | M126: =L126 -> 49.107841 | N126: =M126 -> 49.107841 | O126: =N126 -> 49.107841 | P126: =O126 -> 49.107841 | Q126: =P126 -> 49.107841 | R126: =Q126 -> 49.107841 | S126: =R126 -> 49.107841
B127: =B126+1 -> 2027 | K127: =K119-J119 -> 44.817875 | L127: =K127 -> 44.817875 | M127: =L127 -> 44.817875 | N127: =M127 -> 44.817875 | O127: =N127 -> 44.817875 | P127: =O127 -> 44.817875 | Q127: =P127 -> 44.817875 | R127: =Q127 -> 44.817875 | S127: =R127 -> 44.817875
B128: =B127+1 -> 2028 | L128: =L119-K119 -> 58.208965 | M128: =L128 -> 58.208965 | N128: =M128 -> 58.208965 | O128: =N128 -> 58.208965 | P128: =O128 -> 58.208965 | Q128: =P128 -> 58.208965 | R128: =Q128 -> 58.208965 | S128: =R128 -> 58.208965
B129: =B128+1 -> 2029 | M129: =M119-L119 -> 60.246279 | N129: =M129 -> 60.246279 | O129: =N129 -> 60.246279 | P129: =O129 -> 60.246279 | Q129: =P129 -> 60.246279 | R129: =Q129 -> 60.246279 | S129: =R129 -> 60.246279
B130: =B129+1 -> 2030 | N130: =N119-M119 -> 60.781801 | O130: =O119-N119 -> 68.075617 | P130: =P119-O119 -> 76.244692 | Q130: =Q119-P119 -> 85.394055 | R130: =R119-Q119 -> 95.641341 | S130: =S119-R119 -> 107.1183
B131: Total Depreciation | I131: =SUM(I125:I130) -> 612.69935 | J131: =SUM(J125:J130) -> 661.80719 | K131: =SUM(K125:K130) -> 706.62506 | L131: =SUM(L125:L130) -> 764.83403 | M131: =SUM(M125:M130) -> 825.08031 | N131: =SUM(N125:N130) -> 885.86211 | O131: =SUM(O125:O130) -> 893.15593 | P131: =SUM(P125:P130) -> 901.325 | ... S131: =SUM(S125:S130) -> 932.19861
A133: # | B133: Tax Expense Schedule
B135: Revenue | I135: ='3StatementModel'!H13 -> 12207 | J135: ='3StatementModel'!I13 -> 14404.26 | K135: ='3StatementModel'!J13 -> 16780.963 | L135: ='3StatementModel'!K13 -> 19298.107 | M135: ='3StatementModel'!L13 -> 21903.352 | N135: ='3StatementModel'!M13 -> 24531.754 | O135: ='3StatementModel'!N13 -> 27475.565 | P135: ='3StatementModel'!O13 -> 30772.632 | ... S135: ='3StatementModel'!R13 -> 43233.333
B136: Less: Cost of Good Sold | I136: ='3StatementModel'!H14 -> -3855.04 | J136: ='3StatementModel'!I14 -> -4897.4484 | K136: ='3StatementModel'!J14 -> -5604.8416 | L136: ='3StatementModel'!K14 -> -6329.7792 | M136: ='3StatementModel'!L14 -> -7052.8793 | N136: ='3StatementModel'!M14 -> -7752.0343 | O136: ='3StatementModel'!N14 -> -8682.2784 | P136: ='3StatementModel'!O14 -> -9724.1518 | ... S136: ='3StatementModel'!R14 -> -13661.733
B137: Less: SG&A Expenses | I137: =SUM('3StatementModel'!H20:H24)*-1 -> -5700.1 | J137: =SUM('3StatementModel'!I20:I24)*-1 -> -6409.8957 | K137: =SUM('3StatementModel'!J20:J24)*-1 -> -7467.5285 | L137: =SUM('3StatementModel'!K20:K24)*-1 -> -8587.6578 | M137: =SUM('3StatementModel'!L20:L24)*-1 -> -9746.9916 | N137: =SUM('3StatementModel'!M20:M24)*-1 -> -10916.631 | O137: =SUM('3StatementModel'!N20:N24)*-1 -> -12226.626 | P137: =SUM('3StatementModel'!O20:O24)*-1 -> -13693.821 | ... S137: =SUM('3StatementModel'!R20:R24)*-1 -> -19238.833
B138: Less: Depreciation & Amortization | I138: ='3StatementModel'!H29*-1 -> -621 | J138: ='3StatementModel'!I29*-1 -> -661.80719 | K138: ='3StatementModel'!J29*-1 -> -706.62506 | L138: ='3StatementModel'!K29*-1 -> -764.83403 | M138: ='3StatementModel'!L29*-1 -> -825.08031 | N138: ='3StatementModel'!M29*-1 -> -885.86211 | O138: ='3StatementModel'!N29*-1 -> -953.93773 | P138: ='3StatementModel'!O29*-1 -> -1030.1824 | ... S138: ='3StatementModel'!R29*-1 -> -1318.3361
B139: Add: Other Income | I139: ='3StatementModel'!I35 -> 432.1278 | J139: ='3StatementModel'!I35 -> 432.1278 | K139: ='3StatementModel'!J35 -> 503.42889 | L139: ='3StatementModel'!K35 -> 578.94322 | M139: ='3StatementModel'!L35 -> 657.10055 | N139: ='3StatementModel'!M35 -> 735.95262 | O139: ='3StatementModel'!N35 -> 824.26694 | P139: ='3StatementModel'!O35 -> 923.17897 | Q139: ='3StatementModel'!P35 -> 1033.9604 | ... S139: ='3StatementModel'!R35 -> 1297
B140: Less: Interest Expenses | I140: ='3StatementModel'!H34*-1 -> 429.4 | J140: ='3StatementModel'!I34 -> -561.47041 | K140: ='3StatementModel'!J34 -> -503.42321 | L140: ='3StatementModel'!K34 -> -534.83289 | M140: ='3StatementModel'!L34 -> -576.99301 | N140: ='3StatementModel'!M34 -> -614.8129 | O140: ='3StatementModel'!N34 -> -567.30762 | P140: ='3StatementModel'!O34 -> -513.11571 | Q140: ='3StatementModel'!P34 -> -523.37837 | ... S140: ='3StatementModel'!R34 -> -544.52208
B141: Earnings Before Tax | I141: =SUM(I135:I140) -> 2892.3878 | J141: =SUM(J135:J140) -> 2305.7661 | K141: =SUM(K135:K140) -> 3001.9734 | L141: =SUM(L135:L140) -> 3659.9467 | M141: =SUM(M135:M140) -> 4358.5082 | N141: =SUM(N135:N140) -> 5098.3668 | O141: =SUM(O135:O140) -> 5869.6815 | P141: =SUM(P135:P140) -> 6734.54 | ... S141: =SUM(S135:S140) -> 9766.9083
B142: Less: Tax Expenses | I142: ='3StatementModel'!H39 -> -509.74 | J142: =J141*J145*-1 -> -576.44153 | K142: =K141*K145*-1 -> -750.49335 | L142: =L141*L145*-1 -> -914.98667 | M142: =M141*M145*-1 -> -1089.6271 | N142: =N141*N145*-1 -> -1274.5917 | O142: =O141*O145*-1 -> -1467.4204 | P142: =P141*P145*-1 -> -1683.635 | Q142: =Q141*Q145*-1 -> -1908.056 | ... S142: =S141*S145*-1 -> -2441.7271
B143: Net Income | I143: =I141+I142 -> 2382.6478 | J143: =J141+J142 -> 1729.3246 | K143: =K141+K142 -> 2251.4801 | L143: =L141+L142 -> 2744.96 | M143: =M141+M142 -> 3268.8812 | N143: =N141+N142 -> 3823.7751 | O143: =O141+O142 -> 4402.2611 | P143: =P141+P142 -> 5050.905 | ... S143: =S141+S142 -> 7325.1812
B145: Marginal Tax Rate | I145: =(I142*-1)/I141 -> 0.17623501 | J145: ='ControlSheet '!J139 -> 0.25 | K145: ='ControlSheet '!K139 -> 0.25 | L145: ='ControlSheet '!L139 -> 0.25 | M145: ='ControlSheet '!M139 -> 0.25 | N145: ='ControlSheet '!N139 -> 0.25 | O145: ='ControlSheet '!O139 -> 0.25 | P145: ='ControlSheet '!P139 -> 0.25 | Q145: ='ControlSheet '!Q139 -> 0.25 | ... S145: ='ControlSheet '!S139 -> 0.25
A147: # | B147: Other Equity Schedule
...

Sheet 3StatementModel
B2: ='Input Sheet'!C5 -> Mankind Pharma Ltd
B3: 3 Statement Model
H4: Current Case | J4: 1
T7: CAGR
D8: Actual | I8: Explicit Forecast Period | N8: Maturity Period | T8: 5 Years | U8: 3 Years
B9: In INR Crores unless stated otherwise | D9: ='ControlSheet '!E9 -> 2021 | E9: ='ControlSheet '!F9 -> 2022 | F9: ='ControlSheet '!G9 -> 2023 | G9: ='ControlSheet '!H9 -> 2024 | H9: ='ControlSheet '!I9 -> 2025 | I9: ='ControlSheet '!J9 -> 2026 | J9: ='ControlSheet '!K9 -> 2027 | K9: ='ControlSheet '!L9 -> 2028 | ... R9: ='ControlSheet '!S9 -> 2035
A11: # | B11: Income Statement
B13: Revenue | D13: =Schedules!E13 -> 6223.8982 | E13: =Schedules!F13 -> 7781.5551 | F13: =Schedules!G13 -> 8749.433 | G13: =Schedules!H13 -> 10334.775 | H13: =Schedules!I13 -> 12207 | I13: =Schedules!J13 -> 14404.26 | J13: =Schedules!K13 -> 16780.963 | K13: =Schedules!L13 -> 19298.107 | ... R13: =Schedules!S13 -> 43233.333 | T13: =_xlfn.RRI($M$9-$H$9,H13,M13) -> 0.14980431 | U13: =_xlfn.RRI($M$9-$J$9,J13,M13) -> 0.13493392
B14: Less: Cost of Goods Sold | D14: =Schedules!E20*-1 -> -1780.6092 | E14: =Schedules!F20*-1 -> -2421.7284 | F14: =Schedules!G20*-1 -> -2913.642 | G14: =Schedules!H20*-1 -> -3209.6959 | H14: =Schedules!I20*-1 -> -3855.04 | I14: =Schedules!J20*-1 -> -4897.4484 | J14: =Schedules!K20*-1 -> -5604.8416 | K14: =Schedules!L20*-1 -> -6329.7792 | ... R14: =Schedules!S20*-1 -> -13661.733 | T14: =_xlfn.RRI($M$9-$H$9,H14,M14) -> 0.14994577 | U14: =_xlfn.RRI($M$9-$J$9,J14,M14) -> 0.11416825
B15: Gross Profit | D15: =D13+D14 -> 4443.289 | E15: =E13+E14 -> 5359.8267 | F15: =F13+F14 -> 5835.791 | G15: =G13+G14 -> 7125.0787 | H15: =H13+H14 -> 8351.96 | I15: =I13+I14 -> 9506.8116 | J15: =J13+J14 -> 11176.121 | K15: =K13+K14 -> 12968.328 | ... R15: =R13+R14 -> 29571.6 | T15: =_xlfn.RRI($M$9-$H$9,H15,M15) -> 0.14973899 | U15: =_xlfn.RRI($M$9-$J$9,J15,M15) -> 0.14506779
B17: Gross Margin | D17: =D15/D13 -> 0.71390772 | E17: =E15/E13 -> 0.68878606 | F17: =F15/F13 -> 0.66699076 | G17: =G15/G13 -> 0.68942759 | H17: =H15/H13 -> 0.68419431 | I17: =I15/I13 -> 0.66 | J17: =J15/J13 -> 0.666 | K17: =K15/K13 -> 0.672 | ... R17: =R15/R13 -> 0.684
B19: Less: SG&A Expenses (Excluding Depreciation & Interest) | D19: =SUM(D20:D24) -> 2785.6962 | E19: =SUM(E20:E24) -> 3370.4605 | F19: =SUM(F20:F24) -> 3935.1329 | G19: =SUM(G20:G24) -> 4589.9754 | H19: =SUM(H20:H24) -> 5700.1 | I19: =SUM(I20:I24) -> 6409.8957 | J19: =SUM(J20:J24) -> 7467.5285 | K19: =SUM(K20:K24) -> 8587.6578 | ... R19: =SUM(R20:R24) -> 19238.833
B20: =Schedules!B26 -> Employee Benefit Expense | D20: =Schedules!E28 -> 1415.76 | E20: =Schedules!F28 -> 1620.58 | F20: =Schedules!G28 -> 1918.45 | G20: =Schedules!H28 -> 2274.7 | H20: =Schedules!I28 -> 2692 | I20: =Schedules!J28 -> 3168.9372 | J20: =Schedules!K28 -> 3691.8118 | K20: =Schedules!L28 -> 4245.5836 | ... R20: =Schedules!S28 -> 9511.3332 | T20: =_xlfn.RRI($M$9-$H$9,H20,M20) -> 0.14925194 | U20: =_xlfn.RRI($M$9-$J$9,J20,M20) -> 0.13493392
B21: =Schedules!B31 -> Advertising & Sales Promotion Expense | D21: =Schedules!E33 -> 385.74 | E21: =Schedules!F33 -> 451.56 | F21: =Schedules!G33 -> 373.6656 | G21: =Schedules!H33 -> 603.8922 | H21: =Schedules!I33 -> 755 | I21: =Schedules!J33 -> 835.44708 | J21: =Schedules!K33 -> 973.29585 | K21: =Schedules!L33 -> 1119.2902 | ... R21: =Schedules!S33 -> 2507.5333 | T21: =_xlfn.RRI($M$9-$H$9,H21,M21) -> 0.1351204 | U21: =_xlfn.RRI($M$9-$J$9,J21,M21) -> 0.13493392
B22: =Schedules!B36 -> Travelling and conveyance Expense | D22: =Schedules!E38 -> 270.4 | E22: =Schedules!F38 -> 358.11 | F22: =Schedules!G38 -> 496.0469 | G22: =Schedules!H38 -> 378.4002 | H22: =Schedules!I38 -> 461 | I22: =Schedules!J38 -> 662.59596 | J22: =Schedules!K38 -> 771.92429 | K22: =Schedules!L38 -> 887.71294 | ... R22: =Schedules!S38 -> 1988.7333 | T22: =_xlfn.RRI($M$9-$H$9,H22,M22) -> 0.19607139 | U22: =_xlfn.RRI($M$9-$J$9,J22,M22) -> 0.13493392
B23: =Schedules!B41 -> Other Operating Expense | D23: =Schedules!E43 -> 369.96 | E23: =Schedules!F43 -> 510.97 | F23: =Schedules!G43 -> 619.1845 | G23: =Schedules!H43 -> 803.9094 | H23: =Schedules!I43 -> 1073 | I23: =Schedules!J43 -> 950.68116 | J23: =Schedules!K43 -> 1107.5436 | K23: =Schedules!L43 -> 1273.6751 | ... R23: =Schedules!S43 -> 2853.4 | T23: =_xlfn.RRI($M$9-$H$9,H23,M23) -> 0.085761813 | U23: =_xlfn.RRI($M$9-$J$9,J23,M23) -> 0.13493392
B24: =Schedules!B46 -> Other Misc SG&A Expenses | D24: =Schedules!E48 -> 343.8362 | E24: =Schedules!F48 -> 429.2405 | F24: =Schedules!G48 -> 527.7859 | G24: =Schedules!H48 -> 529.0736 | H24: =Schedules!I48 -> 719.1 | I24: =Schedules!J48 -> 792.2343 | J24: =Schedules!K48 -> 922.95296 | K24: =Schedules!L48 -> 1061.3959 | ... R24: =Schedules!S48 -> 2377.8333 | T24: =_xlfn.RRI($M$9-$H$9,H24,M24) -> 0.13412363 | U24: =_xlfn.RRI($M$9-$J$9,J24,M24) -> 0.13493392
B25: EBITDA | D25: =D15-SUM(D20:D24) -> 1657.5928 | E25: =E15-SUM(E20:E24) -> 1989.3662 | F25: =F15-SUM(F20:F24) -> 1900.6581 | G25: =G15-SUM(G20:G24) -> 2535.1033 | H25: =H15-SUM(H20:H24) -> 2651.86 | I25: =I15-SUM(I20:I24) -> 3096.9159 | J25: =J15-SUM(J20:J24) -> 3708.5928 | K25: =K15-SUM(K20:K24) -> 4380.6704 | ... R25: =R15-SUM(R20:R24) -> 10332.767 | T25: =_xlfn.RRI($M$9-$H$9,H25,M25) -> 0.17196646 | U25: =_xlfn.RRI($M$9-$J$9,J25,M25) -> 0.16494597
B27: EBITDA Margin | D27: =D25/D13 -> 0.26632711 | E27: =E25/E13 -> 0.2556515 | F27: =F25/F13 -> 0.21723215 | G27: =G25/G13 -> 0.24529836 | H27: =H25/H13 -> 0.21724093 | I27: =I25/I13 -> 0.215 | J27: =J25/J13 -> 0.221 | K27: =K25/K13 -> 0.227 | ... R27: =R25/R13 -> 0.239
B29: Less: Depreciation | D29: ='Income Stmt'!E37*-1 -> 118.9703 | E29: ='Income Stmt'!F37*-1 -> 166.6192 | F29: ='Income Stmt'!G37*-1 -> 325.9195 | G29: ='Income Stmt'!H37*-1 -> 398.2537 | H29: ='Income Stmt'!I37*-1 -> 621 | I29: =Schedules!J119 -> 661.80719 | J29: =Schedules!K119 -> 706.62506 | K29: =Schedules!L119 -> 764.83403 | L29: =Schedules!M119 -> 825.08031 | M29: =Schedules!N119 -> 885.86211 | N29: =Schedules!O119 -> 953.93773 | O29: =Schedules!P119 -> 1030.1824 | P29: =Schedules!Q119 -> 1115.5765 | ... R29: =Schedules!S119 -> 1318.3361 | T29: =_xlfn.RRI($M$9-$H$9,H29,M29) -> 0.07363066 | U29: =_xlfn.RRI($M$9-$J$9,J29,M29) -> 0.078265466
B30: EBIT | D30: =D25-D29 -> 1538.6225 | E30: =E25-E29 -> 1822.747 | F30: =F25-F29 -> 1574.7386 | G30: =G25-G29 -> 2136.8496 | H30: =H25-H29 -> 2030.86 | I30: =I25-I29 -> 2435.1087 | J30: =J25-J29 -> 3001.9677 | K30: =K25-K29 -> 3615.8363 | ... R30: =R25-R29 -> 9014.4304 | T30: =_xlfn.RRI($M$9-$H$9,H30,M30) -> 0.19635893 | U30: =_xlfn.RRI($M$9-$J$9,J30,M30) -> 0.18356963
B32: EBIT Margin | D32: =D30/D13 -> 0.24721203 | E32: =E30/E13 -> 0.23423943 | F32: =F30/F13 -> 0.17998179 | G32: =G30/G13 -> 0.20676306 | H32: =H30/H13 -> 0.16636848 | I32: =I30/I13 -> 0.16905476 | J32: =J30/J13 -> 0.17889127 | K32: =K30/K13 -> 0.18736741 | ... R32: =R30/R13 -> 0.20850649
B34: Less: Interest | D34: ='Income Stmt'!E41 -> -20.1474 | E34: ='Income Stmt'!F41 -> -58.6104 | F34: ='Income Stmt'!G41 -> -44.469 | G34: ='Income Stmt'!H41 -> -33.5316 | H34: ='Income Stmt'!I41 -> -429.4 | I34: =Schedules!J246*-1 -> -561.47041 | J34: =Schedules!K246*-1 -> -503.42321 | K34: =Schedules!L246*-1 -> -534.83289 | L34: =Schedules!M246*-1 -> -576.99301 | M34: =Schedules!N246*-1 -> -614.8129 | N34: =Schedules!O246*-1 -> -567.30762 | O34: =Schedules!P246*-1 -> -513.11571 | P34: =Schedules!Q246*-1 -> -523.37837 | ... R34: =Schedules!S246*-1 -> -544.52208
B35: Add: Other Income | D35: ='Income Stmt'!E42 -> 161.4821 | E35: ='Income Stmt'!F42 -> 196.0296 | F35: ='Income Stmt'!G42 -> 128.5668 | G35: ='Income Stmt'!H42 -> 280.8579 | H35: ='Income Stmt'!I42 -> 536.79 | I35: =Schedules!J252 -> 432.1278 | J35: =Schedules!K252 -> 503.42889 | K35: =Schedules!L252 -> 578.94322 | L35: =Schedules!M252 -> 657.10055 | M35: =Schedules!N252 -> 735.95262 | N35: =Schedules!O252 -> 824.26694 | O35: =Schedules!P252 -> 923.17897 | P35: =Schedules!Q252 -> 1033.9604 | ... R35: =Schedules!S252 -> 1297
B36: Less: Share of net profit of associates and joint ventures | D36: ='Income Stmt'!E45*-1 -> -11.6771 | E36: ='Income Stmt'!F45*-1 -> -14.4477 | F36: ='Income Stmt'!G45*-1 -> -12.4242 | G36: ='Income Stmt'!H45*-1 -> -15.2135 | H36: ='Income Stmt'!I45*-1 -> -12.24 | I36: 0 | J36: 0 | K36: 0 | L36: 0 | M36: 0 | N36: 0 | O36: 0 | P36: 0 | Q36: 0 | R36: 0
B37: EBT | D37: =SUM(D30,D34:D36) -> 1668.2801 | E37: =SUM(E30,E34:E36) -> 1945.7185 | F37: =SUM(F30,F34:F36) -> 1646.4122 | G37: =SUM(G30,G34:G36) -> 2368.9624 | H37: =SUM(H30,H34:H36) -> 2126.01 | I37: =SUM(I30,I34:I36) -> 2305.7661 | J37: =SUM(J30,J34:J36) -> 3001.9734 | K37: =SUM(K30,K34:K36) -> 3659.9467 | ... R37: =SUM(R30,R34:R36) -> 9766.9083
B39: Less: Taxes | D39: ='Income Stmt'!E48 -> -398.5839 | E39: ='Income Stmt'!F48 -> -521.6435 | F39: ='Income Stmt'!G48 -> -361.5633 | G39: ='Income Stmt'!H48 -> -457.5865 | H39: ='Income Stmt'!I48 -> -509.74 | I39: =Schedules!J142 -> -576.44153 | J39: =Schedules!K142 -> -750.49335 | K39: =Schedules!L142 -> -914.98667 | L39: =Schedules!M142 -> -1089.6271 | M39: =Schedules!N142 -> -1274.5917 | N39: =Schedules!O142 -> -1467.4204 | O39: =Schedules!P142 -> -1683.635 | P39: =Schedules!Q142 -> -1908.056 | ... R39: =Schedules!S142 -> -2441.7271 | T39: =_xlfn.RRI($M$9-$H$9,H39,M39) -> 0.20116999 | U39: =_xlfn.RRI($M$9-$J$9,J39,M39) -> 0.19309423
B40: Net Income | D40: =SUM(D37,D39) -> 1269.6962 | E40: =SUM(E37,E39) -> 1424.075 | F40: =SUM(F37,F39) -> 1284.8489 | G40: =SUM(G37,G39) -> 1911.3759 | H40: =SUM(H37,H39) -> 1616.27 | I40: =SUM(I37,I39) -> 1729.3246 | J40: =SUM(J37,J39) -> 2251.4801 | K40: =SUM(K37,K39) -> 2744.96 | ... R40: =SUM(R37,R39) -> 7325.1812 | T40: =_xlfn.RRI($M$9-$H$9,H40,M40) -> 0.18794323 | U40: =_xlfn.RRI($M$9-$J$9,J40,M40) -> 0.19309423
B42: Sales Growth % | D42: =IFERROR(D13/C13-1,0) -> 0 | E42: =IFERROR(E13/D13-1,0) -> 0.2502703 | F42: =IFERROR(F13/E13-1,0) -> 0.12438104 | G42: =IFERROR(G13/F13-1,0) -> 0.18119364 | H42: =IFERROR(H13/G13-1,0) -> 0.18115784 | I42: =IFERROR(I13/H13-1,0) -> 0.18 | J42: =IFERROR(J13/I13-1,0) -> 0.165 | K42: =IFERROR(K13/J13-1,0) -> 0.15 | ... R42: =IFERROR(R13/Q13-1,0) -> 0.12 | T42: =_xlfn.RRI($M$9-$H$9,H42,M42) -> -0.079073809 | U42: =_xlfn.RRI($M$9-$J$9,J42,M42) -> -0.10071137
B43: Gross Profit Margins % | D43: =IFERROR(D15/D13,"NM") -> 0.71390772 | E43: =IFERROR(E15/E13,"NM") -> 0.68878606 | F43: =IFERROR(F15/F13,"NM") -> 0.66699076 | G43: =IFERROR(G15/G13,"NM") -> 0.68942759 | H43: =IFERROR(H15/H13,"NM") -> 0.68419431 | I43: =IFERROR(I15/I13,"NM") -> 0.66 | J43: =IFERROR(J15/J13,"NM") -> 0.666 | K43: =IFERROR(K15/K13,"NM") -> 0.672 | ... R43: =IFERROR(R15/R13,"NM") -> 0.684 | T43: =_xlfn.RRI($M$9-$H$9,H43,M43) -> -5.6807492e-05 | U43: =_xlfn.RRI($M$9-$J$9,J43,M43) -> 0.0089290439
B44: EBITDA Margins % | D44: =IFERROR(D25/D13,"NM") -> 0.26632711 | E44: =IFERROR(E25/E13,"NM") -> 0.2556515 | F44: =IFERROR(F25/F13,"NM") -> 0.21723215 | G44: =IFERROR(G25/G13,"NM") -> 0.24529836 | H44: =IFERROR(H25/H13,"NM") -> 0.21724093 | I44: =IFERROR(I25/I13,"NM") -> 0.215 | J44: =IFERROR(J25/J13,"NM") -> 0.221 | K44: =IFERROR(K25/K13,"NM") -> 0.227 | ... R44: =IFERROR(R25/R13,"NM") -> 0.239 | T44: =_xlfn.RRI($M$9-$H$9,H44,M44) -> 0.019274714 | U44: =_xlfn.RRI($M$9-$J$9,J44,M44) -> 0.026443879
B45: EBIT Margins % | D45: =IFERROR(D30/D13,"NM") -> 0.24721203 | E45: =IFERROR(E30/E13,"NM") -> 0.23423943 | F45: =IFERROR(F30/F13,"NM") -> 0.17998179 | G45: =IFERROR(G30/G13,"NM") -> 0.20676306 | H45: =IFERROR(H30/H13,"NM") -> 0.16636848 | I45: =IFERROR(I30/I13,"NM") -> 0.16905476 | J45: =IFERROR(J30/J13,"NM") -> 0.17889127 | K45: =IFERROR(K30/K13,"NM") -> 0.18736741 | ... R45: =IFERROR(R30/R13,"NM") -> 0.20850649 | T45: =_xlfn.RRI($M$9-$H$9,H45,M45) -> 0.040489167 | U45: =_xlfn.RRI($M$9-$J$9,J45,M45) -> 0.042853343
B46: Actual Tax Rate % | D46: =-D39/D37*-1 -> -0.23891905 | E46: =-E39/E37*-1 -> -0.26809813 | F46: =-F39/F37*-1 -> -0.21960679 | G46: =-G39/G37*-1 -> -0.19315904 | H46: =-H39/H37*-1 -> -0.23976369 | I46: =-I39/I37*-1 -> -0.25 | J46: =-J39/J37*-1 -> -0.25 | K46: =-K39/K37*-1 -> -0.25 | ... R46: =-R39/R37*-1 -> -0.25 | T46: =_xlfn.RRI($M$9-$H$9,H46,M46) -> 0.0083964762 | U46: =_xlfn.RRI($M$9-$J$9,J46,M46) -> 0
B47: Net Income Margin % | D47: =IFERROR(D40/D13,"NM") -> 0.20400337 | E47: =IFERROR(E40/E13,"NM") -> 0.18300648 | F47: =IFERROR(F40/F13,"NM") -> 0.14684939 | G47: =IFERROR(G40/G13,"NM") -> 0.18494607 | H47: =IFERROR(H40/H13,"NM") -> 0.13240518 | I47: =IFERROR(I40/I13,"NM") -> 0.12005647 | J47: =IFERROR(J40/J13,"NM") -> 0.1341687 | K47: =IFERROR(K40/K13,"NM") -> 0.14223986 | ... R47: =IFERROR(R40/R13,"NM") -> 0.16943365 | T47: =_xlfn.RRI($M$9-$H$9,H47,M47) -> 0.033169923 | U47: =_xlfn.RRI($M$9-$J$9,J47,M47) -> 0.051245552
A49: # | B49: Balance Sheet
B51: Assets
B53: Non Current Assets
B54: Property , Plants & Equipments | D54: ='Balance Sheet'!E7 -> 1620.2788 | E54: ='Balance Sheet'!F7 -> 1652.4046 | F54: ='Balance Sheet'!G7 -> 2409.4607 | G54: ='Balance Sheet'!H7 -> 2812.5396 | H54: ='Balance Sheet'!I7 -> 2740.6305 | I54: =Schedules!J62 -> 3216.7203 | J54: =Schedules!K62 -> 3712.1631 | K54: =Schedules!L62 -> 4363.6545 | L54: =Schedules!M62 -> 4987.4966 | M54: =Schedules!N62 -> 5559.1252 | N54: =Schedules!O62 -> 6179.3793 | O54: =Schedules!P62 -> 6854.0939 | P54: =Schedules!Q62 -> 7589.8042 | ... R54: =Schedules!S62 -> 9274.3685
B55: Right of Use Assets | D55: ='Balance Sheet'!E9 -> 0 | E55: ='Balance Sheet'!F9 -> 67.3571 | F55: ='Balance Sheet'!G9 -> 114.3647 | G55: ='Balance Sheet'!H9 -> 119.0613 | H55: ='Balance Sheet'!I9 -> 167.25 | I55: =Schedules!J69 -> 158.94935 | J55: =Schedules!K69 -> 150.6487 | K55: =Schedules!L69 -> 142.34804 | L55: =Schedules!M69 -> 134.04739 | M55: =Schedules!N69 -> 125.74674 | N55: =Schedules!O69 -> 117.44609 | O55: =Schedules!P69 -> 109.14543 | P55: =Schedules!Q69 -> 100.84478 | ... R55: =Schedules!S69 -> 84.243475
B56: Capital Work in Progress | D56: ='Balance Sheet'!E8 -> 371.6162 | E56: ='Balance Sheet'!F8 -> 669.8734 | F56: ='Balance Sheet'!G8 -> 493.192 | G56: ='Balance Sheet'!H8 -> 207.0939 | H56: ='Balance Sheet'!I8 -> 306.13 | I56: =Schedules!J75 -> 0 | J56: =Schedules!K75 -> 0 | K56: =Schedules!L75 -> 0 | L56: =Schedules!M75 -> 0 | M56: =Schedules!N75 -> 0 | N56: =Schedules!O75 -> 0 | O56: =Schedules!P75 -> 0 | P56: =Schedules!Q75 -> 0 | ... R56: =Schedules!S75 -> 0
B57: Goodwill | D57: ='Balance Sheet'!E10 -> 20.4422 | E57: ='Balance Sheet'!F10 -> 20.4422 | F57: ='Balance Sheet'!G10 -> 20.0225 | G57: ='Balance Sheet'!H10 -> 20.0225 | H57: ='Balance Sheet'!I10 -> 6492 | I57: =Schedules!J88 -> 6492 | J57: =Schedules!K88 -> 6492 | K57: =Schedules!L88 -> 6492 | L57: =Schedules!M88 -> 6492 | M57: =Schedules!N88 -> 6492 | N57: =Schedules!O88 -> 6492 | O57: =Schedules!P88 -> 6492 | P57: =Schedules!Q88 -> 6492 | ... R57: =Schedules!S88 -> 6492
B58: Other Intangible Asset | D58: ='Balance Sheet'!E11 -> 18.4286 | E58: ='Balance Sheet'!F11 -> 1842.6152 | F58: ='Balance Sheet'!G11 -> 1701.4633 | G58: ='Balance Sheet'!H11 -> 1588.3397 | H58: ='Balance Sheet'!I11 -> 9604.66 | I58: =Schedules!J82 -> 9127.9787 | J58: =Schedules!K82 -> 8651.2974 | K58: =Schedules!L82 -> 8174.6162 | L58: =Schedules!M82 -> 7697.9349 | M58: =Schedules!N82 -> 7221.2536 | N58: =Schedules!O82 -> 6744.5723 | O58: =Schedules!P82 -> 6267.891 | P58: =Schedules!Q82 -> 5791.2097 | ... R58: =Schedules!S82 -> 4837.8472
B59: Non Current Financial Assets | D59: ='Balance Sheet'!E15 -> 68.019 | E59: ='Balance Sheet'!F15 -> 95.6446 | F59: ='Balance Sheet'!G15 -> 205.0883 | G59: ='Balance Sheet'!H15 -> 155.3354 | H59: ='Balance Sheet'!I15 -> 360.57 | I59: =Schedules!J92 -> 360.57 | J59: =Schedules!K92 -> 360.57 | K59: =Schedules!L92 -> 360.57 | L59: =Schedules!M92 -> 360.57 | M59: =Schedules!N92 -> 360.57 | N59: =Schedules!O92 -> 360.57 | O59: =Schedules!P92 -> 360.57 | P59: =Schedules!Q92 -> 360.57 | ... R59: =Schedules!S92 -> 360.57
B60: Other Non Current Assets | D60: ='Balance Sheet'!E20 -> 96.6766 | E60: ='Balance Sheet'!F20 -> 74.1843 | F60: ='Balance Sheet'!G20 -> 73.355 | G60: ='Balance Sheet'!H20 -> 66.2811 | H60: ='Balance Sheet'!I20 -> 92.26 | I60: =Schedules!J96 -> 92.26 | J60: =Schedules!K96 -> 92.26 | K60: =Schedules!L96 -> 92.26 | L60: =Schedules!M96 -> 92.26 | M60: =Schedules!N96 -> 92.26 | N60: =Schedules!O96 -> 92.26 | O60: =Schedules!P96 -> 92.26 | P60: =Schedules!Q96 -> 92.26 | ... R60: =Schedules!S96 -> 92.26
B61: Deffered Tax Assets | D61: ='Balance Sheet'!E22 -> 49.011 | E61: ='Balance Sheet'!F22 -> 39.2862 | F61: ='Balance Sheet'!G22 -> 29.7769 | G61: ='Balance Sheet'!H22 -> 80.3975 | H61: ='Balance Sheet'!I22 -> 107.89 | I61: =Schedules!J104 -> 107.89 | J61: =Schedules!K104 -> 107.89 | K61: =Schedules!L104 -> 107.89 | L61: =Schedules!M104 -> 107.89 | M61: =Schedules!N104 -> 107.89 | N61: =Schedules!O104 -> 107.89 | O61: =Schedules!P104 -> 107.89 | P61: =Schedules!Q104 -> 107.89 | ... R61: =Schedules!S104 -> 107.89
B62: Income Tax Assets | D62: ='Balance Sheet'!E21 -> 55.6056 | E62: ='Balance Sheet'!F21 -> 79.8242 | F62: ='Balance Sheet'!G21 -> 102.5153 | G62: ='Balance Sheet'!H21 -> 81.9839 | H62: ='Balance Sheet'!I21 -> 189.49 | I62: =Schedules!J100 -> 189.49 | J62: =Schedules!K100 -> 189.49 | K62: =Schedules!L100 -> 189.49 | L62: =Schedules!M100 -> 189.49 | M62: =Schedules!N100 -> 189.49 | N62: =Schedules!O100 -> 189.49 | O62: =Schedules!P100 -> 189.49 | P62: =Schedules!Q100 -> 189.49 | ... R62: =Schedules!S100 -> 189.49
B63: Intangible Assets Under Development | D63: ='Balance Sheet'!E12 -> 0.3336 | E63: ='Balance Sheet'!F12 -> 31.5979 | F63: ='Balance Sheet'!G12 -> 56.9536 | G63: ='Balance Sheet'!H12 -> 74.6992 | H63: ='Balance Sheet'!I12 -> 519.54 | I63: =Schedules!J108 -> 519.54 | J63: =Schedules!K108 -> 519.54 | K63: =Schedules!L108 -> 519.54 | L63: =Schedules!M108 -> 519.54 | M63: =Schedules!N108 -> 519.54 | N63: =Schedules!O108 -> 519.54 | O63: =Schedules!P108 -> 519.54 | P63: =Schedules!Q108 -> 519.54 | ... R63: =Schedules!S108 -> 519.54
B64: Investments in associates | D64: ='Balance Sheet'!E13 -> 165.7868 | E64: ='Balance Sheet'!F13 -> 167.7428 | F64: ='Balance Sheet'!G13 -> 181.4112 | G64: ='Balance Sheet'!H13 -> 189.2814 | H64: ='Balance Sheet'!I13 -> 190.9 | I64: =Schedules!J112 -> 190.9 | J64: =Schedules!K112 -> 190.9 | K64: =Schedules!L112 -> 190.9 | L64: =Schedules!M112 -> 190.9 | M64: =Schedules!N112 -> 190.9 | N64: =Schedules!O112 -> 190.9 | O64: =Schedules!P112 -> 190.9 | P64: =Schedules!Q112 -> 190.9 | ... R64: =Schedules!S112 -> 190.9
B65: Total Non Current Assets | D65: =SUM(D54:D64) -> 2466.1984 | E65: =SUM(E54:E64) -> 4740.9725 | F65: =SUM(F54:F64) -> 5387.6035 | G65: =SUM(G54:G64) -> 5395.0355 | H65: =SUM(H54:H64) -> 20771.321 | I65: =SUM(I54:I64) -> 20456.298 | J65: =SUM(J54:J64) -> 20466.759 | K65: =SUM(K54:K64) -> 20633.269 | ... R65: =SUM(R54:R64) -> 22149.109
B67: Current Assets
B68: Cash | D68: ='Balance Sheet'!E34 -> 167.182 | E68: ='Balance Sheet'!F34 -> 302.5347 | F68: ='Balance Sheet'!G34 -> 304.8207 | G68: ='Balance Sheet'!H34 -> 382.0075 | H68: ='Balance Sheet'!I34 -> 407.36 | I68: =I145 -> 1160.7377 | J68: =J145 -> 3013.5062 | K68: =K145 -> 5297.2914 | L68: =L145 -> 8249.6812 | M68: =M145 -> 11409.643 | N68: =N145 -> 10287.808 | O68: =O145 -> 13877.886 | P68: =P145 -> 17914.175 | ... R68: =R145 -> 27547.896
B69: Bank balance | D69: ='Balance Sheet'!E35 -> 533.5598 | E69: ='Balance Sheet'!F35 -> 103.4068 | F69: ='Balance Sheet'!G35 -> 148.3779 | G69: ='Balance Sheet'!H35 -> 815.9637 | H69: ='Balance Sheet'!I35 -> 147.14 | I69: =H69 -> 147.14 | J69: =I69 -> 147.14 | K69: =J69 -> 147.14 | L69: =K69 -> 147.14 | M69: =L69 -> 147.14 | N69: =M69 -> 147.14 | O69: =N69 -> 147.14 | P69: =O69 -> 147.14 | ... R69: =Q69 -> 147.14
B70: Inventory | D70: ='Balance Sheet'!E26 -> 1183.5377 | E70: ='Balance Sheet'!F26 -> 1760.2381 | F70: ='Balance Sheet'!G26 -> 1498.4582 | G70: ='Balance Sheet'!H26 -> 1553.4612 | H70: ='Balance Sheet'!I26 -> 2093.71 | I70: =Schedules!J165 -> 2311.8153 | J70: =Schedules!K165 -> 2693.2648 | K70: =Schedules!L165 -> 2907.934 | L70: =Schedules!M165 -> 3300.5051 | M70: =Schedules!N165 -> 3696.5657 | N70: =Schedules!O165 -> 4140.1536 | O70: =Schedules!P165 -> 4636.972 | P70: =Schedules!Q165 -> 5193.4086 | ... R70: =Schedules!S165 -> 6514.6118
B71: Receivable | D71: ='Balance Sheet'!E27 -> 330.6113 | E71: ='Balance Sheet'!F27 -> 388.166 | F71: ='Balance Sheet'!G27 -> 576.4214 | G71: ='Balance Sheet'!H27 -> 848.2812 | H71: ='Balance Sheet'!I27 -> 1538.34 | I71: =Schedules!J160 -> 940.1806 | J71: =Schedules!K160 -> 1095.3104 | K71: =Schedules!L160 -> 1321.7882 | L71: =Schedules!M160 -> 1500.2296 | M71: =Schedules!N160 -> 1680.2571 | N71: =Schedules!O160 -> 1881.888 | O71: =Schedules!P160 -> 2107.7145 | P71: =Schedules!Q160 -> 2360.6403 | ... R71: =Schedules!S160 -> 2961.1872
B72: Investments | D72: ='Balance Sheet'!E33 -> 1306.1741 | E72: ='Balance Sheet'!F33 -> 874.4618 | F72: ='Balance Sheet'!G33 -> 1075.4741 | G72: ='Balance Sheet'!H33 -> 2258.1124 | H72: ='Balance Sheet'!I33 -> 1690.84 | I72: =Schedules!J257 -> 1995.1912 | J72: =Schedules!K257 -> 2324.3977 | K72: =Schedules!L257 -> 2673.0574 | L72: =Schedules!M257 -> 3033.9202 | M72: =Schedules!N257 -> 3397.9906 | N72: =Schedules!O257 -> 3805.7494 | O72: =Schedules!P257 -> 4262.4394 | P72: =Schedules!Q257 -> 4773.9321 | ... R72: =Schedules!S257 -> 5988.4204
B73: Other Current Assets | D73: ='Balance Sheet'!E28 -> 385.5699 | E73: ='Balance Sheet'!F28 -> 978.0109 | F73: ='Balance Sheet'!G28 -> 724.3197 | G73: ='Balance Sheet'!H28 -> 710.4012 | H73: ='Balance Sheet'!I28 -> 1110.88 | I73: =Schedules!J171 -> 993.89394 | J73: =Schedules!K171 -> 1157.8864 | K73: =Schedules!L171 -> 1331.5694 | L73: =Schedules!M171 -> 1511.3313 | M73: =Schedules!N171 -> 1692.691 | N73: =Schedules!O171 -> 1895.814 | O73: =Schedules!P171 -> 2123.3116 | P73: =Schedules!Q171 -> 2378.109 | ... R73: =Schedules!S171 -> 2983.1
B74: Total Current Assets | D74: =SUM(D68:D73) -> 3906.6348 | E74: =SUM(E68:E73) -> 4406.8183 | F74: =SUM(F68:F73) -> 4327.872 | G74: =SUM(G68:G73) -> 6568.2272 | H74: =SUM(H68:H73) -> 6988.27 | I74: =SUM(I68:I73) -> 7548.9588 | J74: =SUM(J68:J73) -> 10431.506 | K74: =SUM(K68:K73) -> 13678.78 | ... R74: =SUM(R68:R73) -> 46142.355
B76: Total Assets | D76: =D74+D65 -> 6372.8332 | E76: =E74+E65 -> 9147.7908 | F76: =F74+F65 -> 9715.4755 | G76: =G74+G65 -> 11963.263 | H76: =H74+H65 -> 27759.591 | I76: =I74+I65 -> 28005.257 | J76: =J74+J65 -> 30898.265 | K76: =K74+K65 -> 34312.049 | ... R76: =R74+R65 -> 68291.465
B78: Equity & Liabilities
B80: Equity
B81: Share Capital | D81: ='Balance Sheet'!E43 -> 40.0588 | E81: ='Balance Sheet'!F43 -> 40.0588 | F81: ='Balance Sheet'!G43 -> 40.0588 | G81: ='Balance Sheet'!H43 -> 40.0588 | H81: ='Balance Sheet'!I43 -> 41.26 | I81: =H81 -> 41.26 | J81: =I81 -> 41.26 | K81: =J81 -> 41.26 | L81: =K81 -> 41.26 | M81: =L81 -> 41.26 | N81: =M81 -> 41.26 | O81: =N81 -> 41.26 | P81: =O81 -> 41.26 | ... R81: =Q81 -> 41.26
B82: Other Equity | D82: ='Balance Sheet'!E44 -> 4681.945 | E82: ='Balance Sheet'!F44 -> 6115.1733 | F82: ='Balance Sheet'!G44 -> 7395.564 | G82: ='Balance Sheet'!H44 -> 9323.0293 | H82: ='Balance Sheet'!I44 -> 14291.13 | I82: =Schedules!J152 -> 16020.455 | J82: =Schedules!K152 -> 18271.935 | K82: =Schedules!L152 -> 21016.895 | L82: =Schedules!M152 -> 24285.776 | M82: =Schedules!N152 -> 28109.551 | N82: =Schedules!O152 -> 32511.812 | O82: =Schedules!P152 -> 37562.717 | P82: =Schedules!Q152 -> 43286.885 | ... R82: =Schedules!S152 -> 57091.059
B83: Total Shareholder's Equity | D83: =D82+D81 -> 4722.0038 | E83: =E82+E81 -> 6155.2321 | F83: =F82+F81 -> 7435.6228 | G83: =G82+G81 -> 9363.0881 | H83: =H82+H81 -> 14332.39 | I83: =I82+I81 -> 16061.715 | J83: =J82+J81 -> 18313.195 | K83: =K82+K81 -> 21058.155 | ... R83: =R82+R81 -> 57132.319
B84: Non Controlling Interest | D84: ='Balance Sheet'!E46 -> 140.8874 | E84: ='Balance Sheet'!F46 -> 161.0799 | F84: ='Balance Sheet'!G46 -> 188.0701 | G84: ='Balance Sheet'!H46 -> 212.7 | H84: ='Balance Sheet'!I46 -> 235.79 | I84: =H84 -> 235.79 | J84: =I84 -> 235.79 | K84: =J84 -> 235.79 | L84: =K84 -> 235.79 | M84: =L84 -> 235.79 | N84: =M84 -> 235.79 | O84: =N84 -> 235.79 | P84: =O84 -> 235.79 | ... R84: =Q84 -> 235.79
B85: Total Equity | D85: =D83+D84 -> 4862.8912 | E85: =E83+E84 -> 6316.312 | F85: =F83+F84 -> 7623.6929 | G85: =G83+G84 -> 9575.7881 | H85: =H83+H84 -> 14568.18 | I85: =I83+I84 -> 16297.505 | J85: =J83+J84 -> 18548.985 | K85: =K83+K84 -> 21293.945 | ... R85: =R83+R84 -> 57368.109
B87: Liabilities
B89: Non-Current Liabilities
B90: Long Term Borrowing | D90: ='Balance Sheet'!E51 -> 57.4199 | E90: ='Balance Sheet'!F51 -> 49.194 | F90: ='Balance Sheet'!G51 -> 23.1865 | G90: ='Balance Sheet'!H51 -> 24.8677 | H90: ='Balance Sheet'!I51 -> 5526.19 | I90: =Schedules!J234 -> 5802.4995 | J90: =Schedules!K234 -> 6092.6245 | K90: =Schedules!L234 -> 6397.2557 | L90: =Schedules!M234 -> 6525.2008 | M90: =Schedules!N234 -> 6655.7048 | N90: =Schedules!O234 -> 6788.8189 | O90: =Schedules!P234 -> 6924.5953 | P90: =Schedules!Q234 -> 7063.0872 | ... R90: =Schedules!S234 -> 7348.4359
B91: Lease Liabilities | D91: ='Balance Sheet'!E52 -> 5.5105 | E91: ='Balance Sheet'!F52 -> 2.99 | F91: ='Balance Sheet'!G52 -> 5.178 | G91: ='Balance Sheet'!H52 -> 7.7138 | H91: ='Balance Sheet'!I52 -> 14.03 | I91: =H91 -> 14.03 | J91: =I91 -> 14.03 | K91: =J91 -> 14.03 | L91: =K91 -> 14.03 | M91: =L91 -> 14.03 | N91: =M91 -> 14.03 | O91: =N91 -> 14.03 | P91: =O91 -> 14.03 | ... R91: =Q91 -> 14.03
B92: Provisions | D92: ='Balance Sheet'!E53 -> 72.2443 | E92: ='Balance Sheet'!F53 -> 80.0043 | F92: ='Balance Sheet'!G53 -> 97.8888 | G92: ='Balance Sheet'!H53 -> 123.1246 | H92: ='Balance Sheet'!I53 -> 155.06 | I92: =H92 -> 155.06 | J92: =I92 -> 155.06 | K92: =J92 -> 155.06 | L92: =K92 -> 155.06 | M92: =L92 -> 155.06 | N92: =M92 -> 155.06 | O92: =N92 -> 155.06 | P92: =O92 -> 155.06 | ... R92: =Q92 -> 155.06
B93: Deferred tax liabilities (net) | D93: ='Balance Sheet'!E54 -> 13.0319 | E93: ='Balance Sheet'!F54 -> 55.6206 | F93: ='Balance Sheet'!G54 -> 77.3121 | G93: ='Balance Sheet'!H54 -> 89.0692 | H93: ='Balance Sheet'!I54 -> 1812.51 | I93: =H93 -> 1812.51 | J93: =I93 -> 1812.51 | K93: =J93 -> 1812.51 | L93: =K93 -> 1812.51 | M93: =L93 -> 1812.51 | N93: =M93 -> 1812.51 | O93: =N93 -> 1812.51 | P93: =O93 -> 1812.51 | ... R93: =Q93 -> 1812.51
B94: Other non-current liabilities | D94: ='Balance Sheet'!E55 -> 7.8869 | E94: ='Balance Sheet'!F55 -> 20.1542 | F94: ='Balance Sheet'!G55 -> 25.4946 | G94: ='Balance Sheet'!H55 -> 22.9615 | H94: ='Balance Sheet'!I55 -> 20 | I94: =H94 -> 20 | J94: =I94 -> 20 | K94: =J94 -> 20 | L94: =K94 -> 20 | M94: =L94 -> 20 | N94: =M94 -> 20 | O94: =N94 -> 20 | P94: =O94 -> 20 | ... R94: =Q94 -> 20
B95: Total non-current liabilities | D95: =SUM(D90:D94) -> 156.0935 | E95: =SUM(E90:E94) -> 207.9631 | F95: =SUM(F90:F94) -> 229.06 | G95: =SUM(G90:G94) -> 267.7368 | H95: =SUM(H90:H94) -> 7527.79 | I95: =SUM(I90:I94) -> 7804.0995 | J95: =SUM(J90:J94) -> 8094.2245 | K95: =SUM(K90:K94) -> 8398.8557 | ... R95: =SUM(R90:R94) -> 9350.0359
B97: Current Liabilities
B98: Trade Payables | D98: ='Balance Sheet'!E59 -> 667.1675 | E98: ='Balance Sheet'!F59 -> 1076.4388 | F98: ='Balance Sheet'!G59 -> 1007.7633 | G98: ='Balance Sheet'!H59 -> 1102.9988 | H98: ='Balance Sheet'!I59 -> 1133.4605 | I98: =Schedules!J176 -> 1610.12 | J98: =Schedules!K176 -> 1842.6877 | K98: =Schedules!L176 -> 2081.0233 | L98: =Schedules!M176 -> 2318.7548 | M98: =Schedules!N176 -> 2548.614 | N98: =Schedules!O176 -> 0 | O98: =Schedules!P176 -> -0.049297239 | P98: =Schedules!Q176 -> -0.037534769 | ... R98: =Schedules!S176 -> 0
B99: Short Term Borrowing | D99: ='Balance Sheet'!E61 -> 158.6039 | E99: ='Balance Sheet'!F61 -> 818.8332 | F99: ='Balance Sheet'!G61 -> 139.4899 | G99: ='Balance Sheet'!H61 -> 171.1681 | H99: ='Balance Sheet'!I61 -> 2956.84 | I99: =Schedules!J180 -> 720.213 | J99: =Schedules!K180 -> 839.04814 | K99: =Schedules!L180 -> 964.90537 | L99: =Schedules!M180 -> 1533.2346 | M99: =Schedules!N180 -> 1717.2228 | N99: =Schedules!O180 -> 0 | O99: =Schedules!P180 -> 0.010486302 | P99: =Schedules!Q180 -> 0.0094453742 | ... R99: =Schedules!S180 -> 0
B100: Lease Liabilities | D100: ='Balance Sheet'!E62 -> 0 | E100: ='Balance Sheet'!F62 -> 2.0572 | F100: ='Balance Sheet'!G62 -> 2.5565 | G100: ='Balance Sheet'!H62 -> 3.4228 | H100: ='Balance Sheet'!I62 -> 14.39 | I100: =H100 -> 14.39 | J100: =I100 -> 14.39 | K100: =J100 -> 14.39 | L100: =K100 -> 14.39 | M100: =L100 -> 14.39 | N100: =M100 -> 14.39 | O100: =N100 -> 14.39 | P100: =O100 -> 14.39 | ... R100: =Q100 -> 14.39
B101: Other financial liabilities | D101: ='Balance Sheet'!E63 -> 183.5869 | E101: ='Balance Sheet'!F63 -> 221.489 | F101: ='Balance Sheet'!G63 -> 236.4918 | G101: ='Balance Sheet'!H63 -> 235.5491 | H101: ='Balance Sheet'!I63 -> 674.16 | I101: =H101 -> 674.16 | J101: =I101 -> 674.16 | K101: =J101 -> 674.16 | L101: =K101 -> 674.16 | M101: =L101 -> 674.16 | N101: =M101 -> 674.16 | O101: =N101 -> 674.16 | P101: =O101 -> 674.16 | ... R101: =Q101 -> 674.16
B102: Provisions | D102: ='Balance Sheet'!E64 -> 234.2185 | E102: ='Balance Sheet'!F64 -> 264.5126 | F102: ='Balance Sheet'!G64 -> 307.6304 | G102: ='Balance Sheet'!H64 -> 389.3072 | H102: ='Balance Sheet'!I64 -> 663.87 | I102: =H102 -> 663.87 | J102: =I102 -> 663.87 | K102: =J102 -> 663.87 | L102: =K102 -> 663.87 | M102: =L102 -> 663.87 | N102: =M102 -> 663.87 | O102: =N102 -> 663.87 | P102: =O102 -> 663.87 | ... R102: =Q102 -> 663.87
B103: Current tax liabilities (net) | D103: ='Balance Sheet'!E65 -> 11.0847 | E103: ='Balance Sheet'!F65 -> 15.0896 | F103: ='Balance Sheet'!G65 -> 46.2555 | G103: ='Balance Sheet'!H65 -> 46.3787 | H103: ='Balance Sheet'!I65 -> 18.08 | I103: =H103 -> 18.08 | J103: =I103 -> 18.08 | K103: =J103 -> 18.08 | L103: =K103 -> 18.08 | M103: =L103 -> 18.08 | N103: =M103 -> 18.08 | O103: =N103 -> 18.08 | P103: =O103 -> 18.08 | ... R103: =Q103 -> 18.08
B104: Other current liabilities | D104: ='Balance Sheet'!E66 -> 99.187 | E104: ='Balance Sheet'!F66 -> 225.0953 | F104: ='Balance Sheet'!G66 -> 122.5352 | G104: ='Balance Sheet'!H66 -> 170.9131 | H104: ='Balance Sheet'!I66 -> 202.82 | I104: =H104 -> 202.82 | J104: =I104 -> 202.82 | K104: =J104 -> 202.82 | L104: =K104 -> 202.82 | M104: =L104 -> 202.82 | N104: =M104 -> 202.82 | O104: =N104 -> 202.82 | P104: =O104 -> 202.82 | ... R104: =Q104 -> 202.82
B105: Total Current liabilities | D105: =SUM(D98:D104) -> 1353.8485 | E105: =SUM(E98:E104) -> 2623.5157 | F105: =SUM(F98:F104) -> 1862.7226 | G105: =SUM(G98:G104) -> 2119.7378 | H105: =SUM(H98:H104) -> 5663.6205 | I105: =SUM(I98:I104) -> 3903.653 | J105: =SUM(J98:J104) -> 4255.0558 | K105: =SUM(K98:K104) -> 4619.2487 | ... R105: =SUM(R98:R104) -> 1573.32
B107: Total Equity & Liabilities | D107: =D105+D95+D85 -> 6372.8332 | E107: =E105+E95+E85 -> 9147.7908 | F107: =F105+F95+F85 -> 9715.4755 | G107: =G105+G95+G85 -> 11963.263 | H107: =H105+H95+H85 -> 27759.59 | I107: =I105+I95+I85 -> 28005.257 | J107: =J105+J95+J85 -> 30898.265 | K107: =K105+K95+K85 -> 34312.049 | ... R107: =R105+R95+R85 -> 68291.465
B109: Check | D109: =D107-D76 -> 0 | E109: =E107-E76 -> 0 | F109: =F107-F76 -> 0 | G109: =G107-G76 -> 0 | H109: =H107-H76 -> 0 | I109: =I107-I76 -> 0 | J109: =J107-J76 -> 0 | K109: =K107-K76 -> 0 | ... R109: =R107-R76 -> 0
B111: Net Working Capital | D111: =D74-D105 -> 2552.7863 | E111: =E74-E105 -> 1783.3026 | F111: =F74-F105 -> 2465.1494 | G111: =G74-G105 -> 4448.4894 | H111: =H74-H105 -> 1324.6495 | I111: =I74-I105 -> 3645.3057 | J111: =J74-J105 -> 6176.4498 | K111: =K74-K105 -> 9059.5317 | ... R111: =R74-R105 -> 44569.035
B112: Debtor Days | D112: =Schedules!E161 -> 0 | E112: =Schedules!F161 -> 16.857409 | F112: =Schedules!G161 -> 20.119841 | G112: =Schedules!H161 -> 25.158577 | H112: =Schedules!I161 -> 35.681033 | I112: =Schedules!J161 -> 23.823919 | J112: =Schedules!K161 -> 23.823919 | K112: =Schedules!L161 -> 25 | ... R112: =Schedules!S161 -> 25
B113: Inventory Days | D113: =Schedules!E166 -> 0 | E113: =Schedules!F166 -> 69.040067 | F113: =Schedules!G166 -> 67.971499 | G113: =Schedules!H166 -> 53.893318 | H113: =Schedules!I166 -> 54.526808 | I113: =Schedules!J166 -> 58.580766 | J113: =Schedules!K166 -> 58.580766 | K113: =Schedules!L166 -> 55 | ... R113: =Schedules!S166 -> 55
B114: Trade Payable Days | D114: =Schedules!E177 -> 0 | E114: =Schedules!F177 -> 131.39713 | F114: =Schedules!G177 -> 130.54688 | G114: =Schedules!H177 -> 120.01576 | H114: =Schedules!I177 -> 105.87538 | I114: =Schedules!J177 -> 120 | J114: =Schedules!K177 -> 120 | K114: =Schedules!L177 -> 120 | ... R114: =Schedules!S177 -> 120
B115: Other Current Assets % Sales | D115: =D73/D13 -> 0.061949905 | E115: =E73/E13 -> 0.12568322 | F115: =F73/F13 -> 0.082784759 | G115: =G73/G13 -> 0.068738916 | H115: =H73/H13 -> 0.091003523 | I115: =I73/I13 -> 0.069 | J115: =J73/J13 -> 0.069 | K115: =K73/K13 -> 0.069 | ... R115: =R73/R13 -> 0.069
B116: Other Current Liabilities % Sales | D116: =D104/D13 -> 0.015936475 | E116: =E104/E13 -> 0.028926776 | F116: =F104/F13 -> 0.01400493 | G116: =G104/G13 -> 0.016537671 | H116: =H104/H13 -> 0.016615057 | I116: =I104/I13 -> 0.014080557 | J116: =J104/J13 -> 0.012086315 | K116: =K104/K13 -> 0.010509839 | ... R116: =R104/R13 -> 0.0046912877
A118: # | B118: Cash Flow Statement
B120: Profit Before Tax | D120: ='Cash Flow'!E8 -> 1668.2801 | E120: ='Cash Flow'!F8 -> 1945.7185 | F120: ='Cash Flow'!G8 -> 1646.4122 | G120: ='Cash Flow'!H8 -> 2368.9624 | H120: ='Cash Flow'!I8 -> 2516 | I120: =I37 -> 2305.7661 | J120: =J37 -> 3001.9734 | K120: =K37 -> 3659.9467 | L120: =L37 -> 4358.5082 | M120: =M37 -> 5098.3668 | N120: =N37 -> 5869.6815 | O120: =O37 -> 6734.54 | P120: =P37 -> 7632.2238 | ... R120: =R37 -> 9766.9083
B121: Add: Depreciation | D121: =D29 -> 118.9703 | E121: =E29 -> 166.6192 | F121: =F29 -> 325.9195 | G121: =G29 -> 398.2537 | H121: =H29 -> 621 | I121: =I29 -> 661.80719 | J121: =J29 -> 706.62506 | K121: =K29 -> 764.83403 | ... R121: =R29 -> 1318.3361
B122: Add: Interest Expense | D122: ='Cash Flow'!E25 -> 3.7015 | E122: ='Cash Flow'!F25 -> 10.7409 | F122: ='Cash Flow'!G25 -> 4.226 | G122: ='Cash Flow'!H25 -> 8.1553 | H122: ='Cash Flow'!I25 -> 25.4 | I122: =I34*-1 -> 561.47041 | J122: =J34*-1 -> 503.42321 | K122: =K34*-1 -> 534.83289 | L122: =L34*-1 -> 576.99301 | M122: =M34*-1 -> 614.8129 | N122: =N34*-1 -> 567.30762 | O122: =O34*-1 -> 513.11571 | P122: =P34*-1 -> 523.37837 | ... R122: =R34*-1 -> 544.52208
B123: Add: Other Items | D123: =SUM('Cash Flow'!E10,'Cash Flow'!E12:E24) -> -106.1041 | E123: =SUM('Cash Flow'!F10,'Cash Flow'!F12:F24) -> -118.1491 | F123: =SUM('Cash Flow'!G10,'Cash Flow'!G12:G24) -> -7.7447 | G123: =SUM('Cash Flow'!H10,'Cash Flow'!H12:H24) -> -164.2506 | H123: =SUM('Cash Flow'!I10,'Cash Flow'!I12:I24) -> -36.62 | I123: 0 | J123: 0 | K123: 0 | L123: 0 | M123: 0 | N123: 0 | O123: 0 | P123: 0 | Q123: 0 | R123: 0
B124: Less: Change in Working Capital | D124: =SUM('Cash Flow'!E29:E36) -> -94.0292 | E124: =SUM('Cash Flow'!F29:F36) -> -586.1207 | F124: =SUM('Cash Flow'!G29:G36) -> 167.1674 | G124: =SUM('Cash Flow'!H29:H36) -> 20.4159 | H124: =SUM('Cash Flow'!I29:I36) -> -146.42 | I124: =Schedules!J229*-1 -> 973.69968 | J124: =Schedules!K229*-1 -> -468.00419 | K124: =Schedules!L229*-1 -> -376.49425 | L124: =Schedules!M229*-1 -> -513.04283 | M124: =Schedules!N229*-1 -> -527.58874 | N124: =Schedules!O229*-1 -> -3396.9557 | O124: =Schedules!P229*-1 -> -950.19196 | P124: =Schedules!Q229*-1 -> -1064.148 | ... R124: =Schedules!S229*-1 -> -1334.882
B125: Less: Tax Paid | D125: ='Cash Flow'!E38 -> -454.075 | E125: ='Cash Flow'!F38 -> -499.5083 | F125: ='Cash Flow'!G38 -> -323.0967 | G125: ='Cash Flow'!H38 -> -479.5338 | H125: ='Cash Flow'!I38 -> -566.75 | I125: =I39 -> -576.44153 | J125: =J39 -> -750.49335 | K125: =K39 -> -914.98667 | L125: =L39 -> -1089.6271 | M125: =M39 -> -1274.5917 | N125: =N39 -> -1467.4204 | O125: =O39 -> -1683.635 | P125: =P39 -> -1908.056 | ... R125: =R39 -> -2441.7271
B126: Net Cash Flow from Operations | D126: =SUM(D120:D125) -> 1136.7436 | E126: =SUM(E120:E125) -> 919.3005 | F126: =SUM(F120:F125) -> 1812.8837 | G126: =SUM(G120:G125) -> 2152.0029 | H126: =SUM(H120:H125) -> 2412.61 | I126: =SUM(I120:I125) -> 3926.3019 | J126: =SUM(J120:J125) -> 2993.5241 | K126: =SUM(K120:K125) -> 3668.1327 | ... R126: =SUM(R120:R125) -> 7853.1574
B128: Net Purchased of Fixed Assets | D128: =SUM('Cash Flow'!E42:E44,'Cash Flow'!E46) -> -307.6859 | E128: =SUM('Cash Flow'!F42:F44,'Cash Flow'!F46) -> -2325.368 | F128: =SUM('Cash Flow'!G42:G44,'Cash Flow'!G46) -> -826.0211 | G128: =SUM('Cash Flow'!H42:H44,'Cash Flow'!H46) -> -381.7042 | H128: =SUM('Cash Flow'!I42:I44,'Cash Flow'!I46) -> -519 | I128: =Schedules!J60*-1 -> -652.91502 | J128: =Schedules!K60*-1 -> -717.086 | K128: =Schedules!L60*-1 -> -931.34344 | L128: =Schedules!M60*-1 -> -963.94046 | M128: =Schedules!N60*-1 -> -972.50882 | N128: =Schedules!O60*-1 -> -1089.2099 | O128: =Schedules!P60*-1 -> -1219.9151 | P128: =Schedules!Q60*-1 -> -1366.3049 | ... R128: =Schedules!S60*-1 -> -1713.8928
B129: Additional CWIP | I129: =H56-I56 -> 306.13 | J129: =I56-J56 -> 0 | K129: =J56-K56 -> 0 | L129: =K56-L56 -> 0 | M129: =L56-M56 -> 0 | N129: =M56-N56 -> 0 | O129: =N56-O56 -> 0 | P129: =O56-P56 -> 0 | ... R129: =Q56-R56 -> 0
...

Sheet CommonSizeStatement
B2: ='Input Sheet'!C5 -> Mankind Pharma Ltd
B3: Common Size Statement
H4: Current Case | J4: 1
D8: Actual | I8: Explicit Forecast Period | O8: 5 Years | P8: 3 Years
B9: In INR Crores unless stated otherwise | D9: ='ControlSheet '!E9 -> 2021 | E9: ='ControlSheet '!F9 -> 2022 | F9: ='ControlSheet '!G9 -> 2023 | G9: ='ControlSheet '!H9 -> 2024 | H9: ='ControlSheet '!I9 -> 2025 | I9: ='ControlSheet '!J9 -> 2026 | J9: ='ControlSheet '!K9 -> 2027 | K9: ='ControlSheet '!L9 -> 2028 | ... M9: ='ControlSheet '!N9 -> 2030
A11: # | B11: Income Statement
B13: Revenue | D13: ='3StatementModel'!D13/'3StatementModel'!D$13 -> 1 | E13: ='3StatementModel'!E13/'3StatementModel'!E$13 -> 1 | F13: ='3StatementModel'!F13/'3StatementModel'!F$13 -> 1 | G13: ='3StatementModel'!G13/'3StatementModel'!G$13 -> 1 | H13: ='3StatementModel'!H13/'3StatementModel'!H$13 -> 1 | I13: ='3StatementModel'!I13/'3StatementModel'!I$13 -> 1 | J13: ='3StatementModel'!J13/'3StatementModel'!J$13 -> 1 | K13: ='3StatementModel'!K13/'3StatementModel'!K$13 -> 1 | ... M13: ='3StatementModel'!M13/'3StatementModel'!M$13 -> 1 | O13: =_xlfn.RRI($M$9-$H$9,H13,M13) -> 0 | P13: =_xlfn.RRI($M$9-$J$9,J13,M13) -> 0
B14: Less: Cost of Goods Sold | D14: ='3StatementModel'!D14/'3StatementModel'!D$13*-1 -> 0.28609228 | E14: ='3StatementModel'!E14/'3StatementModel'!E$13*-1 -> 0.31121394 | F14: ='3StatementModel'!F14/'3StatementModel'!F$13*-1 -> 0.33300924 | G14: ='3StatementModel'!G14/'3StatementModel'!G$13*-1 -> 0.31057241 | H14: ='3StatementModel'!H14/'3StatementModel'!H$13*-1 -> 0.31580569 | I14: ='3StatementModel'!I14/'3StatementModel'!I$13*-1 -> 0.34 | J14: ='3StatementModel'!J14/'3StatementModel'!J$13*-1 -> 0.334 | K14: ='3StatementModel'!K14/'3StatementModel'!K$13*-1 -> 0.328 | ... M14: ='3StatementModel'!M14/'3StatementModel'!M$13*-1 -> 0.316 | O14: =_xlfn.RRI($M$9-$H$9,H14,M14) -> 0.00012302941 | P14: =_xlfn.RRI($M$9-$J$9,J14,M14) -> -0.018296803
B15: Gross Profit | D15: ='3StatementModel'!D15/'3StatementModel'!D$13 -> 0.71390772 | E15: ='3StatementModel'!E15/'3StatementModel'!E$13 -> 0.68878606 | F15: ='3StatementModel'!F15/'3StatementModel'!F$13 -> 0.66699076 | G15: ='3StatementModel'!G15/'3StatementModel'!G$13 -> 0.68942759 | H15: ='3StatementModel'!H15/'3StatementModel'!H$13 -> 0.68419431 | I15: ='3StatementModel'!I15/'3StatementModel'!I$13 -> 0.66 | J15: ='3StatementModel'!J15/'3StatementModel'!J$13 -> 0.666 | K15: ='3StatementModel'!K15/'3StatementModel'!K$13 -> 0.672 | ... M15: ='3StatementModel'!M15/'3StatementModel'!M$13 -> 0.684 | O15: =_xlfn.RRI($M$9-$H$9,H15,M15) -> -5.6807492e-05 | P15: =_xlfn.RRI($M$9-$J$9,J15,M15) -> 0.0089290439
B17: Gross Margin | D17: 0.71390772 | E17: 0.68878606 | F17: 0.66699076 | G17: 0.68942759 | H17: 0.68419431 | I17: 0.66 | J17: 0.666 | K17: 0.672 | L17: 0.678 | M17: 0.684
B19: Less: SG&A Expenses (Excluding Depreciation & Interest)
B20: Employee Benefit Expense | D20: ='3StatementModel'!D20/'3StatementModel'!D$13 -> 0.22747159 | E20: ='3StatementModel'!E20/'3StatementModel'!E$13 -> 0.20825914 | F20: ='3StatementModel'!F20/'3StatementModel'!F$13 -> 0.21926564 | G20: ='3StatementModel'!G20/'3StatementModel'!G$13 -> 0.22010156 | H20: ='3StatementModel'!H20/'3StatementModel'!H$13 -> 0.2205292 | I20: ='3StatementModel'!I20/'3StatementModel'!I$13 -> 0.22 | J20: ='3StatementModel'!J20/'3StatementModel'!J$13 -> 0.22 | K20: ='3StatementModel'!K20/'3StatementModel'!K$13 -> 0.22 | ... M20: ='3StatementModel'!M20/'3StatementModel'!M$13 -> 0.22 | O20: =_xlfn.RRI($M$9-$H$9,H20,M20) -> -0.00048040191 | P20: =_xlfn.RRI($M$9-$J$9,J20,M20) -> 0
B21: Advertising & Sales Promotion Expense | D21: ='3StatementModel'!D21/'3StatementModel'!D$13 -> 0.061977235 | E21: ='3StatementModel'!E21/'3StatementModel'!E$13 -> 0.058029532 | F21: ='3StatementModel'!F21/'3StatementModel'!F$13 -> 0.042707407 | G21: ='3StatementModel'!G21/'3StatementModel'!G$13 -> 0.058433031 | H21: ='3StatementModel'!H21/'3StatementModel'!H$13 -> 0.061849758 | I21: ='3StatementModel'!I21/'3StatementModel'!I$13 -> 0.058 | J21: ='3StatementModel'!J21/'3StatementModel'!J$13 -> 0.058 | K21: ='3StatementModel'!K21/'3StatementModel'!K$13 -> 0.058 | ... M21: ='3StatementModel'!M21/'3StatementModel'!M$13 -> 0.058 | O21: =_xlfn.RRI($M$9-$H$9,H21,M21) -> -0.012770789 | P21: =_xlfn.RRI($M$9-$J$9,J21,M21) -> 0
B22: Travelling and conveyance Expense | D22: ='3StatementModel'!D22/'3StatementModel'!D$13 -> 0.043445441 | E22: ='3StatementModel'!E22/'3StatementModel'!E$13 -> 0.046020364 | F22: ='3StatementModel'!F22/'3StatementModel'!F$13 -> 0.056694748 | G22: ='3StatementModel'!G22/'3StatementModel'!G$13 -> 0.036614267 | H22: ='3StatementModel'!H22/'3StatementModel'!H$13 -> 0.037765217 | I22: ='3StatementModel'!I22/'3StatementModel'!I$13 -> 0.046 | J22: ='3StatementModel'!J22/'3StatementModel'!J$13 -> 0.046 | K22: ='3StatementModel'!K22/'3StatementModel'!K$13 -> 0.046 | ... M22: ='3StatementModel'!M22/'3StatementModel'!M$13 -> 0.046 | O22: =_xlfn.RRI($M$9-$H$9,H22,M22) -> 0.040239091 | P22: =_xlfn.RRI($M$9-$J$9,J22,M22) -> 0
B23: Other Operating Expense | D23: ='3StatementModel'!D23/'3StatementModel'!D$13 -> 0.059441846 | E23: ='3StatementModel'!E23/'3StatementModel'!E$13 -> 0.065664253 | F23: ='3StatementModel'!F23/'3StatementModel'!F$13 -> 0.070768529 | G23: ='3StatementModel'!G23/'3StatementModel'!G$13 -> 0.077786834 | H23: ='3StatementModel'!H23/'3StatementModel'!H$13 -> 0.087900385 | I23: ='3StatementModel'!I23/'3StatementModel'!I$13 -> 0.066 | J23: ='3StatementModel'!J23/'3StatementModel'!J$13 -> 0.066 | K23: ='3StatementModel'!K23/'3StatementModel'!K$13 -> 0.066 | ... M23: ='3StatementModel'!M23/'3StatementModel'!M$13 -> 0.066 | O23: =_xlfn.RRI($M$9-$H$9,H23,M23) -> -0.055698604 | P23: =_xlfn.RRI($M$9-$J$9,J23,M23) -> 0
B24: Other Misc SG&A Expenses | D24: ='3StatementModel'!D24/'3StatementModel'!D$13 -> 0.055244509 | E24: ='3StatementModel'!E24/'3StatementModel'!E$13 -> 0.055161275 | F24: ='3StatementModel'!F24/'3StatementModel'!F$13 -> 0.060322297 | G24: ='3StatementModel'!G24/'3StatementModel'!G$13 -> 0.051193531 | H24: ='3StatementModel'!H24/'3StatementModel'!H$13 -> 0.058908823 | I24: ='3StatementModel'!I24/'3StatementModel'!I$13 -> 0.055 | J24: ='3StatementModel'!J24/'3StatementModel'!J$13 -> 0.055 | K24: ='3StatementModel'!K24/'3StatementModel'!K$13 -> 0.055 | ... M24: ='3StatementModel'!M24/'3StatementModel'!M$13 -> 0.055 | O24: =_xlfn.RRI($M$9-$H$9,H24,M24) -> -0.01363769 | P24: =_xlfn.RRI($M$9-$J$9,J24,M24) -> 0
B25: EBITDA | D25: ='3StatementModel'!D25/'3StatementModel'!D$13 -> 0.26632711 | E25: ='3StatementModel'!E25/'3StatementModel'!E$13 -> 0.2556515 | F25: ='3StatementModel'!F25/'3StatementModel'!F$13 -> 0.21723215 | G25: ='3StatementModel'!G25/'3StatementModel'!G$13 -> 0.24529836 | H25: ='3StatementModel'!H25/'3StatementModel'!H$13 -> 0.21724093 | I25: ='3StatementModel'!I25/'3StatementModel'!I$13 -> 0.215 | J25: ='3StatementModel'!J25/'3StatementModel'!J$13 -> 0.221 | K25: ='3StatementModel'!K25/'3StatementModel'!K$13 -> 0.227 | ... M25: ='3StatementModel'!M25/'3StatementModel'!M$13 -> 0.239 | O25: =_xlfn.RRI($M$9-$H$9,H25,M25) -> 0.019274714 | P25: =_xlfn.RRI($M$9-$J$9,J25,M25) -> 0.026443879
B27: EBITDA Margin | D27: 0.26632711 | E27: 0.2556515 | F27: 0.21723215 | G27: 0.24529836 | H27: 0.21724093 | I27: 0.215 | J27: 0.221 | K27: 0.227 | L27: 0.233 | M27: 0.239
B29: Less: Depreciation | D29: ='3StatementModel'!D29/'3StatementModel'!D$13 -> 0.019115078 | E29: ='3StatementModel'!E29/'3StatementModel'!E$13 -> 0.02141207 | F29: ='3StatementModel'!F29/'3StatementModel'!F$13 -> 0.037250357 | G29: ='3StatementModel'!G29/'3StatementModel'!G$13 -> 0.038535306 | H29: ='3StatementModel'!H29/'3StatementModel'!H$13 -> 0.05087245 | I29: ='3StatementModel'!I29/'3StatementModel'!I$13 -> 0.04594524 | J29: ='3StatementModel'!J29/'3StatementModel'!J$13 -> 0.042108732 | K29: ='3StatementModel'!K29/'3StatementModel'!K$13 -> 0.039632593 | ... M29: ='3StatementModel'!M29/'3StatementModel'!M$13 -> 0.036110834 | O29: =_xlfn.RRI($M$9-$H$9,H29,M29) -> -0.066249228 | P29: =_xlfn.RRI($M$9-$J$9,J29,M29) -> -0.049931058
B30: EBIT | D30: ='3StatementModel'!D30/'3StatementModel'!D$13 -> 0.24721203 | E30: ='3StatementModel'!E30/'3StatementModel'!E$13 -> 0.23423943 | F30: ='3StatementModel'!F30/'3StatementModel'!F$13 -> 0.17998179 | G30: ='3StatementModel'!G30/'3StatementModel'!G$13 -> 0.20676306 | H30: ='3StatementModel'!H30/'3StatementModel'!H$13 -> 0.16636848 | I30: ='3StatementModel'!I30/'3StatementModel'!I$13 -> 0.16905476 | J30: ='3StatementModel'!J30/'3StatementModel'!J$13 -> 0.17889127 | K30: ='3StatementModel'!K30/'3StatementModel'!K$13 -> 0.18736741 | ... M30: ='3StatementModel'!M30/'3StatementModel'!M$13 -> 0.20288917 | O30: =_xlfn.RRI($M$9-$H$9,H30,M30) -> 0.040489167 | P30: =_xlfn.RRI($M$9-$J$9,J30,M30) -> 0.042853343
B32: EBIT Margin | D32: 0.24721203 | E32: 0.23423943 | F32: 0.17998179 | G32: 0.20676306 | H32: 0.16636848 | I32: 0.16905476 | J32: 0.17889127 | K32: 0.18736741 | L32: 0.19533087 | M32: 0.20288917
B34: Less: Interest | D34: ='3StatementModel'!D34/'3StatementModel'!D$13 -> -0.0032371031 | E34: ='3StatementModel'!E34/'3StatementModel'!E$13 -> -0.0075319649 | F34: ='3StatementModel'!F34/'3StatementModel'!F$13 -> -0.0050825008 | G34: ='3StatementModel'!G34/'3StatementModel'!G$13 -> -0.003244541 | H34: ='3StatementModel'!H34/'3StatementModel'!H$13 -> -0.035176538 | I34: ='3StatementModel'!I34/'3StatementModel'!I$13 -> -0.038979469 | J34: ='3StatementModel'!J34/'3StatementModel'!J$13 -> -0.029999662 | K34: ='3StatementModel'!K34/'3StatementModel'!K$13 -> -0.027714266 | ... M34: ='3StatementModel'!M34/'3StatementModel'!M$13 -> -0.025061922
B35: Add: Other Income | D35: ='3StatementModel'!D35/'3StatementModel'!D$13 -> 0.025945492 | E35: ='3StatementModel'!E35/'3StatementModel'!E$13 -> 0.025191571 | F35: ='3StatementModel'!F35/'3StatementModel'!F$13 -> 0.014694301 | G35: ='3StatementModel'!G35/'3StatementModel'!G$13 -> 0.027176006 | H35: ='3StatementModel'!H35/'3StatementModel'!H$13 -> 0.043973949 | I35: ='3StatementModel'!I35/'3StatementModel'!I$13 -> 0.03 | J35: ='3StatementModel'!J35/'3StatementModel'!J$13 -> 0.03 | K35: ='3StatementModel'!K35/'3StatementModel'!K$13 -> 0.03 | ... M35: ='3StatementModel'!M35/'3StatementModel'!M$13 -> 0.03
B36: Less: Share of net profit of associates and joint ventures | D36: ='3StatementModel'!D36/'3StatementModel'!D$13 -> -0.0018761714 | E36: ='3StatementModel'!E36/'3StatementModel'!E$13 -> -0.0018566597 | F36: ='3StatementModel'!F36/'3StatementModel'!F$13 -> -0.0014200006 | G36: ='3StatementModel'!G36/'3StatementModel'!G$13 -> -0.0014720689 | H36: ='3StatementModel'!H36/'3StatementModel'!H$13 -> -0.0010027034 | I36: ='3StatementModel'!I36/'3StatementModel'!I$13 -> 0 | J36: ='3StatementModel'!J36/'3StatementModel'!J$13 -> 0 | K36: ='3StatementModel'!K36/'3StatementModel'!K$13 -> 0 | ... M36: ='3StatementModel'!M36/'3StatementModel'!M$13 -> 0
B37: EBT | D37: ='3StatementModel'!D37/'3StatementModel'!D$13 -> 0.26804425 | E37: ='3StatementModel'!E37/'3StatementModel'!E$13 -> 0.25004237 | F37: ='3StatementModel'!F37/'3StatementModel'!F$13 -> 0.18817359 | G37: ='3StatementModel'!G37/'3StatementModel'!G$13 -> 0.22922245 | H37: ='3StatementModel'!H37/'3StatementModel'!H$13 -> 0.17416319 | I37: ='3StatementModel'!I37/'3StatementModel'!I$13 -> 0.16007529 | J37: ='3StatementModel'!J37/'3StatementModel'!J$13 -> 0.17889161 | K37: ='3StatementModel'!K37/'3StatementModel'!K$13 -> 0.18965314 | ... M37: ='3StatementModel'!M37/'3StatementModel'!M$13 -> 0.20782724
B39: Less: Taxes | D39: ='3StatementModel'!D39/'3StatementModel'!D$13 -> -0.064040877 | E39: ='3StatementModel'!E39/'3StatementModel'!E$13 -> -0.067035894 | F39: ='3StatementModel'!F39/'3StatementModel'!F$13 -> -0.041324198 | G39: ='3StatementModel'!G39/'3StatementModel'!G$13 -> -0.044276389 | H39: ='3StatementModel'!H39/'3StatementModel'!H$13 -> -0.041758008 | I39: ='3StatementModel'!I39/'3StatementModel'!I$13 -> -0.040018823 | J39: ='3StatementModel'!J39/'3StatementModel'!J$13 -> -0.044722902 | K39: ='3StatementModel'!K39/'3StatementModel'!K$13 -> -0.047413285 | ... M39: ='3StatementModel'!M39/'3StatementModel'!M$13 -> -0.051956811 | O39: =_xlfn.RRI($M$9-$H$9,H39,M39) -> 0.044673416 | P39: =_xlfn.RRI($M$9-$J$9,J39,M39) -> 0.051245552
B40: Net Income | D40: ='3StatementModel'!D40/'3StatementModel'!D$13 -> 0.20400337 | E40: ='3StatementModel'!E40/'3StatementModel'!E$13 -> 0.18300648 | F40: ='3StatementModel'!F40/'3StatementModel'!F$13 -> 0.14684939 | G40: ='3StatementModel'!G40/'3StatementModel'!G$13 -> 0.18494607 | H40: ='3StatementModel'!H40/'3StatementModel'!H$13 -> 0.13240518 | I40: ='3StatementModel'!I40/'3StatementModel'!I$13 -> 0.12005647 | J40: ='3StatementModel'!J40/'3StatementModel'!J$13 -> 0.1341687 | K40: ='3StatementModel'!K40/'3StatementModel'!K$13 -> 0.14223986 | ... M40: ='3StatementModel'!M40/'3StatementModel'!M$13 -> 0.15587043 | O40: =_xlfn.RRI($M$9-$H$9,H40,M40) -> 0.033169923 | P40: =_xlfn.RRI($M$9-$J$9,J40,M40) -> 0.051245552
B42: Sales Growth % | D42: 0 | E42: 0.2502703 | F42: 0.12438104 | G42: 0.18119364 | H42: 0.18115784 | I42: 0.18 | J42: 0.165 | K42: 0.15 | L42: 0.135 | M42: 0.12
B43: Gross Profit Margins % | D43: 0.71390772 | E43: 0.68878606 | F43: 0.66699076 | G43: 0.68942759 | H43: 0.68419431 | I43: 0.66 | J43: 0.666 | K43: 0.672 | L43: 0.678 | M43: 0.684
B44: EBITDA Margins % | D44: 0.26632711 | E44: 0.2556515 | F44: 0.21723215 | G44: 0.24529836 | H44: 0.21724093 | I44: 0.215 | J44: 0.221 | K44: 0.227 | L44: 0.233 | M44: 0.239
B45: EBIT Margins % | D45: 0.24721203 | E45: 0.23423943 | F45: 0.17998179 | G45: 0.20676306 | H45: 0.16636848 | I45: 0.16905476 | J45: 0.17889127 | K45: 0.18736741 | L45: 0.19533087 | M45: 0.20288917
B46: Actual Tax Rate % | D46: -0.23891905 | E46: -0.26809813 | F46: -0.21960679 | G46: -0.19315904 | H46: -0.23976369 | I46: -0.25 | J46: -0.25 | K46: -0.25 | L46: -0.25 | M46: -0.25
B47: Net Income Margin % | D47: 0.20400337 | E47: 0.18300648 | F47: 0.14684939 | G47: 0.18494607 | H47: 0.13240518 | I47: 0.12005647 | J47: 0.1341687 | K47: 0.14223986 | L47: 0.14924114 | M47: 0.15587043
A49: # | B49: Balance Sheet
B51: Assets
B53: Non Current Assets
B54: Property , Plants & Equipments | D54: ='3StatementModel'!D54/'3StatementModel'!D$76 -> 0.2542478 | E54: ='3StatementModel'!E54/'3StatementModel'!E$76 -> 0.18063428 | F54: ='3StatementModel'!F54/'3StatementModel'!F$76 -> 0.24800234 | G54: ='3StatementModel'!G54/'3StatementModel'!G$76 -> 0.23509804 | H54: ='3StatementModel'!H54/'3StatementModel'!H$76 -> 0.098727339 | I54: ='3StatementModel'!I54/'3StatementModel'!I$76 -> 0.1148613 | J54: ='3StatementModel'!J54/'3StatementModel'!J$76 -> 0.12014148 | K54: ='3StatementModel'!K54/'3StatementModel'!K$76 -> 0.12717557 | ... M54: ='3StatementModel'!M54/'3StatementModel'!M$76 -> 0.12963452
B55: Right of Use Assets | D55: ='3StatementModel'!D55/'3StatementModel'!D$76 -> 0 | E55: ='3StatementModel'!E55/'3StatementModel'!E$76 -> 0.0073632095 | F55: ='3StatementModel'!F55/'3StatementModel'!F$76 -> 0.011771395 | G55: ='3StatementModel'!G55/'3StatementModel'!G$76 -> 0.0099522432 | H55: ='3StatementModel'!H55/'3StatementModel'!H$76 -> 0.0060249448 | I55: ='3StatementModel'!I55/'3StatementModel'!I$76 -> 0.0056756968 | J55: ='3StatementModel'!J55/'3StatementModel'!J$76 -> 0.0048756361 | K55: ='3StatementModel'!K55/'3StatementModel'!K$76 -> 0.0041486314 | ... M55: ='3StatementModel'!M55/'3StatementModel'!M$76 -> 0.0029323171
B56: Capital Work in Progress | D56: ='3StatementModel'!D56/'3StatementModel'!D$76 -> 0.058312557 | E56: ='3StatementModel'!E56/'3StatementModel'!E$76 -> 0.073227888 | F56: ='3StatementModel'!F56/'3StatementModel'!F$76 -> 0.050763547 | G56: ='3StatementModel'!G56/'3StatementModel'!G$76 -> 0.017310821 | H56: ='3StatementModel'!H56/'3StatementModel'!H$76 -> 0.0110279 | I56: ='3StatementModel'!I56/'3StatementModel'!I$76 -> 0 | J56: ='3StatementModel'!J56/'3StatementModel'!J$76 -> 0 | K56: ='3StatementModel'!K56/'3StatementModel'!K$76 -> 0 | ... M56: ='3StatementModel'!M56/'3StatementModel'!M$76 -> 0
B57: Goodwill | D57: ='3StatementModel'!D57/'3StatementModel'!D$76 -> 0.0032077099 | E57: ='3StatementModel'!E57/'3StatementModel'!E$76 -> 0.0022346598 | F57: ='3StatementModel'!F57/'3StatementModel'!F$76 -> 0.0020608873 | G57: ='3StatementModel'!G57/'3StatementModel'!G$76 -> 0.0016736655 | H57: ='3StatementModel'!H57/'3StatementModel'!H$76 -> 0.23386512 | I57: ='3StatementModel'!I57/'3StatementModel'!I$76 -> 0.23181362 | J57: ='3StatementModel'!J57/'3StatementModel'!J$76 -> 0.21010889 | K57: ='3StatementModel'!K57/'3StatementModel'!K$76 -> 0.18920467 | ... M57: ='3StatementModel'!M57/'3StatementModel'!M$76 -> 0.15138844
B58: Other Intangible Asset | D58: ='3StatementModel'!D58/'3StatementModel'!D$76 -> 0.0028917437 | E58: ='3StatementModel'!E58/'3StatementModel'!E$76 -> 0.20142734 | F58: ='3StatementModel'!F58/'3StatementModel'!F$76 -> 0.17512918 | G58: ='3StatementModel'!G58/'3StatementModel'!G$76 -> 0.1327681 | H58: ='3StatementModel'!H58/'3StatementModel'!H$76 -> 0.3459943 | I58: ='3StatementModel'!I58/'3StatementModel'!I$76 -> 0.32593804 | J58: ='3StatementModel'!J58/'3StatementModel'!J$76 -> 0.27999299 | K58: ='3StatementModel'!K58/'3StatementModel'!K$76 -> 0.23824331 | ... M58: ='3StatementModel'!M58/'3StatementModel'!M$76 -> 0.16839407
B59: Non Current Financial Assets | D59: ='3StatementModel'!D59/'3StatementModel'!D$76 -> 0.010673275 | E59: ='3StatementModel'!E59/'3StatementModel'!E$76 -> 0.010455486 | F59: ='3StatementModel'!F59/'3StatementModel'!F$76 -> 0.021109445 | G59: ='3StatementModel'!G59/'3StatementModel'!G$76 -> 0.012984368 | H59: ='3StatementModel'!H59/'3StatementModel'!H$76 -> 0.012989024 | I59: ='3StatementModel'!I59/'3StatementModel'!I$76 -> 0.012875083 | J59: ='3StatementModel'!J59/'3StatementModel'!J$76 -> 0.011669587 | K59: ='3StatementModel'!K59/'3StatementModel'!K$76 -> 0.010508553 | ... M59: ='3StatementModel'!M59/'3StatementModel'!M$76 -> 0.0084082148
B60: Other Non Current Assets | D60: ='3StatementModel'!D60/'3StatementModel'!D$76 -> 0.015170113 | E60: ='3StatementModel'!E60/'3StatementModel'!E$76 -> 0.0081095318 | F60: ='3StatementModel'!F60/'3StatementModel'!F$76 -> 0.0075503253 | G60: ='3StatementModel'!G60/'3StatementModel'!G$76 -> 0.0055403866 | H60: ='3StatementModel'!H60/'3StatementModel'!H$76 -> 0.0033235361 | I60: ='3StatementModel'!I60/'3StatementModel'!I$76 -> 0.0032943815 | J60: ='3StatementModel'!J60/'3StatementModel'!J$76 -> 0.0029859282 | K60: ='3StatementModel'!K60/'3StatementModel'!K$76 -> 0.0026888514 | ... M60: ='3StatementModel'!M60/'3StatementModel'!M$76 -> 0.0021514322
B61: Deffered Tax Assets | D61: ='3StatementModel'!D61/'3StatementModel'!D$76 -> 0.007690614 | E61: ='3StatementModel'!E61/'3StatementModel'!E$76 -> 0.0042946107 | F61: ='3StatementModel'!F61/'3StatementModel'!F$76 -> 0.0030648937 | G61: ='3StatementModel'!G61/'3StatementModel'!G$76 -> 0.0067203657 | H61: ='3StatementModel'!H61/'3StatementModel'!H$76 -> 0.0038865847 | I61: ='3StatementModel'!I61/'3StatementModel'!I$76 -> 0.003852491 | J61: ='3StatementModel'!J61/'3StatementModel'!J$76 -> 0.0034917818 | K61: ='3StatementModel'!K61/'3StatementModel'!K$76 -> 0.0031443765 | ... M61: ='3StatementModel'!M61/'3StatementModel'!M$76 -> 0.0025159117
B62: Income Tax Assets | D62: ='3StatementModel'!D62/'3StatementModel'!D$76 -> 0.0087254127 | E62: ='3StatementModel'!E62/'3StatementModel'!E$76 -> 0.0087260631 | F62: ='3StatementModel'!F62/'3StatementModel'!F$76 -> 0.010551753 | G62: ='3StatementModel'!G62/'3StatementModel'!G$76 -> 0.0068529716 | H62: ='3StatementModel'!H62/'3StatementModel'!H$76 -> 0.0068261093 | I62: ='3StatementModel'!I62/'3StatementModel'!I$76 -> 0.0067662296 | J62: ='3StatementModel'!J62/'3StatementModel'!J$76 -> 0.0061327068 | K62: ='3StatementModel'!K62/'3StatementModel'!K$76 -> 0.0055225498 | ... M62: ='3StatementModel'!M62/'3StatementModel'!M$76 -> 0.0044187609
B63: Intangible Assets Under Development | D63: ='3StatementModel'!D63/'3StatementModel'!D$76 -> 5.2347204e-05 | E63: ='3StatementModel'!E63/'3StatementModel'!E$76 -> 0.0034541564 | F63: ='3StatementModel'!F63/'3StatementModel'!F$76 -> 0.0058621526 | G63: ='3StatementModel'!G63/'3StatementModel'!G$76 -> 0.0062440491 | H63: ='3StatementModel'!H63/'3StatementModel'!H$76 -> 0.018715694 | I63: ='3StatementModel'!I63/'3StatementModel'!I$76 -> 0.018551517 | J63: ='3StatementModel'!J63/'3StatementModel'!J$76 -> 0.016814536 | K63: ='3StatementModel'!K63/'3StatementModel'!K$76 -> 0.01514162 | ... M63: ='3StatementModel'!M63/'3StatementModel'!M$76 -> 0.012115273
B64: Investments in associates | D64: ='3StatementModel'!D64/'3StatementModel'!D$76 -> 0.026014615 | E64: ='3StatementModel'!E64/'3StatementModel'!E$76 -> 0.018336974 | F64: ='3StatementModel'!F64/'3StatementModel'!F$76 -> 0.018672395 | G64: ='3StatementModel'!G64/'3StatementModel'!G$76 -> 0.015821888 | H64: ='3StatementModel'!H64/'3StatementModel'!H$76 -> 0.0068769026 | I64: ='3StatementModel'!I64/'3StatementModel'!I$76 -> 0.0068165773 | J64: ='3StatementModel'!J64/'3StatementModel'!J$76 -> 0.0061783405 | K64: ='3StatementModel'!K64/'3StatementModel'!K$76 -> 0.0055636433 | ... M64: ='3StatementModel'!M64/'3StatementModel'!M$76 -> 0.004451641
B65: Total Non Current Assets | D65: ='3StatementModel'!D65/'3StatementModel'!D$76 -> 0.38698618 | E65: ='3StatementModel'!E65/'3StatementModel'!E$76 -> 0.5182642 | F65: ='3StatementModel'!F65/'3StatementModel'!F$76 -> 0.55453832 | G65: ='3StatementModel'!G65/'3StatementModel'!G$76 -> 0.4509669 | H65: ='3StatementModel'!H65/'3StatementModel'!H$76 -> 0.74825745 | I65: ='3StatementModel'!I65/'3StatementModel'!I$76 -> 0.73044494 | J65: ='3StatementModel'!J65/'3StatementModel'!J$76 -> 0.66239186 | K65: ='3StatementModel'!K65/'3StatementModel'!K$76 -> 0.60134178 | ... M65: ='3StatementModel'!M65/'3StatementModel'!M$76 -> 0.48641059
B67: Current Assets
B68: Cash | D68: ='3StatementModel'!D68/'3StatementModel'!D$76 -> 0.026233544 | E68: ='3StatementModel'!E68/'3StatementModel'!E$76 -> 0.033071887 | F68: ='3StatementModel'!F68/'3StatementModel'!F$76 -> 0.031374759 | G68: ='3StatementModel'!G68/'3StatementModel'!G$76 -> 0.031931715 | H68: ='3StatementModel'!H68/'3StatementModel'!H$76 -> 0.014674568 | I68: ='3StatementModel'!I68/'3StatementModel'!I$76 -> 0.041447137 | J68: ='3StatementModel'!J68/'3StatementModel'!J$76 -> 0.09752995 | K68: ='3StatementModel'!K68/'3StatementModel'!K$76 -> 0.15438575 | ... M68: ='3StatementModel'!M68/'3StatementModel'!M$76 -> 0.26606408
B69: Bank balance | D69: ='3StatementModel'!D69/'3StatementModel'!D$76 -> 0.083724112 | E69: ='3StatementModel'!E69/'3StatementModel'!E$76 -> 0.011304019 | F69: ='3StatementModel'!F69/'3StatementModel'!F$76 -> 0.015272325 | G69: ='3StatementModel'!G69/'3StatementModel'!G$76 -> 0.068205783 | H69: ='3StatementModel'!H69/'3StatementModel'!H$76 -> 0.0053005105 | I69: ='3StatementModel'!I69/'3StatementModel'!I$76 -> 0.0052540135 | J69: ='3StatementModel'!J69/'3StatementModel'!J$76 -> 0.0047620797 | K69: ='3StatementModel'!K69/'3StatementModel'!K$76 -> 0.0042882895 | ... M69: ='3StatementModel'!M69/'3StatementModel'!M$76 -> 0.0034311915
B70: Inventory | D70: ='3StatementModel'!D70/'3StatementModel'!D$76 -> 0.1857161 | E70: ='3StatementModel'!E70/'3StatementModel'!E$76 -> 0.19242221 | F70: ='3StatementModel'!F70/'3StatementModel'!F$76 -> 0.15423416 | G70: ='3StatementModel'!G70/'3StatementModel'!G$76 -> 0.12985264 | H70: ='3StatementModel'!H70/'3StatementModel'!H$76 -> 0.075422943 | I70: ='3StatementModel'!I70/'3StatementModel'!I$76 -> 0.082549333 | J70: ='3StatementModel'!J70/'3StatementModel'!J$76 -> 0.087165569 | K70: ='3StatementModel'!K70/'3StatementModel'!K$76 -> 0.084749645 | ... M70: ='3StatementModel'!M70/'3StatementModel'!M$76 -> 0.086201065
B71: Receivable | D71: ='3StatementModel'!D71/'3StatementModel'!D$76 -> 0.051878229 | E71: ='3StatementModel'!E71/'3StatementModel'!E$76 -> 0.042432759 | F71: ='3StatementModel'!F71/'3StatementModel'!F$76 -> 0.05933023 | G71: ='3StatementModel'!G71/'3StatementModel'!G$76 -> 0.070907178 | H71: ='3StatementModel'!H71/'3StatementModel'!H$76 -> 0.055416524 | I71: ='3StatementModel'!I71/'3StatementModel'!I$76 -> 0.033571575 | J71: ='3StatementModel'!J71/'3StatementModel'!J$76 -> 0.035448929 | K71: ='3StatementModel'!K71/'3StatementModel'!K$76 -> 0.038522566 | ... M71: ='3StatementModel'!M71/'3StatementModel'!M$76 -> 0.039182302
B72: Investments | D72: ='3StatementModel'!D72/'3StatementModel'!D$76 -> 0.20495972 | E72: ='3StatementModel'!E72/'3StatementModel'!E$76 -> 0.095592676 | F72: ='3StatementModel'!F72/'3StatementModel'!F$76 -> 0.11069701 | G72: ='3StatementModel'!G72/'3StatementModel'!G$76 -> 0.18875389 | H72: ='3StatementModel'!H72/'3StatementModel'!H$76 -> 0.06091012 | I72: ='3StatementModel'!I72/'3StatementModel'!I$76 -> 0.071243452 | J72: ='3StatementModel'!J72/'3StatementModel'!J$76 -> 0.075227452 | K72: ='3StatementModel'!K72/'3StatementModel'!K$76 -> 0.077904336 | ... M72: ='3StatementModel'!M72/'3StatementModel'!M$76 -> 0.079238524
B73: Other Current Assets | D73: ='3StatementModel'!D73/'3StatementModel'!D$76 -> 0.060502117 | E73: ='3StatementModel'!E73/'3StatementModel'!E$76 -> 0.10691225 | F73: ='3StatementModel'!F73/'3StatementModel'!F$76 -> 0.074553191 | G73: ='3StatementModel'!G73/'3StatementModel'!G$76 -> 0.059381894 | H73: ='3StatementModel'!H73/'3StatementModel'!H$76 -> 0.040017881 | I73: ='3StatementModel'!I73/'3StatementModel'!I$76 -> 0.035489549 | J73: ='3StatementModel'!J73/'3StatementModel'!J$76 -> 0.037474157 | K73: ='3StatementModel'!K73/'3StatementModel'!K$76 -> 0.038807633 | ... M73: ='3StatementModel'!M73/'3StatementModel'!M$76 -> 0.039472251
B74: Total Current Assets | D74: ='3StatementModel'!D74/'3StatementModel'!D$76 -> 0.61301382 | E74: ='3StatementModel'!E74/'3StatementModel'!E$76 -> 0.4817358 | F74: ='3StatementModel'!F74/'3StatementModel'!F$76 -> 0.44546168 | G74: ='3StatementModel'!G74/'3StatementModel'!G$76 -> 0.5490331 | H74: ='3StatementModel'!H74/'3StatementModel'!H$76 -> 0.25174255 | I74: ='3StatementModel'!I74/'3StatementModel'!I$76 -> 0.26955506 | J74: ='3StatementModel'!J74/'3StatementModel'!J$76 -> 0.33760814 | K74: ='3StatementModel'!K74/'3StatementModel'!K$76 -> 0.39865822 | ... M74: ='3StatementModel'!M74/'3StatementModel'!M$76 -> 0.51358941
B76: Total Assets | D76: ='3StatementModel'!D76/'3StatementModel'!D$76 -> 1 | E76: ='3StatementModel'!E76/'3StatementModel'!E$76 -> 1 | F76: ='3StatementModel'!F76/'3StatementModel'!F$76 -> 1 | G76: ='3StatementModel'!G76/'3StatementModel'!G$76 -> 1 | H76: ='3StatementModel'!H76/'3StatementModel'!H$76 -> 1 | I76: ='3StatementModel'!I76/'3StatementModel'!I$76 -> 1 | J76: ='3StatementModel'!J76/'3StatementModel'!J$76 -> 1 | K76: ='3StatementModel'!K76/'3StatementModel'!K$76 -> 1 | ... M76: ='3StatementModel'!M76/'3StatementModel'!M$76 -> 1
B78: Equity & Liabilities
B80: Equity
B81: Share Capital | D81: ='3StatementModel'!D81/'3StatementModel'!D$107 -> 0.0062858698 | E81: ='3StatementModel'!E81/'3StatementModel'!E$107 -> 0.0043790682 | F81: ='3StatementModel'!F81/'3StatementModel'!F$107 -> 0.004123195 | G81: ='3StatementModel'!G81/'3StatementModel'!G$107 -> 0.0033484845 | H81: ='3StatementModel'!H81/'3StatementModel'!H$107 -> 0.0014863332 | I81: ='3StatementModel'!I81/'3StatementModel'!I$107 -> 0.0014732948 | J81: ='3StatementModel'!J81/'3StatementModel'!J$107 -> 0.0013353501 | K81: ='3StatementModel'!K81/'3StatementModel'!K$107 -> 0.001202493 | ... M81: ='3StatementModel'!M81/'3StatementModel'!M$107 -> 0.00096215143
B82: Other Equity | D82: ='3StatementModel'!D82/'3StatementModel'!D$107 -> 0.73467245 | E82: ='3StatementModel'!E82/'3StatementModel'!E$107 -> 0.66848635 | F82: ='3StatementModel'!F82/'3StatementModel'!F$107 -> 0.76121483 | G82: ='3StatementModel'!G82/'3StatementModel'!G$107 -> 0.7793049 | H82: ='3StatementModel'!H82/'3StatementModel'!H$107 -> 0.51481775 | I82: ='3StatementModel'!I82/'3StatementModel'!I$107 -> 0.57205169 | J82: ='3StatementModel'!J82/'3StatementModel'!J$107 -> 0.59135795 | K82: ='3StatementModel'!K82/'3StatementModel'!K$107 -> 0.61252228 | ... M82: ='3StatementModel'!M82/'3StatementModel'!M$107 -> 0.65549308
B83: Total Shareholder's Equity | D83: ='3StatementModel'!D83/'3StatementModel'!D$107 -> 0.74095832 | E83: ='3StatementModel'!E83/'3StatementModel'!E$107 -> 0.67286542 | F83: ='3StatementModel'!F83/'3StatementModel'!F$107 -> 0.76533802 | G83: ='3StatementModel'!G83/'3StatementModel'!G$107 -> 0.78265339 | H83: ='3StatementModel'!H83/'3StatementModel'!H$107 -> 0.51630409 | I83: ='3StatementModel'!I83/'3StatementModel'!I$107 -> 0.57352498 | J83: ='3StatementModel'!J83/'3StatementModel'!J$107 -> 0.5926933 | K83: ='3StatementModel'!K83/'3StatementModel'!K$107 -> 0.61372478 | ... M83: ='3StatementModel'!M83/'3StatementModel'!M$107 -> 0.65645524
B84: Non Controlling Interest | D84: ='3StatementModel'!D84/'3StatementModel'!D$107 -> 0.022107498 | E84: ='3StatementModel'!E84/'3StatementModel'!E$107 -> 0.017608612 | F84: ='3StatementModel'!F84/'3StatementModel'!F$107 -> 0.019357786 | G84: ='3StatementModel'!G84/'3StatementModel'!G$107 -> 0.017779431 | H84: ='3StatementModel'!H84/'3StatementModel'!H$107 -> 0.0084940014 | I84: ='3StatementModel'!I84/'3StatementModel'!I$107 -> 0.0084194906 | J84: ='3StatementModel'!J84/'3StatementModel'!J$107 -> 0.0076311728 | K84: ='3StatementModel'!K84/'3StatementModel'!K$107 -> 0.00687193 | ... M84: ='3StatementModel'!M84/'3StatementModel'!M$107 -> 0.0054984413
B85: Total Equity | D85: ='3StatementModel'!D85/'3StatementModel'!D$107 -> 0.76306582 | E85: ='3StatementModel'!E85/'3StatementModel'!E$107 -> 0.69047403 | F85: ='3StatementModel'!F85/'3StatementModel'!F$107 -> 0.78469581 | G85: ='3StatementModel'!G85/'3StatementModel'!G$107 -> 0.80043282 | H85: ='3StatementModel'!H85/'3StatementModel'!H$107 -> 0.52479809 | I85: ='3StatementModel'!I85/'3StatementModel'!I$107 -> 0.58194447 | J85: ='3StatementModel'!J85/'3StatementModel'!J$107 -> 0.60032447 | K85: ='3StatementModel'!K85/'3StatementModel'!K$107 -> 0.62059671 | ... M85: ='3StatementModel'!M85/'3StatementModel'!M$107 -> 0.66195368
B87: Liabilities
B89: Non-Current Liabilities
B90: Long Term Borrowing | D90: ='3StatementModel'!D90/'3StatementModel'!D$107 -> 0.0090101056 | E90: ='3StatementModel'!E90/'3StatementModel'!E$107 -> 0.0053776918 | F90: ='3StatementModel'!F90/'3StatementModel'!F$107 -> 0.0023865533 | G90: ='3StatementModel'!G90/'3StatementModel'!G$107 -> 0.0020786721 | H90: ='3StatementModel'!H90/'3StatementModel'!H$107 -> 0.19907318 | I90: ='3StatementModel'!I90/'3StatementModel'!I$107 -> 0.20719322 | J90: ='3StatementModel'!J90/'3StatementModel'!J$107 -> 0.19718339 | K90: ='3StatementModel'!K90/'3StatementModel'!K$107 -> 0.18644342 | ... M90: ='3StatementModel'!M90/'3StatementModel'!M$107 -> 0.15520591
B91: Lease Liabilities | D91: ='3StatementModel'!D91/'3StatementModel'!D$107 -> 0.00086468606 | E91: ='3StatementModel'!E91/'3StatementModel'!E$107 -> 0.00032685487 | F91: ='3StatementModel'!F91/'3StatementModel'!F$107 -> 0.00053296414 | G91: ='3StatementModel'!G91/'3StatementModel'!G$107 -> 0.00064479066 | H91: ='3StatementModel'!H91/'3StatementModel'!H$107 -> 0.00050541091 | I91: ='3StatementModel'!I91/'3StatementModel'!I$107 -> 0.00050097737 | J91: ='3StatementModel'!J91/'3StatementModel'!J$107 -> 0.0004540708 | K91: ='3StatementModel'!K91/'3StatementModel'!K$107 -> 0.00040889426 | ... M91: ='3StatementModel'!M91/'3StatementModel'!M$107 -> 0.0003271688
B92: Provisions | D92: ='3StatementModel'!D92/'3StatementModel'!D$107 -> 0.011336292 | E92: ='3StatementModel'!E92/'3StatementModel'!E$107 -> 0.0087457509 | F92: ='3StatementModel'!F92/'3StatementModel'!F$107 -> 0.010075554 | G92: ='3StatementModel'!G92/'3StatementModel'!G$107 -> 0.010291891 | H92: ='3StatementModel'!H92/'3StatementModel'!H$107 -> 0.0055858173 | I92: ='3StatementModel'!I92/'3StatementModel'!I$107 -> 0.0055368176 | J92: ='3StatementModel'!J92/'3StatementModel'!J$107 -> 0.0050184048 | K92: ='3StatementModel'!K92/'3StatementModel'!K$107 -> 0.0045191122 | ... M92: ='3StatementModel'!M92/'3StatementModel'!M$107 -> 0.0036158798
B93: Deferred tax liabilities (net) | D93: ='3StatementModel'!D93/'3StatementModel'!D$107 -> 0.0020449147 | E93: ='3StatementModel'!E93/'3StatementModel'!E$107 -> 0.0060802221 | F93: ='3StatementModel'!F93/'3StatementModel'!F$107 -> 0.0079576239 | G93: ='3StatementModel'!G93/'3StatementModel'!G$107 -> 0.0074452265 | H93: ='3StatementModel'!H93/'3StatementModel'!H$107 -> 0.06529311 | I93: ='3StatementModel'!I93/'3StatementModel'!I$107 -> 0.064720349 | J93: ='3StatementModel'!J93/'3StatementModel'!J$107 -> 0.058660575 | K93: ='3StatementModel'!K93/'3StatementModel'!K$107 -> 0.052824301 | ... M93: ='3StatementModel'!M93/'3StatementModel'!M$107 -> 0.042266338
B94: Other non-current liabilities | D94: ='3StatementModel'!D94/'3StatementModel'!D$107 -> 0.0012375814 | E94: ='3StatementModel'!E94/'3StatementModel'!E$107 -> 0.0022031767 | F94: ='3StatementModel'!F94/'3StatementModel'!F$107 -> 0.0026241227 | G94: ='3StatementModel'!G94/'3StatementModel'!G$107 -> 0.0019193343 | H94: ='3StatementModel'!H94/'3StatementModel'!H$107 -> 0.00072047172 | I94: ='3StatementModel'!I94/'3StatementModel'!I$107 -> 0.00071415163 | J94: ='3StatementModel'!J94/'3StatementModel'!J$107 -> 0.00064728554 | K94: ='3StatementModel'!K94/'3StatementModel'!K$107 -> 0.00058288562 | ... M94: ='3StatementModel'!M94/'3StatementModel'!M$107 -> 0.0004663846
B95: Total non-current liabilities | D95: ='3StatementModel'!D95/'3StatementModel'!D$107 -> 0.02449358 | E95: ='3StatementModel'!E95/'3StatementModel'!E$107 -> 0.022733697 | F95: ='3StatementModel'!F95/'3StatementModel'!F$107 -> 0.023576818 | G95: ='3StatementModel'!G95/'3StatementModel'!G$107 -> 0.022379915 | H95: ='3StatementModel'!H95/'3StatementModel'!H$107 -> 0.27117799 | I95: ='3StatementModel'!I95/'3StatementModel'!I$107 -> 0.27866552 | J95: ='3StatementModel'!J95/'3StatementModel'!J$107 -> 0.26196372 | K95: ='3StatementModel'!K95/'3StatementModel'!K$107 -> 0.24477861 | ... M95: ='3StatementModel'!M95/'3StatementModel'!M$107 -> 0.20188168
B97: Current Liabilities
B98: Trade Payables | D98: ='3StatementModel'!D98/'3StatementModel'!D$107 -> 0.10468931 | E98: ='3StatementModel'!E98/'3StatementModel'!E$107 -> 0.117672 | F98: ='3StatementModel'!F98/'3StatementModel'!F$107 -> 0.10372764 | G98: ='3StatementModel'!G98/'3StatementModel'!G$107 -> 0.092198828 | H98: ='3StatementModel'!H98/'3StatementModel'!H$107 -> 0.040831312 | I98: ='3StatementModel'!I98/'3StatementModel'!I$107 -> 0.057493492 | J98: ='3StatementModel'!J98/'3StatementModel'!J$107 -> 0.059637253 | K98: ='3StatementModel'!K98/'3StatementModel'!K$107 -> 0.060649928 | ... M98: ='3StatementModel'!M98/'3StatementModel'!M$107 -> 0.059431716
B99: Short Term Borrowing | D99: ='3StatementModel'!D99/'3StatementModel'!D$107 -> 0.024887502 | E99: ='3StatementModel'!E99/'3StatementModel'!E$107 -> 0.089511579 | F99: ='3StatementModel'!F99/'3StatementModel'!F$107 -> 0.014357496 | G99: ='3StatementModel'!G99/'3StatementModel'!G$107 -> 0.014307811 | H99: ='3StatementModel'!H99/'3StatementModel'!H$107 -> 0.10651598 | I99: ='3StatementModel'!I99/'3StatementModel'!I$107 -> 0.025717064 | J99: ='3StatementModel'!J99/'3StatementModel'!J$107 -> 0.027155186 | K99: ='3StatementModel'!K99/'3StatementModel'!K$107 -> 0.028121473 | ... M99: ='3StatementModel'!M99/'3StatementModel'!M$107 -> 0.040044313
B100: Lease Liabilities | D100: ='3StatementModel'!D100/'3StatementModel'!D$107 -> 0 | E100: ='3StatementModel'!E100/'3StatementModel'!E$107 -> 0.0002248849 | F100: ='3StatementModel'!F100/'3StatementModel'!F$107 -> 0.00026313689 | G100: ='3StatementModel'!G100/'3StatementModel'!G$107 -> 0.00028610924 | H100: ='3StatementModel'!H100/'3StatementModel'!H$107 -> 0.0005183794 | I100: ='3StatementModel'!I100/'3StatementModel'!I$107 -> 0.0005138321 | J100: ='3StatementModel'!J100/'3StatementModel'!J$107 -> 0.00046572194 | K100: ='3StatementModel'!K100/'3StatementModel'!K$107 -> 0.0004193862 | ... M100: ='3StatementModel'!M100/'3StatementModel'!M$107 -> 0.00033556372
B101: Other financial liabilities | D101: ='3StatementModel'!D101/'3StatementModel'!D$107 -> 0.028807737 | E101: ='3StatementModel'!E101/'3StatementModel'!E$107 -> 0.024212294 | F101: ='3StatementModel'!F101/'3StatementModel'!F$107 -> 0.024341763 | G101: ='3StatementModel'!G101/'3StatementModel'!G$107 -> 0.01968937 | H101: ='3StatementModel'!H101/'3StatementModel'!H$107 -> 0.024285661 | I101: ='3StatementModel'!I101/'3StatementModel'!I$107 -> 0.024072623 | J101: ='3StatementModel'!J101/'3StatementModel'!J$107 -> 0.021818701 | K101: ='3StatementModel'!K101/'3StatementModel'!K$107 -> 0.019647909 | ... M101: ='3StatementModel'!M101/'3StatementModel'!M$107 -> 0.015720892
B102: Provisions | D102: ='3StatementModel'!D102/'3StatementModel'!D$107 -> 0.036752649 | E102: ='3StatementModel'!E102/'3StatementModel'!E$107 -> 0.028915462 | F102: ='3StatementModel'!F102/'3StatementModel'!F$107 -> 0.031663957 | G102: ='3StatementModel'!G102/'3StatementModel'!G$107 -> 0.032541892 | H102: ='3StatementModel'!H102/'3StatementModel'!H$107 -> 0.023914978 | I102: ='3StatementModel'!I102/'3StatementModel'!I$107 -> 0.023705192 | J102: ='3StatementModel'!J102/'3StatementModel'!J$107 -> 0.021485672 | K102: ='3StatementModel'!K102/'3StatementModel'!K$107 -> 0.019348014 | ... M102: ='3StatementModel'!M102/'3StatementModel'!M$107 -> 0.015480937
B103: Current tax liabilities (net) | D103: ='3StatementModel'!D103/'3StatementModel'!D$107 -> 0.0017393677 | E103: ='3StatementModel'!E103/'3StatementModel'!E$107 -> 0.0016495349 | F103: ='3StatementModel'!F103/'3StatementModel'!F$107 -> 0.0047610125 | G103: ='3StatementModel'!G103/'3StatementModel'!G$107 -> 0.0038767601 | H103: ='3StatementModel'!H103/'3StatementModel'!H$107 -> 0.00065130644 | I103: ='3StatementModel'!I103/'3StatementModel'!I$107 -> 0.00064559307 | J103: ='3StatementModel'!J103/'3StatementModel'!J$107 -> 0.00058514613 | K103: ='3StatementModel'!K103/'3StatementModel'!K$107 -> 0.0005269286 | ... M103: ='3StatementModel'!M103/'3StatementModel'!M$107 -> 0.00042161168
B104: Other current liabilities | D104: ='3StatementModel'!D104/'3StatementModel'!D$107 -> 0.015564035 | E104: ='3StatementModel'!E104/'3StatementModel'!E$107 -> 0.02460652 | F104: ='3StatementModel'!F104/'3StatementModel'!F$107 -> 0.012612373 | G104: ='3StatementModel'!G104/'3StatementModel'!G$107 -> 0.014286496 | H104: ='3StatementModel'!H104/'3StatementModel'!H$107 -> 0.0073063037 | I104: ='3StatementModel'!I104/'3StatementModel'!I$107 -> 0.0072422117 | J104: ='3StatementModel'!J104/'3StatementModel'!J$107 -> 0.0065641226 | K104: ='3StatementModel'!K104/'3StatementModel'!K$107 -> 0.0059110431 | ... M104: ='3StatementModel'!M104/'3StatementModel'!M$107 -> 0.0047296062
B105: Total Current liabilities | D105: ='3StatementModel'!D105/'3StatementModel'!D$107 -> 0.2124406 | E105: ='3StatementModel'!E105/'3StatementModel'!E$107 -> 0.28679227 | F105: ='3StatementModel'!F105/'3StatementModel'!F$107 -> 0.19172737 | G105: ='3StatementModel'!G105/'3StatementModel'!G$107 -> 0.17718727 | H105: ='3StatementModel'!H105/'3StatementModel'!H$107 -> 0.20402392 | I105: ='3StatementModel'!I105/'3StatementModel'!I$107 -> 0.13939001 | J105: ='3StatementModel'!J105/'3StatementModel'!J$107 -> 0.1377118 | K105: ='3StatementModel'!K105/'3StatementModel'!K$107 -> 0.13462468 | ... M105: ='3StatementModel'!M105/'3StatementModel'!M$107 -> 0.13616464
B107: Total Equity & Liabilities | D107: ='3StatementModel'!D107/'3StatementModel'!D$107 -> 1 | E107: ='3StatementModel'!E107/'3StatementModel'!E$107 -> 1 | F107: ='3StatementModel'!F107/'3StatementModel'!F$107 -> 1 | G107: ='3StatementModel'!G107/'3StatementModel'!G$107 -> 1 | H107: ='3StatementModel'!H107/'3StatementModel'!H$107 -> 1 | I107: ='3StatementModel'!I107/'3StatementModel'!I$107 -> 1 | J107: ='3StatementModel'!J107/'3StatementModel'!J$107 -> 1 | K107: ='3StatementModel'!K107/'3StatementModel'!K$107 -> 1 | ... M107: ='3StatementModel'!M107/'3StatementModel'!M$107 -> 1
B109: Check | D109: 0 | E109: 0 | F109: 0 | G109: 0 | H109: 0 | I109: 0 | J109: 0 | K109: 0 | L109: 0 | M109: 0
B111: Net Working Capital | D111: 2552.7863 | E111: 1783.3026 | F111: 2465.1494 | G111: 4448.4894 | H111: 1324.6495 | I111: 3645.3057 | J111: 6176.4498 | K111: 9059.5317 | L111: 12317.498 | M111: 16185.13
B112: Debtor Days | D112: 0 | E112: 16.857409 | F112: 20.119841 | G112: 25.158577 | H112: 35.681033 | I112: 23.823919 | J112: 23.823919 | K112: 23.823919 | L112: 23.823919 | M112: 23.823919
B113: Inventory Days | D113: 0 | E113: 69.040067 | F113: 67.971499 | G113: 53.893318 | H113: 54.526808 | I113: 58.580766 | J113: 58.580766 | K113: 55 | L113: 55 | M113: 55
B114: Trade Payable Days | D114: 0 | E114: 131.39713 | F114: 130.54688 | G114: 120.01576 | H114: 105.87538 | I114: 120 | J114: 120 | K114: 120 | L114: 120 | M114: 120
B115: Other Current Assets % Sales | D115: 0.061949905 | E115: 0.12568322 | F115: 0.082784759 | G115: 0.068738916 | H115: 0.091003523 | I115: 0.069 | J115: 0.069 | K115: 0.069 | L115: 0.069 | M115: 0.069
B116: Other Current Liabilities % Sales | D116: 0.015936475 | E116: 0.028926776 | F116: 0.01400493 | G116: 0.016537671 | H116: 0.016615057 | I116: 0.014080557 | J116: 0.012086315 | K116: 0.010509839 | L116: 0.00925977 | M116: 0.0082676518

Sheet Ratios
B2: ='Input Sheet'!C5 -> Mankind Pharma Ltd
B3: Common Size Statement
F4: Current Case | H4: 1
D8: Actual | I8: Explicit Forecasted Period
B9: In INR Crores unless stated otherwise | D9: 2021 | E9: =D9+1 -> 2022 | F9: =E9+1 -> 2023 | G9: =F9+1 -> 2024 | H9: =G9+1 -> 2025 | I9: =H9+1 -> 2026 | J9: =I9+1 -> 2027 | K9: =J9+1 -> 2028 | L9: =K9+1 -> 2029 | M9: =L9+1 -> 2030
A11: # | B11: Liquidity Ratios
B13: Current Assets | D13: ='3StatementModel'!D74 -> 3906.6348 | E13: ='3StatementModel'!E74 -> 4406.8183 | F13: ='3StatementModel'!F74 -> 4327.872 | G13: ='3StatementModel'!G74 -> 6568.2272 | H13: ='3StatementModel'!H74 -> 6988.27 | I13: ='3StatementModel'!I74 -> 7548.9588 | J13: ='3StatementModel'!J74 -> 10431.506 | K13: ='3StatementModel'!K74 -> 13678.78 | ... M13: ='3StatementModel'!M74 -> 22024.287
B14: Current Liabilities | D14: ='3StatementModel'!D83 -> 4722.0038 | E14: ='3StatementModel'!E83 -> 6155.2321 | F14: ='3StatementModel'!F83 -> 7435.6228 | G14: ='3StatementModel'!G83 -> 9363.0881 | H14: ='3StatementModel'!H83 -> 14332.39 | I14: ='3StatementModel'!I83 -> 16061.715 | J14: ='3StatementModel'!J83 -> 18313.195 | K14: ='3StatementModel'!K83 -> 21058.155 | ... M14: ='3StatementModel'!M83 -> 28150.811
B15: Current Ratio | D15: =D13/D14 -> 0.82732564 | E15: =E13/E14 -> 0.71594673 | F15: =F13/F14 -> 0.58204566 | G15: =G13/G14 -> 0.70150223 | H15: =H13/H14 -> 0.48758581 | I15: =I13/I14 -> 0.46999707 | J15: =J13/J14 -> 0.56961693 | K15: =K13/K14 -> 0.64957165 | ... M15: =M13/M14 -> 0.78236776
B17: Current Assets | D17: =D13 -> 3906.6348 | E17: =E13 -> 4406.8183 | F17: =F13 -> 4327.872 | G17: =G13 -> 6568.2272 | H17: =H13 -> 6988.27 | I17: =I13 -> 7548.9588 | J17: =J13 -> 10431.506 | K17: =K13 -> 13678.78 | ... M17: =M13 -> 22024.287
B18: Inventory | D18: ='3StatementModel'!D70 -> 1183.5377 | E18: ='3StatementModel'!E70 -> 1760.2381 | F18: ='3StatementModel'!F70 -> 1498.4582 | G18: ='3StatementModel'!G70 -> 1553.4612 | H18: ='3StatementModel'!H70 -> 2093.71 | I18: ='3StatementModel'!I70 -> 2311.8153 | J18: ='3StatementModel'!J70 -> 2693.2648 | K18: ='3StatementModel'!K70 -> 2907.934 | ... M18: ='3StatementModel'!M70 -> 3696.5657
B19: Other Current Assets | D19: ='3StatementModel'!D73 -> 385.5699 | E19: ='3StatementModel'!E73 -> 978.0109 | F19: ='3StatementModel'!F73 -> 724.3197 | G19: ='3StatementModel'!G73 -> 710.4012 | H19: ='3StatementModel'!H73 -> 1110.88 | I19: ='3StatementModel'!I73 -> 993.89394 | J19: ='3StatementModel'!J73 -> 1157.8864 | K19: ='3StatementModel'!K73 -> 1331.5694 | ... M19: ='3StatementModel'!M73 -> 1692.691
B20: Current Liabilities | D20: =D14 -> 4722.0038 | E20: =E14 -> 6155.2321 | F20: =F14 -> 7435.6228 | G20: =G14 -> 9363.0881 | H20: =H14 -> 14332.39 | I20: =I14 -> 16061.715 | J20: =J14 -> 18313.195 | K20: =K14 -> 21058.155 | ... M20: =M14 -> 28150.811
B21: Quick Ratio (Acid Test Ratio) | D21: =(D17-D18-D19)/D20 -> 0.49502866 | E21: =(E17-E18-E19)/E20 -> 0.27108146 | F21: =(F17-F18-F19)/F20 -> 0.28310932 | G21: =(G17-G18-G19)/G20 -> 0.45971636 | H21: =(H17-H18-H19)/H20 -> 0.26399505 | I21: =(I17-I18-I19)/I20 -> 0.26418409 | J21: =(J17-J18-J19)/J20 -> 0.35932313 | K21: =(K17-K18-K19)/K20 -> 0.44824806 | ... M21: =(M17-M18-M19)/M20 -> 0.59092544
B23: Inventory Days | D23: ='3StatementModel'!D113 -> 0 | E23: ='3StatementModel'!E113 -> 69.040067 | F23: ='3StatementModel'!F113 -> 67.971499 | G23: ='3StatementModel'!G113 -> 53.893318 | H23: ='3StatementModel'!H113 -> 54.526808 | I23: ='3StatementModel'!I113 -> 58.580766 | J23: ='3StatementModel'!J113 -> 58.580766 | K23: ='3StatementModel'!K113 -> 55 | ... M23: ='3StatementModel'!M113 -> 55
B24: Debtor Days | D24: ='3StatementModel'!D112 -> 0 | E24: ='3StatementModel'!E112 -> 16.857409 | F24: ='3StatementModel'!F112 -> 20.119841 | G24: ='3StatementModel'!G112 -> 25.158577 | H24: ='3StatementModel'!H112 -> 35.681033 | I24: ='3StatementModel'!I112 -> 23.823919 | J24: ='3StatementModel'!J112 -> 23.823919 | K24: ='3StatementModel'!K112 -> 25 | ... M24: ='3StatementModel'!M112 -> 25
B25: Creditor Days | D25: ='3StatementModel'!D114 -> 0 | E25: ='3StatementModel'!E114 -> 131.39713 | F25: ='3StatementModel'!F114 -> 130.54688 | G25: ='3StatementModel'!G114 -> 120.01576 | H25: ='3StatementModel'!H114 -> 105.87538 | I25: ='3StatementModel'!I114 -> 120 | J25: ='3StatementModel'!J114 -> 120 | K25: ='3StatementModel'!K114 -> 120 | ... M25: ='3StatementModel'!M114 -> 120
B26: Cash Conversion Days | D26: =D23+D24-D25 -> 0 | E26: =E23+E24-E25 -> -45.499649 | F26: =F23+F24-F25 -> -42.455544 | G26: =G23+G24-G25 -> -40.963862 | H26: =H23+H24-H25 -> -15.667538 | I26: =I23+I24-I25 -> -37.595315 | J26: =J23+J24-J25 -> -37.595315 | K26: =K23+K24-K25 -> -40 | ... M26: =M23+M24-M25 -> -40
A28: # | B28: Leverage Ratios / Solvency Ratios
B30: Total Debt | D30: =SUM('3StatementModel'!D99,'3StatementModel'!D90) -> 216.0238 | E30: =SUM('3StatementModel'!E99,'3StatementModel'!E90) -> 868.0272 | F30: =SUM('3StatementModel'!F99,'3StatementModel'!F90) -> 162.6764 | G30: =SUM('3StatementModel'!G99,'3StatementModel'!G90) -> 196.0358 | H30: =SUM('3StatementModel'!H99,'3StatementModel'!H90) -> 8483.03 | I30: =SUM('3StatementModel'!I99,'3StatementModel'!I90) -> 6522.7125 | J30: =SUM('3StatementModel'!J99,'3StatementModel'!J90) -> 6931.6726 | K30: =SUM('3StatementModel'!K99,'3StatementModel'!K90) -> 7362.1611 | ... M30: =SUM('3StatementModel'!M99,'3StatementModel'!M90) -> 8372.9276
B31: Total Equity | D31: ='3StatementModel'!D85 -> 4862.8912 | E31: ='3StatementModel'!E85 -> 6316.312 | F31: ='3StatementModel'!F85 -> 7623.6929 | G31: ='3StatementModel'!G85 -> 9575.7881 | H31: ='3StatementModel'!H85 -> 14568.18 | I31: ='3StatementModel'!I85 -> 16297.505 | J31: ='3StatementModel'!J85 -> 18548.985 | K31: ='3StatementModel'!K85 -> 21293.945 | ... M31: ='3StatementModel'!M85 -> 28386.601
B32: Debt to Equity Ratio | D32: =D30/D31 -> 0.044422914 | E32: =E30/E31 -> 0.13742627 | F32: =F30/F31 -> 0.021338268 | G32: =G30/G31 -> 0.020472028 | H32: =H30/H31 -> 0.58229854 | I32: =I30/I31 -> 0.40022768 | J32: =J30/J31 -> 0.37369553 | K32: =K30/K31 -> 0.34573965 | ... M32: =M30/M31 -> 0.29496056
B34: Total Debt | D34: =D30 -> 216.0238 | E34: =E30 -> 868.0272 | F34: =F30 -> 162.6764 | G34: =G30 -> 196.0358 | H34: =H30 -> 8483.03 | I34: =I30 -> 6522.7125 | J34: =J30 -> 6931.6726 | K34: =K30 -> 7362.1611 | ... M34: =M30 -> 8372.9276
B35: Total Assets | D35: ='3StatementModel'!D76 -> 6372.8332 | E35: ='3StatementModel'!E76 -> 9147.7908 | F35: ='3StatementModel'!F76 -> 9715.4755 | G35: ='3StatementModel'!G76 -> 11963.263 | H35: ='3StatementModel'!H76 -> 27759.591 | I35: ='3StatementModel'!I76 -> 28005.257 | J35: ='3StatementModel'!J76 -> 30898.265 | K35: ='3StatementModel'!K76 -> 34312.049 | ... M35: ='3StatementModel'!M76 -> 42883.063
B36: Debt to Assets Ratio | D36: =D34/D35 -> 0.033897608 | E36: =E34/E35 -> 0.094889271 | F36: =F34/F35 -> 0.016744049 | G36: =G34/G35 -> 0.016386483 | H36: =H34/H35 -> 0.30558916 | I36: =I34/I35 -> 0.23291029 | J36: =J34/J35 -> 0.22433857 | K36: =K34/K35 -> 0.21456489 | ... M36: =M34/M35 -> 0.19525023
B38: Total Equity | D38: =D31 -> 4862.8912 | E38: =E31 -> 6316.312 | F38: =F31 -> 7623.6929 | G38: =G31 -> 9575.7881 | H38: =H31 -> 14568.18 | I38: =I31 -> 16297.505 | J38: =J31 -> 18548.985 | K38: =K31 -> 21293.945 | ... M38: =M31 -> 28386.601
B39: Total Assets | D39: =D35 -> 6372.8332 | E39: =E35 -> 9147.7908 | F39: =F35 -> 9715.4755 | G39: =G35 -> 11963.263 | H39: =H35 -> 27759.591 | I39: =I35 -> 28005.257 | J39: =J35 -> 30898.265 | K39: =K35 -> 34312.049 | ... M39: =M35 -> 42883.063
B40: Equity Ratio | D40: =D38/D39 -> 0.76306582 | E40: =E38/E39 -> 0.69047403 | F40: =F38/F39 -> 0.78469581 | G40: =G38/G39 -> 0.80043282 | H40: =H38/H39 -> 0.52479809 | I40: =I38/I39 -> 0.58194447 | J40: =J38/J39 -> 0.60032447 | K40: =K38/K39 -> 0.62059671 | ... M40: =M38/M39 -> 0.66195368
A42: # | B42: Profitability / Margins Ratio
B44: Gross Profit | D44: ='3StatementModel'!D15 -> 4443.289 | E44: ='3StatementModel'!E15 -> 5359.8267 | F44: ='3StatementModel'!F15 -> 5835.791 | G44: ='3StatementModel'!G15 -> 7125.0787 | H44: ='3StatementModel'!H15 -> 8351.96 | I44: ='3StatementModel'!I15 -> 9506.8116 | J44: ='3StatementModel'!J15 -> 11176.121 | K44: ='3StatementModel'!K15 -> 12968.328 | ... M44: ='3StatementModel'!M15 -> 16779.72
B45: Total Sales | D45: ='3StatementModel'!D13 -> 6223.8982 | E45: ='3StatementModel'!E13 -> 7781.5551 | F45: ='3StatementModel'!F13 -> 8749.433 | G45: ='3StatementModel'!G13 -> 10334.775 | H45: ='3StatementModel'!H13 -> 12207 | I45: ='3StatementModel'!I13 -> 14404.26 | J45: ='3StatementModel'!J13 -> 16780.963 | K45: ='3StatementModel'!K13 -> 19298.107 | ... M45: ='3StatementModel'!M13 -> 24531.754
B46: Gross Margin | D46: =D44/D45 -> 0.71390772 | E46: =E44/E45 -> 0.68878606 | F46: =F44/F45 -> 0.66699076 | G46: =G44/G45 -> 0.68942759 | H46: =H44/H45 -> 0.68419431 | I46: =I44/I45 -> 0.66 | J46: =J44/J45 -> 0.666 | K46: =K44/K45 -> 0.672 | ... M46: =M44/M45 -> 0.684
B48: EBITDA | D48: ='3StatementModel'!D25 -> 1657.5928 | E48: ='3StatementModel'!E25 -> 1989.3662 | F48: ='3StatementModel'!F25 -> 1900.6581 | G48: ='3StatementModel'!G25 -> 2535.1033 | H48: ='3StatementModel'!H25 -> 2651.86 | I48: ='3StatementModel'!I25 -> 3096.9159 | J48: ='3StatementModel'!J25 -> 3708.5928 | K48: ='3StatementModel'!K25 -> 4380.6704 | ... M48: ='3StatementModel'!M25 -> 5863.0892
B49: Total Sales | D49: =D45 -> 6223.8982 | E49: =E45 -> 7781.5551 | F49: =F45 -> 8749.433 | G49: =G45 -> 10334.775 | H49: =H45 -> 12207 | I49: =I45 -> 14404.26 | J49: =J45 -> 16780.963 | K49: =K45 -> 19298.107 | ... M49: =M45 -> 24531.754
B50: EBITDA Margin | D50: =D48/D49 -> 0.26632711 | E50: =E48/E49 -> 0.2556515 | F50: =F48/F49 -> 0.21723215 | G50: =G48/G49 -> 0.24529836 | H50: =H48/H49 -> 0.21724093 | I50: =I48/I49 -> 0.215 | J50: =J48/J49 -> 0.221 | K50: =K48/K49 -> 0.227 | ... M50: =M48/M49 -> 0.239
B52: EBIT | D52: ='3StatementModel'!D30 -> 1538.6225 | E52: ='3StatementModel'!E30 -> 1822.747 | F52: ='3StatementModel'!F30 -> 1574.7386 | G52: ='3StatementModel'!G30 -> 2136.8496 | H52: ='3StatementModel'!H30 -> 2030.86 | I52: ='3StatementModel'!I30 -> 2435.1087 | J52: ='3StatementModel'!J30 -> 3001.9677 | K52: ='3StatementModel'!K30 -> 3615.8363 | ... M52: ='3StatementModel'!M30 -> 4977.2271
B53: Total Sales | D53: =D45 -> 6223.8982 | E53: =E45 -> 7781.5551 | F53: =F45 -> 8749.433 | G53: =G45 -> 10334.775 | H53: =H45 -> 12207 | I53: =I45 -> 14404.26 | J53: =J45 -> 16780.963 | K53: =K45 -> 19298.107 | ... M53: =M45 -> 24531.754
B54: EBIT Margin | D54: =D52/D53 -> 0.24721203 | E54: =E52/E53 -> 0.23423943 | F54: =F52/F53 -> 0.17998179 | G54: =G52/G53 -> 0.20676306 | H54: =H52/H53 -> 0.16636848 | I54: =I52/I53 -> 0.16905476 | J54: =J52/J53 -> 0.17889127 | K54: =K52/K53 -> 0.18736741 | ... M54: =M52/M53 -> 0.20288917
B56: Net Profit | D56: ='3StatementModel'!D40 -> 1269.6962 | E56: ='3StatementModel'!E40 -> 1424.075 | F56: ='3StatementModel'!F40 -> 1284.8489 | G56: ='3StatementModel'!G40 -> 1911.3759 | H56: ='3StatementModel'!H40 -> 1616.27 | I56: ='3StatementModel'!I40 -> 1729.3246 | J56: ='3StatementModel'!J40 -> 2251.4801 | K56: ='3StatementModel'!K40 -> 2744.96 | ... M56: ='3StatementModel'!M40 -> 3823.7751
B57: Total Sales | D57: =D45 -> 6223.8982 | E57: =E45 -> 7781.5551 | F57: =F45 -> 8749.433 | G57: =G45 -> 10334.775 | H57: =H45 -> 12207 | I57: =I45 -> 14404.26 | J57: =J45 -> 16780.963 | K57: =K45 -> 19298.107 | ... M57: =M45 -> 24531.754
B58: Net Profit Margin | D58: =D56/D57 -> 0.20400337 | E58: =E56/E57 -> 0.18300648 | F58: =F56/F57 -> 0.14684939 | G58: =G56/G57 -> 0.18494607 | H58: =H56/H57 -> 0.13240518 | I58: =I56/I57 -> 0.12005647 | J58: =J56/J57 -> 0.1341687 | K58: =K56/K57 -> 0.14223986 | ... M58: =M56/M57 -> 0.15587043
B60: Net Income | D60: =D56 -> 1269.6962 | E60: =E56 -> 1424.075 | F60: =F56 -> 1284.8489 | G60: =G56 -> 1911.3759 | H60: =H56 -> 1616.27 | I60: =I56 -> 1729.3246 | J60: =J56 -> 2251.4801 | K60: =K56 -> 2744.96 | ... M60: =M56 -> 3823.7751
B61: Total Assets | D61: =D35 -> 6372.8332 | E61: =E35 -> 9147.7908 | F61: =F35 -> 9715.4755 | G61: =G35 -> 11963.263 | H61: =H35 -> 27759.591 | I61: =I35 -> 28005.257 | J61: =J35 -> 30898.265 | K61: =K35 -> 34312.049 | ... M61: =M35 -> 42883.063
B62: Return on Assets | D62: =D60/D61 -> 0.19923575 | E62: =E60/E61 -> 0.1556742 | F62: =F60/F61 -> 0.13224766 | G62: =G60/G61 -> 0.15977045 | H62: =H60/H61 -> 0.058223842 | I62: =I60/I61 -> 0.061749998 | J62: =J60/J61 -> 0.072867524 | K62: =K60/K61 -> 0.079999886 | ... M62: =M60/M61 -> 0.089167492
B64: Net Income | D64: =D56 -> 1269.6962 | E64: =E56 -> 1424.075 | F64: =F56 -> 1284.8489 | G64: =G56 -> 1911.3759 | H64: =H56 -> 1616.27 | I64: =I56 -> 1729.3246 | J64: =J56 -> 2251.4801 | K64: =K56 -> 2744.96 | ... M64: =M56 -> 3823.7751
B65: Total Equity | D65: =D31 -> 4862.8912 | E65: =E31 -> 6316.312 | F65: =F31 -> 7623.6929 | G65: =G31 -> 9575.7881 | H65: =H31 -> 14568.18 | I65: =I31 -> 16297.505 | J65: =J31 -> 18548.985 | K65: =K31 -> 21293.945 | ... M65: =M31 -> 28386.601
B66: Return on Equity | D66: =D64/D65 -> 0.26109904 | E66: =E64/E65 -> 0.22545989 | F66: =F64/F65 -> 0.16853366 | G66: =G64/G65 -> 0.19960507 | H66: =H64/H65 -> 0.11094522 | I66: =I64/I65 -> 0.10610978 | J66: =J64/J65 -> 0.12138023 | K66: =K64/K65 -> 0.12890801 | ... M66: =M64/M65 -> 0.13470352
A68: # | B68: Efficiency Ratio
B70: Revenue | D70: =D45 -> 6223.8982 | E70: =E45 -> 7781.5551 | F70: =F45 -> 8749.433 | G70: =G45 -> 10334.775 | H70: =H45 -> 12207 | I70: =I45 -> 14404.26 | J70: =J45 -> 16780.963 | K70: =K45 -> 19298.107 | ... M70: =M45 -> 24531.754
B71: Total Assets | D71: =D35 -> 6372.8332 | E71: =E35 -> 9147.7908 | F71: =F35 -> 9715.4755 | G71: =G35 -> 11963.263 | H71: =H35 -> 27759.591 | I71: =I35 -> 28005.257 | J71: =J35 -> 30898.265 | K71: =K35 -> 34312.049 | ... M71: =M35 -> 42883.063
B72: Asset Turnover Ratio | D72: =D70/D71 -> 0.9766297 | E72: =E70/E71 -> 0.85064856 | F72: =F70/F71 -> 0.90056663 | G72: =G70/G71 -> 0.86387592 | H72: =H70/H71 -> 0.43973992 | I72: =I70/I71 -> 0.51434129 | J72: =J70/J71 -> 0.54310373 | K72: =K70/K71 -> 0.56242946 | ... M72: =M70/M71 -> 0.57206162
B74: Change in Revenue | D74: 0 | E74: =E70-D70 -> 1557.6569 | F74: =F70-E70 -> 967.8779 | G74: =G70-F70 -> 1585.3416 | H74: =H70-G70 -> 1872.2254 | I74: =I70-H70 -> 2197.26 | J74: =J70-I70 -> 2376.7029 | K74: =K70-J70 -> 2517.1444 | L74: =L70-K70 -> 2605.2445 | M74: =M70-L70 -> 2628.4022
B75: Change in Total Assets | D75: 0 | E75: =E71-D71 -> 2774.9576 | F75: =F71-E71 -> 567.6847 | G75: =G71-F71 -> 2247.7872 | H75: =H71-G71 -> 15796.328 | I75: =I71-H71 -> 245.6666 | J75: =J71-I71 -> 2893.0078 | K75: =K71-J71 -> 3413.7841 | L75: =L71-K71 -> 4202.8871 | M75: =M71-L71 -> 4368.1265
B76: Reinvestment Ratio | D76: 0 | E76: =E74/E75 -> 0.56132638 | F76: =F74/F75 -> 1.7049568 | G76: =G74/G75 -> 0.7052899 | H76: =H74/H75 -> 0.11852283 | I76: =I74/I75 -> 8.944073 | J76: =J74/J75 -> 0.82153352 | K76: =K74/K75 -> 0.73734729 | L76: =L74/L75 -> 0.61987021 | M76: =M74/M75 -> 0.60172301
B78: COGS | D78: ='3StatementModel'!D14*-1 -> 1780.6092 | E78: ='3StatementModel'!E14*-1 -> 2421.7284 | F78: ='3StatementModel'!F14*-1 -> 2913.642 | G78: ='3StatementModel'!G14*-1 -> 3209.6959 | H78: ='3StatementModel'!H14*-1 -> 3855.04 | I78: ='3StatementModel'!I14*-1 -> 4897.4484 | J78: ='3StatementModel'!J14*-1 -> 5604.8416 | K78: ='3StatementModel'!K14*-1 -> 6329.7792 | ... M78: ='3StatementModel'!M14*-1 -> 7752.0343
B79: Inventory | D79: =D18 -> 1183.5377 | E79: =E18 -> 1760.2381 | F79: =F18 -> 1498.4582 | G79: =G18 -> 1553.4612 | H79: =H18 -> 2093.71 | I79: =I18 -> 2311.8153 | J79: =J18 -> 2693.2648 | K79: =K18 -> 2907.934 | ... M79: =M18 -> 3696.5657
B80: Inventory Turnover Ratio | D80: =D78/D79 -> 1.5044803 | E80: =E78/E79 -> 1.3757959 | F80: =F78/F79 -> 1.9444266 | G80: =G78/G79 -> 2.0661578 | H80: =H78/H79 -> 1.8412483 | I80: =I78/I79 -> 2.1184428 | J80: =J78/J79 -> 2.0810585 | K80: =K78/K79 -> 2.1767273 | ... M80: =M78/M79 -> 2.0970909
A82: # | B82: Coverage Ratio
B84: Total Debt | D84: =D30 -> 216.0238 | E84: =E30 -> 868.0272 | F84: =F30 -> 162.6764 | G84: =G30 -> 196.0358 | H84: =H30 -> 8483.03 | I84: =I30 -> 6522.7125 | J84: =J30 -> 6931.6726 | K84: =K30 -> 7362.1611 | ... M84: =M30 -> 8372.9276
B85: EBITDA | D85: =D48 -> 1657.5928 | E85: =E48 -> 1989.3662 | F85: =F48 -> 1900.6581 | G85: =G48 -> 2535.1033 | H85: =H48 -> 2651.86 | I85: =I48 -> 3096.9159 | J85: =J48 -> 3708.5928 | K85: =K48 -> 4380.6704 | ... M85: =M48 -> 5863.0892
B86: Debt to EBITDA Coverage Ratio | D86: =D84/D85 -> 0.1303238 | E86: =E84/E85 -> 0.43633354 | F86: =F84/F85 -> 0.085589512 | G86: =G84/G85 -> 0.077328525 | H86: =H84/H85 -> 3.1988981 | I86: =I84/I85 -> 2.1061962 | J86: =J84/J85 -> 1.8690843 | K86: =K84/K85 -> 1.6806015 | ... M86: =M84/M85 -> 1.4280744
B88: EBIT | E88: =E52 -> 1822.747 | F88: =F52 -> 1574.7386 | G88: =G52 -> 2136.8496 | H88: =H52 -> 2030.86 | I88: =I52 -> 2435.1087 | J88: =J52 -> 3001.9677 | K88: =K52 -> 3615.8363 | L88: =L52 -> 4278.4007 | M88: =M52 -> 4977.2271
B89: Interest | E89: ='3StatementModel'!E34*-1 -> 58.6104 | F89: ='3StatementModel'!F34*-1 -> 44.469 | G89: ='3StatementModel'!G34*-1 -> 33.5316 | H89: ='3StatementModel'!H34*-1 -> 429.4 | I89: ='3StatementModel'!I34*-1 -> 561.47041 | J89: ='3StatementModel'!J34*-1 -> 503.42321 | K89: ='3StatementModel'!K34*-1 -> 534.83289 | L89: ='3StatementModel'!L34*-1 -> 576.99301 | M89: ='3StatementModel'!M34*-1 -> 614.8129
B90: Debt Repayment | E90: =D34-E34 -> -652.0034 | F90: =E34-F34 -> 705.3508 | G90: =F34-G34 -> -33.3594 | H90: =G34-H34 -> -8286.9942 | I90: =H34-I34 -> 1960.3175 | J90: =I34-J34 -> -408.96012 | K90: =J34-K34 -> -430.48845 | L90: =K34-L34 -> -696.27437 | M90: =L34-M34 -> -314.49217
B91: Debt Service Coverage Ratio | E91: =E88/SUM(E89:E90) -> -3.0717366 | F91: =F88/SUM(F89:F90) -> 2.1001561 | G91: =G88/SUM(G89:G90) -> 12409.115 | H91: =H88/SUM(H89:H90) -> -0.25845824 | I91: =I88/SUM(I89:I90) -> 0.96562788 | J91: =J88/SUM(J89:J90) -> 31.779266 | K91: =K88/SUM(K89:K90) -> 34.652888 | L91: =L88/SUM(L89:L90) -> -35.868141 | M91: =M88/SUM(M89:M90) -> 16.573039
B93: EBIT | D93: =D52 -> 1538.6225 | E93: =E52 -> 1822.747 | F93: =F52 -> 1574.7386 | G93: =G52 -> 2136.8496 | H93: =H52 -> 2030.86 | I93: =I52 -> 2435.1087 | J93: =J52 -> 3001.9677 | K93: =K52 -> 3615.8363 | ... M93: =M52 -> 4977.2271
B94: Interest Expense | D94: ='3StatementModel'!D122 -> 3.7015 | E94: ='3StatementModel'!E122 -> 10.7409 | F94: ='3StatementModel'!F122 -> 4.226 | G94: ='3StatementModel'!G122 -> 8.1553 | H94: ='3StatementModel'!H122 -> 25.4 | I94: ='3StatementModel'!I122 -> 561.47041 | J94: ='3StatementModel'!J122 -> 503.42321 | K94: ='3StatementModel'!K122 -> 534.83289 | ... M94: ='3StatementModel'!M122 -> 614.8129
B95: Interest Coverage Ratio | D95: =D93/D94 -> 415.6754 | E95: =E93/E94 -> 169.70151 | F95: =F93/F94 -> 372.631 | G95: =G93/G94 -> 262.01974 | H95: =H93/H94 -> 79.955118 | I95: =I93/I94 -> 4.3370206 | J95: =J93/J94 -> 5.9631095 | K95: =K93/K94 -> 6.7606843 | ... M95: =M93/M94 -> 8.0955151

Sheet Option value
B2: Valuing Options or Warrants
B3: Enter the current stock price = | E3: 2467
B4: Enter the strike price on the option = | E4: 860
B5: Enter the expiration of the option = | E5: 4
B6: Enter the standard deviation in stock prices = | E6: 0.003 | F6: (volatility) | L6: Grant Date | M6: No. of options granted | N6: Exercise Price | O6: Maturity | P6: Expected Volatility | Q6: Expected Dividend
B7: Enter the annualized dividend yield on stock = | E7: 0 | K7: 1 | L7: 45016 | M7: 26325 | N7: 860 | O7: 4 | P7: 0.2785 | Q7: 0
B8: Enter the Risk Free rate = | E8: =WACC!E7 -> 0.0421 | K8: =K7+1 -> 2 | L8: 45016 | M8: 209302 | N8: 860 | O8: 4 | P8: 0.2785 | Q8: 0
B9: Enter the number of options outstanding = | E9: 0.11 | K9: =K8+1 -> 3 | L9: 45016 | M9: 313954 | N9: 860 | O9: 4 | P9: 0.2785 | Q9: 0
B10: Enter the number of shares outstanding = | E10: 41.3 | K10: =K9+1 -> 4 | L10: 45016 | M10: 418605 | N10: 860 | O10: 4 | P10: 0.2785 | Q10: 0
K11: =K10+1 -> 5 | L11: 45212 | M11: 0 | N11: 860 | O11: 4 | P11: 0.2712 | Q11: 0
B12: Do not input any numbers below this line | K12: =K11+1 -> 6 | L12: 45212 | M12: 14000 | N12: 860 | O12: 4 | P12: 0.2712 | Q12: 0
B13: VALUING OPTIONS WHEN THERE IS DILUTION | K13: =K12+1 -> 7 | L13: 45212 | M13: 21000 | N13: 860 | O13: 4 | P13: 0.2712 | Q13: 0
B14: Stock Price= | D14: =E3 -> 2467 | E14: # Warrants issued= | G14: =E9 -> 0.11 | K14: =K13+1 -> 8 | L14: 45212 | M14: 28000 | N14: 860 | O14: 4 | P14: 0.2712 | Q14: 0
B15: Strike Price= | D15: =E4 -> 860 | E15: # Shares outstanding= | G15: =E10 -> 41.3 | K15: =K14+1 -> 9 | L15: 45427 | M15: 5813 | N15: 860 | O15: 4 | P15: 0.2649 | Q15: 0
B16: Adjusted S = | D16: =(D14*G15+D27*G14)/(G15+G14) -> 2465.0644 | E16: T.Bond rate= | G16: =E8 -> 0.0421 | K16: =K15+1 -> 10 | L16: 45427 | M16: 11627 | N16: 860 | O16: 4 | P16: 0.2649 | Q16: 0
B17: Adjusted K = | D17: =D15 -> 860 | E17: Variance= | G17: =E6^2 -> 9e-06 | K17: =K16+1 -> 11 | L17: 45427 | M17: 17441 | N17: 860 | O17: 4 | P17: 0.2649 | Q17: 0
B18: Expiration (in years) = | D18: =E5 -> 4 | E18: Annualized dividend yield= | G18: =E7 -> 0 | K18: =K17+1 -> 12 | L18: 45427 | M18: 23258 | N18: 860 | O18: 4 | P18: 0.2649 | Q18: 0
E19: Div. Adj. interest rate= | G19: =G16-G18 -> 0.0421 | K19: =K18+1 -> 13 | L19: 45504 | M19: 3800 | N19: 860 | O19: 4 | P19: 0.2653 | Q19: 0
K20: =K19+1 -> 14 | L20: 45504 | M20: 7600 | N20: 860 | O20: 4 | P20: 0.2653 | Q20: 0
B21: d1 = | C21: =(LN(D16/D17)+(G19+(G17/2))*D18)/(((G17)^(0.5))*(D18^0.5)) -> 203.57647 | K21: =K20+1 -> 15 | L21: 45504 | M21: 11400 | N21: 860 | O21: 4 | P21: 0.2653 | Q21: 0
B22: N (d1) = | C22: =NORMSDIST(C21) -> 1 | K22: =K21+1 -> 16 | L22: 45504 | M22: 15200 | N22: 860 | O22: 4 | P22: 0.2653 | Q22: 0
M23: Weighted Average | N23: =SUMPRODUCT(N7:N22,$M$7:$M$22)/SUM($M$7:$M$22) -> 860 | O23: =SUMPRODUCT(O7:O22,$M$7:$M$22)/SUM($M$7:$M$22) -> 4 | P23: =SUMPRODUCT(P7:P22,$M$7:$M$22)/SUM($M$7:$M$22) -> 0.27694571 | Q23: =SUMPRODUCT(Q7:Q22,$M$7:$M$22)/SUM($M$7:$M$22) -> 0
B24: d2 = | C24: =C21-((G17^0.5)*(D18^(0.5))) -> 203.57047
B25: N (d2) = | C25: =NORMSDIST(C24) -> 1
B27: Value per option = | D27: =((EXP((0-G18)*D18))*D16*C22-D17*(EXP((0-G16)*D18))*C25) -> 1738.3509
B28: Value of all options outstanding = | E28: =D27*E9 -> 191.2186

Sheet DCF >

Sheet WACC
B2: ='Input Sheet'!C5 -> Mankind Pharma Ltd
B3: Weighted Average Cost of Capital
B5: Particulars | D5: Low | E5: Mid | F5: High | H5: Risk Free Rate
B7: Risk Free Rate | D7: ='Input Sheet'!C9-'Input Sheet'!C11 -> 0.0421 | E7: =D7 -> 0.0421 | F7: =E7 -> 0.0421 | H7: ="We have considered "&TEXT(E7,"0.00%")&" as the risk free rate in the estimation of cost of equity of "&TEXT(E12,"0.00%")&". The risk free rate of India is calculated by considering local currency 10 Year Government Bond Yield adjusted for default spread of India." -> We have considered 4.21% as the risk free rate in the estimation of cost of equity of 8.88%. The risk free rate of India is calculated by considering local currency 10 Year Government Bond Yield adjusted for default spread of India.
B8: Equity Risk Premium | D8: ='Input Sheet'!C12+'Input Sheet'!C11 -> 0.06 | E8: =D8 -> 0.06 | F8: =E8 -> 0.06
B9: Asset Beta | D9: =E9-'Input Sheet'!C14 -> 0.48918512 | E9: ='Input Sheet'!C13 -> 0.53918512 | F9: =E9+'Input Sheet'!C14 -> 0.58918512
B10: D/E Ratio | D10: ='Input Sheet'!C15 -> 0.59187826 | E10: =D10 -> 0.59187826 | F10: =E10 -> 0.59187826
B11: Equity Beta | D11: =D9*(1+(D10*(1-'Input Sheet'!$C$17))) -> 0.70633865 | E11: =E9*(1+(E10*(1-'Input Sheet'!$C$17))) -> 0.77853409 | F11: =F9*(1+(F10*(1-'Input Sheet'!$C$17))) -> 0.85072952
B12: CAPM Cost of Equity | D12: =D7+D8*D11 -> 0.084480319 | E12: =E7+E8*E11 -> 0.088812045 | F12: =F7+F8*F11 -> 0.093143771 | H12: Asset Beta
B14: Small Size Premium | D14: 0.029 | E14: =D14 -> 0.029 | F14: =E14 -> 0.029 | H14: ="We have estimated an Asset Beta Range of "&TEXT(D9,"0.00")&" to "&TEXT(F9,"0.00")&", with a mid point of "&TEXT(E9,"0.00")&" based on observed median 2 Year weekly asset beta of benchmarked listed companies adjusted for blume effect." -> We have estimated an Asset Beta Range of 0.49 to 0.59, with a mid point of 0.54 based on observed median 2 Year weekly asset beta of benchmarked listed companies adjusted for blume effect.
B15: Asset Specific Premium | D15: ='Input Sheet'!C24 -> 0 | E15: =D15 -> 0 | F15: =E15 -> 0
B16: Modified Cost of Equity | D16: =D12+D14+D15 -> 0.11348032 | E16: =E12+E14+E15 -> 0.11781205 | F16: =F12+F14+F15 -> 0.12214377
B18: Pre Tax Cost of Debt | D18: ='Input Sheet'!C9+(IF('Input Sheet'!C18="No",'Input Sheet'!C22,VLOOKUP('Input Sheet'!C20,'Damodaran Data'!J7:K21,2,FALSE))) -> 0.0722 | E18: =D18 -> 0.0722 | F18: =E18 -> 0.0722
B19: Marginal Tax Rate | D19: ='Input Sheet'!C17 -> 0.25 | E19: =D19 -> 0.25 | F19: =E19 -> 0.25 | H19: Equity Risk Premium (ERP)
B20: Post Tax Cost of Debt | D20: =D18*(1-D19) -> 0.05415 | E20: =E18*(1-E19) -> 0.05415 | F20: =F18*(1-F19) -> 0.05415
H21: ="An ERP of "&TEXT(E8,"0.00%")&" has been adopted based on US Implied ERP, relative equity volatility of ICE BoFA Public Sector Issues Emerging Markets Index, S&P Emerging BMI Index and country risk premium of India." -> An ERP of 6.00% has been adopted based on US Implied ERP, relative equity volatility of ICE BoFA Public Sector Issues Emerging Markets Index, S&P Emerging BMI Index and country risk premium of India.
B22: Capital Gearing (D/D+E) | D22: ='Input Sheet'!C16 -> 0.36800801 | E22: =D22 -> 0.36800801 | F22: =E22 -> 0.36800801
B23: Weighted Average Cost of Capital | D23: =(D20*D22)+(D16*(1-D22)) -> 0.091646286 | E23: =(E20*E22)+(E16*(1-E22)) -> 0.094383902 | F23: =(F20*F22)+(F16*(1-F22)) -> 0.097121519
B24: Weighted Average Cost of Capital (Rounded) | D24: =ROUNDUP(D23,2) -> 0.1 | E24: =ROUNDUP(E23,2) -> 0.1 | F24: =ROUNDUP(F23,2) -> 0.1
B26: 1. Tax rate considered as Marginal Tax Rate of India | H26: Cost of Debt
B27: 2.Asset Beta is considered as median of 5 years beta of comps adjusted for blume affect
B28: 3.Equity Beta = Asset Beta*(1+(1-Tax Rate%)*Debt/Equity) | H28: For the purpose of assessing cost of Debt, we have used country's Risk Free Rate, country's default spread and corporate default spread on company's debt rating and interest coverage ratio.
B33: =B2 -> Mankind Pharma Ltd
B34: Beta Analysis - 2 Years Weekly
B36: Comparable Company | D36: Ticker | E36: No. of Weekly Observations | F36: Market Cap | G36: Asset Beta | H36: 2 Years Avg D/E | I36: Equity Beta | J36: 2 Years Avg D/D+E | L36: Consideration ? | M36: Narrow Set
B38: Sun Pharmaceutical Industries Ltd | D38: NSE: SUNPHARMA | E38: 104 | F38: 380750 | G38: =I38/(1+(H38*(1-$D$19))) -> 0.44870766 | H38: =AVERAGE('Assumptions Working'!Q806:R806) -> 0.033555146 | I38: 0.46 | J38: ='Assumptions Working'!AC817 -> 0.032436297 | L38: Yes | M38: =IF(L38="Yes","TRUE","FALSE") -> TRUE | O38: Yes
B39: Torrent Pharmaceuticals Ltd | D39: NSE: TORNTPHARM | E39: 104 | F39: 120928 | G39: =I39/(1+(H39*(1-$D$19))) -> 0.42498863 | H39: =AVERAGE('Assumptions Working'!Q812:R812) -> 0.4863232 | I39: 0.58 | J39: ='Assumptions Working'!AC818 -> 0.32484435 | L39: No | M39: =IF(L39="Yes","TRUE","FALSE") -> FALSE | O39: No
B40: Cipla Ltd | D40: NSE: CIPLA | E40: 104 | F40: 120016 | G40: =I40/(1+(H40*(1-$D$19))) -> 1.2244331 | H40: =AVERAGE('Assumptions Working'!Q818:R818) -> 0.0060620503 | I40: 1.23 | J40: ='Assumptions Working'!AC819 -> 0.0060157561 | L40: Yes | M40: =IF(L40="Yes","TRUE","FALSE") -> TRUE
B41: Dr. Reddy's Laboratories Ltd | D41: NSE: DRREDDY | E41: 104 | F41: 10101 | G41: =I41/(1+(H41*(1-$D$19))) -> 0.33297269 | H41: =AVERAGE('Assumptions Working'!U806:V806) -> 0.9090928 | I41: 0.56 | J41: ='Assumptions Working'!AC820 -> 0.46062763 | L41: No | M41: =IF(L41="Yes","TRUE","FALSE") -> FALSE
B42: Zydus Lifesciences Ltd | D42: NSE: ZYDUSLIFE | E42: 104 | F42: 94199 | G42: =I42/(1+(H42*(1-$D$19))) -> 0.67624895 | H42: =AVERAGE('Assumptions Working'!U812:V812) -> 0.08626222 | I42: 0.72 | J42: ='Assumptions Working'!AC821 -> 0.07685897 | L42: Yes | M42: =IF(L42="Yes","TRUE","FALSE") -> TRUE
B44: Median - Broad Set | G44: =MEDIAN(G38:G42) -> 0.44870766 | H44: =MEDIAN(H38:H42) -> 0.08626222 | I44: =MEDIAN(I38:I42) -> 0.58 | J44: =MEDIAN(J38:J42) -> 0.07685897
B45: Average - Broad Set | G45: =AVERAGE(G38:G42) -> 0.6214702 | H45: =AVERAGE(H38:H42) -> 0.30425908 | I45: =AVERAGE(I38:I42) -> 0.71 | J45: =AVERAGE(J38:J42) -> 0.1801566
B50: =B2 -> Mankind Pharma Ltd
B51: Beta Analysis - 5 Years Monthly
B53: Comparable Company | D53: Ticker | E53: No. of Monthly Observations | F53: Market Cap | G53: Asset Beta | H53: 5 Years Avg D/E | I53: Equity Beta | J53: 5 Years Avg D/D+E | L53: Consideration ? | M53: Narrow Set
B55: Sun Pharmaceutical Industries Ltd | D55: NSE: SUNPHARMA | E55: 60 | F55: 380750 | G55: =I55/(1+(H55*(1-$D$19))) -> 0.53918512 | H55: ='Assumptions Working'!Z833 -> 0.051472427 | I55: 0.56 | J55: ='Assumptions Working'!AA833 -> 0.048127993 | L55: Yes | M55: =IF(L55="Yes","TRUE","FALSE") -> TRUE | O55: Yes
B56: Torrent Pharmaceuticals Ltd | D56: NSE: TORNTPHARM | E56: 60 | F56: 120928 | G56: =I56/(1+(H56*(1-$D$19))) -> 0.22464321 | H56: ='Assumptions Working'!Z841 -> 0.62532815 | I56: 0.33 | J56: ='Assumptions Working'!AA841 -> 0.37957189 | L56: No | M56: =IF(L56="Yes","TRUE","FALSE") -> FALSE | O56: No
B57: Cipla Ltd | D57: NSE: CIPLA | E57: 60 | F57: 120016 | G57: =I57/(1+(H57*(1-$D$19))) -> 0.39929192 | H57: ='Assumptions Working'!Z849 -> 0.035756911 | I57: 0.41 | J57: ='Assumptions Working'!AA849 -> 0.033328883 | L57: Yes | M57: =IF(L57="Yes","TRUE","FALSE") -> TRUE
B58: Dr. Reddy's Laboratories Ltd | D58: NSE: DRREDDY | E58: 60 | F58: 10101 | G58: =I58/(1+(H58*(1-$D$19))) -> 0.61795716 | H58: ='Assumptions Working'!AG833 -> 0.4359371 | I58: 0.82 | J58: ='Assumptions Working'!AH833 -> 0.24761256 | L58: No | M58: =IF(L58="Yes","TRUE","FALSE") -> FALSE
B59: Zydus Lifesciences Ltd | D59: NSE: ZYDUSLIFE | E59: 60 | F59: 94199 | G59: =I59/(1+(H59*(1-$D$19))) -> 0.68675449 | H59: ='Assumptions Working'!AG841 -> 0.1422061 | I59: 0.76 | J59: ='Assumptions Working'!AH841 -> 0.11916452 | L59: Yes | M59: =IF(L59="Yes","TRUE","FALSE") -> TRUE
B61: Median - Broad Set | G61: =MEDIAN(G55:G59) -> 0.53918512 | H61: =MEDIAN(H55:H59) -> 0.1422061 | I61: =MEDIAN(I55:I59) -> 0.56 | J61: =MEDIAN(J55:J59) -> 0.11916452
B62: Average - Broad Set | G62: =AVERAGE(G55:G59) -> 0.49356638 | H62: =AVERAGE(H55:H59) -> 0.25814014 | I62: =AVERAGE(I55:I59) -> 0.576 | J62: =AVERAGE(J55:J59) -> 0.16556117
B67: Blume Beta Analysis - 5 Years Monthly
B69: Comparable Company | D69: Ticker | E69: No. of Monthly Observations | F69: Market Cap | G69: Asset Beta | H69: 5 Years Avg D/E | I69: Equity Beta | J69: 5 Years Avg D/D+E | L69: Consideration ? | M69: Narrow Set
B71: Sun Pharmaceutical Industries Ltd | D71: NSE: SUNPHARMA | E71: 60 | F71: 380750 | G71: =I71/(1+(H71*(1-$D$19))) -> 0.53918512 | H71: =H55 -> 0.051472427 | I71: =I55 -> 0.56 | J71: =J55 -> 0.048127993 | L71: Yes | M71: =IF(L71="Yes","TRUE","FALSE") -> TRUE | O71: Yes
B72: Torrent Pharmaceuticals Ltd | D72: NSE: TORNTPHARM | E72: 60 | F72: 120928 | G72: =I72/(1+(H72*(1-$D$19))) -> 0.22464321 | H72: =H56 -> 0.62532815 | I72: =I56 -> 0.33 | J72: =J56 -> 0.37957189 | L72: Yes | M72: =IF(L72="Yes","TRUE","FALSE") -> TRUE | O72: No
B73: Cipla Ltd | D73: NSE: CIPLA | E73: 60 | F73: 120016 | G73: =I73/(1+(H73*(1-$D$19))) -> 0.39929192 | H73: =H57 -> 0.035756911 | I73: =I57 -> 0.41 | J73: =J57 -> 0.033328883 | L73: Yes | M73: =IF(L73="Yes","TRUE","FALSE") -> TRUE
B74: Dr. Reddy's Laboratories Ltd | D74: NSE: DRREDDY | E74: 60 | F74: 10101 | G74: =I74/(1+(H74*(1-$D$19))) -> 0.61795716 | H74: =H58 -> 0.4359371 | I74: =I58 -> 0.82 | J74: =J58 -> 0.24761256 | L74: No | M74: =IF(L74="Yes","TRUE","FALSE") -> FALSE
B75: Zydus Lifesciences Ltd | D75: NSE: ZYDUSLIFE | E75: 60 | F75: 94199 | G75: =I75/(1+(H75*(1-$D$19))) -> 0.68675449 | H75: =H59 -> 0.1422061 | I75: =I59 -> 0.76 | J75: =J59 -> 0.11916452 | L75: Yes | M75: =IF(L75="Yes","TRUE","FALSE") -> TRUE
B77: Median - Broad Set | G77: =MEDIAN(G71:G75) -> 0.53918512 | H77: =MEDIAN(H71:H75) -> 0.1422061 | I77: =MEDIAN(I71:I75) -> 0.56 | J77: =MEDIAN(J71:J75) -> 0.11916452
B78: Average - Broad Set | G78: =AVERAGE(G71:G75) -> 0.49356638 | H78: =AVERAGE(H71:H75) -> 0.25814014 | I78: =AVERAGE(I71:I75) -> 0.576 | J78: =AVERAGE(J71:J75) -> 0.16556117
B80: ="We are taking "&"=G84 "&"as asset beta of botteling unit" -> We are taking =G84 as asset beta of botteling unit

Sheet DCF Val
B2: ='Input Sheet'!C5 -> Mankind Pharma Ltd
B3: DCF Model
W4: Mid Year Convention
W5: Yes
W6: No
E8: Actual | J8: Explicit Forecast Period | O8: Maturity Period
B9: In INR Crores unless stated otherwise | E9: ='3StatementModel'!D9 -> 2021 | F9: ='3StatementModel'!E9 -> 2022 | G9: ='3StatementModel'!F9 -> 2023 | H9: ='3StatementModel'!G9 -> 2024 | I9: ='3StatementModel'!H9 -> 2025 | J9: ='3StatementModel'!I9 -> 2026 | K9: ='3StatementModel'!J9 -> 2027 | L9: ='3StatementModel'!K9 -> 2028 | ... S9: ='3StatementModel'!R9 -> 2035
A11: # | B11: Free Cash Flow to Firm
B13: EBITDA | E13: ='3StatementModel'!D25 -> 1657.5928 | F13: ='3StatementModel'!E25 -> 1989.3662 | G13: ='3StatementModel'!F25 -> 1900.6581 | H13: ='3StatementModel'!G25 -> 2535.1033 | I13: ='3StatementModel'!H25 -> 2651.86 | J13: ='3StatementModel'!I25 -> 3096.9159 | K13: ='3StatementModel'!J25 -> 3708.5928 | L13: ='3StatementModel'!K25 -> 4380.6704 | ... S13: ='3StatementModel'!R25 -> 10332.767
B14: Less: Depreciation & Amortization | E14: ='3StatementModel'!D29*-1 -> -118.9703 | F14: ='3StatementModel'!E29*-1 -> -166.6192 | G14: ='3StatementModel'!F29*-1 -> -325.9195 | H14: ='3StatementModel'!G29*-1 -> -398.2537 | I14: ='3StatementModel'!H29*-1 -> -621 | J14: ='3StatementModel'!I29*-1 -> -661.80719 | K14: ='3StatementModel'!J29*-1 -> -706.62506 | L14: ='3StatementModel'!K29*-1 -> -764.83403 | ... S14: ='3StatementModel'!R29*-1 -> -1318.3361
B15: EBIT | E15: =SUM(E13:E14) -> 1538.6225 | F15: =SUM(F13:F14) -> 1822.747 | G15: =SUM(G13:G14) -> 1574.7386 | H15: =SUM(H13:H14) -> 2136.8496 | I15: =SUM(I13:I14) -> 2030.86 | J15: =SUM(J13:J14) -> 2435.1087 | K15: =SUM(K13:K14) -> 3001.9677 | L15: =SUM(L13:L14) -> 3615.8363 | ... S15: =SUM(S13:S14) -> 9014.4304
B16: Less: Tax | E16: ='3StatementModel'!D39 -> -398.5839 | F16: ='3StatementModel'!E39 -> -521.6435 | G16: ='3StatementModel'!F39 -> -361.5633 | H16: ='3StatementModel'!G39 -> -457.5865 | I16: ='3StatementModel'!H39 -> -509.74 | J16: ='3StatementModel'!I39 -> -576.44153 | K16: ='3StatementModel'!J39 -> -750.49335 | L16: ='3StatementModel'!K39 -> -914.98667 | ... S16: ='3StatementModel'!R39 -> -2441.7271
B17: EBIT (1-T) | E17: =SUM(E15:E16) -> 1140.0386 | F17: =SUM(F15:F16) -> 1301.1035 | G17: =SUM(G15:G16) -> 1213.1753 | H17: =SUM(H15:H16) -> 1679.2631 | I17: =SUM(I15:I16) -> 1521.12 | J17: =SUM(J15:J16) -> 1858.6672 | K17: =SUM(K15:K16) -> 2251.4744 | L17: =SUM(L15:L16) -> 2700.8497 | ... S17: =SUM(S15:S16) -> 6572.7033
B18: Add: Depreciation & Amortization | E18: ='3StatementModel'!D29 -> 118.9703 | F18: ='3StatementModel'!E29 -> 166.6192 | G18: ='3StatementModel'!F29 -> 325.9195 | H18: ='3StatementModel'!G29 -> 398.2537 | I18: ='3StatementModel'!H29 -> 621 | J18: ='3StatementModel'!I29 -> 661.80719 | K18: ='3StatementModel'!J29 -> 706.62506 | L18: ='3StatementModel'!K29 -> 764.83403 | ... S18: ='3StatementModel'!R29 -> 1318.3361
B19: Cash NOPAT | E19: =SUM(E17:E18) -> 1259.0089 | F19: =SUM(F17:F18) -> 1467.7227 | G19: =SUM(G17:G18) -> 1539.0948 | H19: =SUM(H17:H18) -> 2077.5168 | I19: =SUM(I17:I18) -> 2142.12 | J19: =SUM(J17:J18) -> 2520.4744 | K19: =SUM(K17:K18) -> 2958.0994 | L19: =SUM(L17:L18) -> 3465.6837 | ... S19: =SUM(S17:S18) -> 7891.0394
B20: Less: Reinvestments
B21: Change in Working Capital | E21: ='3StatementModel'!D124 -> -94.0292 | F21: ='3StatementModel'!E124 -> -586.1207 | G21: ='3StatementModel'!F124 -> 167.1674 | H21: ='3StatementModel'!G124 -> 20.4159 | I21: ='3StatementModel'!H124 -> -146.42 | J21: ='3StatementModel'!I124 -> 973.69968 | K21: ='3StatementModel'!J124 -> -468.00419 | L21: ='3StatementModel'!K124 -> -376.49425 | ... S21: ='3StatementModel'!R124 -> -1334.882
B22: Capex During the Year | E22: ='3StatementModel'!D128 -> -307.6859 | F22: ='3StatementModel'!E128 -> -2325.368 | G22: ='3StatementModel'!F128 -> -826.0211 | H22: ='3StatementModel'!G128 -> -381.7042 | I22: ='3StatementModel'!H128 -> -519 | J22: ='3StatementModel'!I128 -> -652.91502 | K22: ='3StatementModel'!J128 -> -717.086 | L22: ='3StatementModel'!K128 -> -931.34344 | ... S22: ='3StatementModel'!R128 -> -1713.8928
B23: Free Cash Flow to Firm | E23: =E19+SUM(E21:E22) -> 857.2938 | F23: =F19+SUM(F21:F22) -> -1443.766 | G23: =G19+SUM(G21:G22) -> 880.2411 | H23: =H19+SUM(H21:H22) -> 1716.2285 | I23: =I19+SUM(I21:I22) -> 1476.7 | J23: =J19+SUM(J21:J22) -> 2841.259 | K23: =K19+SUM(K21:K22) -> 1773.0093 | L23: =L19+SUM(L21:L22) -> 2157.846 | ... S23: =S19+SUM(S21:S22) -> 4842.2646
B25: Discount Period (Years) | C25: Mid Year? | D25: Yes | J25: =IF(D25="Yes",(J9-I9)/2,J9-I9) -> 0.5 | K25: =J25+1 -> 1.5 | L25: =K25+1 -> 2.5 | M25: =L25+1 -> 3.5 | N25: =M25+1 -> 4.5 | O25: =N25+1 -> 5.5 | P25: =O25+1 -> 6.5 | Q25: =P25+1 -> 7.5 | R25: =Q25+1 -> 8.5 | S25: =R25+1 -> 9.5
B26: Discount Rate (WACC) | C26: =WACC!E24 -> 0.1
B27: Present Value Factor | J27: =1/(1+$C$26)^J25 -> 0.95346259 | K27: =1/(1+$C$26)^K25 -> 0.86678417 | L27: =1/(1+$C$26)^L25 -> 0.78798561 | M27: =1/(1+$C$26)^M25 -> 0.71635056 | N27: =1/(1+$C$26)^N25 -> 0.65122778 | O27: =1/(1+$C$26)^O25 -> 0.59202525 | P27: =1/(1+$C$26)^P25 -> 0.53820477 | Q27: =1/(1+$C$26)^Q25 -> 0.48927707 | ... S27: =1/(1+$C$26)^S25 -> 0.40436121
B29: Present Value of Free Cash Flow to Firm | J29: =J23*J27 -> 2709.0342 | K29: =K23*K27 -> 1536.8164 | L29: =L23*L27 -> 1700.3516 | M29: =M23*M27 -> 1817.2887 | N29: =N23*N27 -> 2011.2518 | O29: =O23*O27 -> 362.95529 | P29: =P23*P27 -> 1884.2103 | Q29: =Q23*Q27 -> 1907.5491 | ... S29: =S23*S27 -> 1958.024
A31: # | B31: DCF Calculation - Perpetuity Growth
B33: Perpetual Growth Rate | C33: =WACC!E7 -> 0.0421
B34: Terminal Year FCFF x (1+PGR) | C34: =S23*(1+C33) -> 5046.1239
B35: Terminal Value | C35: =C34/(C26-C33) -> 87152.399
B36: Present Value of Terminal Value | C36: =C35*S27 -> 35241.05
B37: Present Value of FCFFs | C37: =SUM(J29:S29) -> 17819.653
B38: Enterprise Value | C38: =SUM(C36:C37) -> 53060.703
B39: Implied Exit Multiple | C39: =C38/S13 -> 5.1351884
B40: Implied EV/EBITDA | C40: =C38/'3StatementModel'!H25 -> 20.008863
B41: Less: Debt | C41: =SUM('3StatementModel'!H90,'3StatementModel'!H99)*-1 -> -8483.03
B42: Add: Cash | C42: =SUM('3StatementModel'!H68,'3StatementModel'!H69) -> 554.5
B43: Less: Minority Interest | C43: ='3StatementModel'!H84*-1 -> -235.79
B44: Add: Non Operating Asset | C44: ='3StatementModel'!M59 -> 360.57
B45: Equity Value | C45: =SUM(C38,C41,C42,C43,C44) -> 45256.953
B46: Less: Value of Options | C46: ='Option value'!E28*-1 -> -191.2186
B47: Equity Value for Shareholders | C47: =SUM(C45:C46) -> #VALUE!
A50: # | B50: DCF Calculation - Exit Multiple
B52: Exit Multiple | C52: 12 | D52: 4
B53: Terminal Year EBITDA | C53: =S13 -> 10332.767
B54: Terminal Value | C54: =C53*C52 -> 123993.2
B55: Present Value of Terminal Value | C55: =C54*S27 -> 50138.04
B56: Present Value of FCFFs | C56: =C37 -> 17819.653
B57: Enterprise Value | C57: =SUM(C55:C56) -> 67957.693
B58: Implied Exit Multiple | C58: =C57/S13 -> 6.5769117
B59: Implied EV/EBITDA | C59: =C57/'3StatementModel'!H25 -> 25.626426
B60: Less: Debt | C60: ='DCF Val'!C41 -> -8483.03
B61: Add: Cash | C61: ='DCF Val'!C42 -> 554.5
B62: =B43 -> Less: Minority Interest | C62: =C43 -> -235.79
B63: =B44 -> Add: Non Operating Asset | C63: =C44 -> 360.57
B64: Equity Value | C64: =SUM(C60:C63,C57) -> 60153.943
B65: =B46 -> Less: Value of Options | C65: =C46 -> -191.2186
B66: =B47 -> Equity Value for Shareholders | C66: =SUM(C64:C65) -> #VALUE!
A68: # | B68: Sensitivity Analysis
E69: WACC
D70: =C47 -> 0 | E70: 0.09 | F70: 0.1 | G70: 0.11 | H70: 0.12 | I70: 0.13 | J70: 0.14 | K70: 0.15
C71: Terminal Growth Rate % | D71: 0.03 | E71: 0 | F71: 0 | G71: 0 | H71: 0 | I71: 0 | J71: 0 | K71: 0
D72: 0.04 | E72: 0 | F72: 0 | G72: 0 | H72: 0 | I72: 0 | J72: 0 | K72: 0
D73: 0.05 | E73: 0 | F73: 0 | G73: 0 | H73: 0 | I73: 0 | J73: 0 | K73: 0
D74: 0.06 | E74: 0 | F74: 0 | G74: 0 | H74: 0 | I74: 0 | J74: 0 | K74: 0
D75: 0.07 | E75: 0 | F75: 0 | G75: 0 | H75: 0 | I75: 0 | J75: 0 | K75: 0
E78: WACC
D79: =C66 -> #VALUE! | E79: 0.09 | F79: 0.1 | G79: 0.11 | H79: 0.12 | I79: 0.13 | J79: 0.14 | K79: 0.15
C80: Exit Multiple | D80: 11 | E80: #VALUE! | F80: #VALUE! | G80: #VALUE! | H80: #VALUE! | I80: #VALUE! | J80: #VALUE! | K80: #VALUE!
D81: 12 | E81: #VALUE! | F81: #VALUE! | G81: #VALUE! | H81: #VALUE! | I81: #VALUE! | J81: #VALUE! | K81: #VALUE!
D82: 13 | E82: #VALUE! | F82: #VALUE! | G82: #VALUE! | H82: #VALUE! | I82: #VALUE! | J82: #VALUE! | K82: #VALUE!
D83: 14 | E83: #VALUE! | F83: #VALUE! | G83: #VALUE! | H83: #VALUE! | I83: #VALUE! | J83: #VALUE! | K83: #VALUE!
D84: 15 | E84: #VALUE! | F84: #VALUE! | G84: #VALUE! | H84: #VALUE! | I84: #VALUE! | J84: #VALUE! | K84: #VALUE!

Sheet Relative >

Sheet Comps Description
B2: Comparable Companies | C2: Market Cap (in Cr) | D2: Segment | E2: Industry | F2: Enterprise Value | G2: Stock Price | H2: Debt | I2: Description
B4: NSE: CIPLA | C4: 123315 | D4: OTC + Global Generics | E4: Pharmaceutical | F4: 122954 | G4: 1527 | H4: 91 | I4: Cipla is a leading Indian multinational pharmaceutical company headquartered in Mumbai, with operations in over 86 countries. Its core business revolves around branded generics, catering to acute and chronic therapy areas such as respiratory, cardiovascular, diabetes, anti-infectives, gastrointestinal, dermatology, and oncology. Cipla is also the world’s largest supplier of antiretroviral drugs for HIV/AIDS treatment. Alongside prescription medicines, it has a growing consumer health portfolio including brands like Cofsils and Nicotex. The company operates 47 manufacturing facilities worldwide and maintains a strong focus on R&D to deliver affordable, high-quality medicines. Its business model emphasizes accessibility, therapeutic diversity, and expansion in both domestic and emerging markets, with selective presence in regulated markets like the U.S. and Europe.
B6: NSE: ZYDUSLIFE | C6: 94802 | D6: Wellness + Vaccines | E6: Pharmaceutical | F6: 95059 | G6: 942 | H6: 3169 | I6: Zydus Lifesciences (formerly Cadila Healthcare) is an integrated pharmaceutical company headquartered in Ahmedabad, operating across generics, branded formulations, consumer wellness, vaccines, biologics, and animal health. Its branded generics portfolio covers key therapeutic areas such as cardiovascular, diabetes, respiratory, dermatology, oncology, and gastroenterology. The consumer wellness division includes popular OTC brands like Sugar Free, Complan, and Everyuth. Zydus maintains a balanced business model with a strong India base complemented by exports to the U.S., Latin America, Africa, and other emerging markets. The company also invests in novel drug discovery and biologics, developing products in metabolic disorders, oncology, and autoimmune diseases. Its diversified portfolio, significant domestic market share, and presence in consumer healthcare make it closely comparable to Mankind Pharma’s brand-led, multi-therapy, and India-focused business model.
B8: NSE: TORNTPHARM | C8: 122573 | E8: Pharmaceutical | F8: 125196 | G8: 3622 | H8: 3025 | I8: Torrent Pharmaceuticals, part of the Torrent Group and based in Ahmedabad, is a major player in the branded generics space with a strong domestic presence. Its portfolio covers a wide range of therapy areas, including cardiovascular, central nervous system (CNS), gastrointestinal, diabetology, anti-infectives, and pain management, alongside niche areas like oncology, nephrology, respiratory, and pediatrics. Torrent operates in over 40 countries and has over 2,000 registered products globally. The company’s business model is built on brand-led growth in India, supported by strategic international markets. Torrent emphasizes specialty-focused marketing and deep relationships with healthcare professionals, enabling strong brand recall and prescription loyalty. While its exports contribute meaningfully, the company’s revenue is largely India-centric, making it a direct comparable to Mankind Pharma in terms of therapy mix and domestic dominance.

Sheet Relative_Val
B2: In INR Crores
D3: Market Data | I3: Financials | AB3: Multiples
I4: 2025 | J4: =I4+1 -> 2026 | K4: =J4+1 -> 2027 | L4: =I4 -> 2025 | M4: =J4 -> 2026 | N4: =K4 -> 2027 | O4: =I4 -> 2025 | P4: =J4 -> 2026 | Q4: =K4 -> 2027 | R4: =O4 -> 2025 | S4: =P4 -> 2026 | T4: =Q4 -> 2027 | U4: =I4 -> 2025 | V4: =J4 -> 2026 | W4: =K4 -> 2027 | X4: =U4 -> 2025 | Y4: =V4 -> 2026 | Z4: =W4 -> 2027 | AB4: =U4 -> 2025 | AC4: =V4 -> 2026 | AD4: =W4 -> 2027 | AE4: =AB4 -> 2025 | AF4: =AC4 -> 2026 | AG4: =AD4 -> 2027 | AH4: =AE4 -> 2025 | AI4: =AF4 -> 2026 | AJ4: =AG4 -> 2027
B5: Relative Valuation | D5: Ticker | E5: Stock Price | F5: Market Cap | G5: Debt | H5: EV | I5: Revenue | J5: Revenue | K5: Revenue | L5: Revenue Growth (%) | M5: Revenue Growth (%) | N5: Revenue Growth (%) | O5: EBITDA | P5: EBITDA | Q5: EBITDA | R5: EBITDA Margins (%) | S5: EBITDA Margins (%) | T5: EBITDA Margins (%) | U5: Net Profit | V5: Net Profit | W5: Net Profit | X5: Net Profit Growth (%) | Y5: Net Profit Growth (%) | Z5: Net Profit Growth (%) | AB5: EV/Revenue | AC5: =AB5 -> EV/Revenue | AD5: =AC5 -> EV/Revenue | AE5: EV/EBITDA | AF5: =AE5 -> EV/EBITDA | AG5: =AF5 -> EV/EBITDA | AH5: PE | AI5: PE | AJ5: PE
B7: Mankind Pharma | D7: NSE: MANKIND | E7: 2481 | F7: 102398 | G7: 8483.03 | H7: 110355 | I7: ='3StatementModel'!H13 -> 12207 | J7: ='3StatementModel'!I13 -> 14404.26 | K7: ='3StatementModel'!J13 -> 16780.963 | L7: ='3StatementModel'!H13/'3StatementModel'!G13-1 -> 0.18115784 | M7: ='3StatementModel'!I13/'3StatementModel'!H13-1 -> 0.18 | N7: ='3StatementModel'!J13/'3StatementModel'!I13-1 -> 0.165 | O7: ='3StatementModel'!H25 -> 2651.86 | P7: ='3StatementModel'!I25 -> 3096.9159 | Q7: ='3StatementModel'!J25 -> 3708.5928 | R7: ='3StatementModel'!H25/'3StatementModel'!G25-1 -> 0.046055993 | S7: ='3StatementModel'!I25/'3StatementModel'!H25-1 -> 0.16782783 | T7: ='3StatementModel'!J25/'3StatementModel'!I25-1 -> 0.19751163 | U7: ='3StatementModel'!H40 -> 1616.27 | V7: ='3StatementModel'!I40 -> 1729.3246 | W7: ='3StatementModel'!J40 -> 2251.4801 | X7: ='3StatementModel'!H40/'3StatementModel'!G40-1 -> -0.15439449 | Y7: ='3StatementModel'!I40/'3StatementModel'!H40-1 -> 0.069947829 | Z7: ='3StatementModel'!J40/'3StatementModel'!I40-1 -> 0.30194186
B9: CIPLA | D9: ='Comps Description'!B4 -> NSE: CIPLA | E9: ='Comps Description'!G4 -> 1527 | F9: ='Comps Description'!C4 -> 123315 | G9: ='Comps Description'!H4 -> 91 | H9: ='Comps Description'!F4 -> 122954 | I9: =Benchmarking!G27 -> 27548 | J9: =Benchmarking!H27 -> 29484 | K9: =Benchmarking!I27 -> 32849 | L9: =Benchmarking!G28 -> 0.068829053 | M9: =J9/I9-1 -> 0.070277334 | N9: =K9/J9-1 -> 0.1141297 | O9: =Benchmarking!G48 -> 7128 | P9: =Benchmarking!H48 -> 7244 | Q9: =Benchmarking!I48 -> 7765 | R9: =Benchmarking!G49 -> 0.25874837 | S9: =P9/O9-1 -> 0.01627385 | T9: =Q9/P9-1 -> 0.07192159 | U9: =Benchmarking!P27 -> 5269 | V9: =Benchmarking!Q27 -> 5228 | W9: =Benchmarking!R27 -> 5588 | X9: =Benchmarking!P28 -> 0.19126615 | Y9: =V9/U9-1 -> -0.0077813627 | Z9: =W9/V9-1 -> 0.068859985 | AB9: =$H9/I9 -> 4.4632641 | AC9: =$H9/J9 -> 4.170194 | AD9: =$H9/K9 -> 3.7430059 | AE9: =$H9/O9 -> 17.249439 | AF9: =$H9/P9 -> 16.973219 | AG9: =$H9/Q9 -> 15.834385 | AH9: =$F9/U9 -> 23.403872 | AI9: =$F9/V9 -> 23.587414 | AJ9: =$F9/W9 -> 22.067824 | AM9: EV/Revenue
B10: Zydus Lifesciences | D10: ='Comps Description'!B6 -> NSE: ZYDUSLIFE | E10: ='Comps Description'!G6 -> 942 | F10: ='Comps Description'!C6 -> 94802 | G10: ='Comps Description'!H6 -> 3169 | H10: ='Comps Description'!F6 -> 95059 | I10: =Benchmarking!G33 -> 23241 | J10: =Benchmarking!H33 -> 25910 | K10: =Benchmarking!I33 -> 28228 | L10: =Benchmarking!G34 -> 0.18898041 | M10: =J10/I10-1 -> 0.11484015 | N10: =K10/J10-1 -> 0.089463528 | O10: =Benchmarking!G54 -> 6895 | P10: =Benchmarking!H54 -> 6860 | Q10: =Benchmarking!I54 -> 6641 | R10: =Benchmarking!G55 -> 0.29667398 | S10: =P10/O10-1 -> -0.0050761421 | T10: =Q10/P10-1 -> -0.031924198 | U10: =Benchmarking!P33 -> 4673 | V10: =Benchmarking!Q33 -> 4482 | W10: =Benchmarking!R33 -> 4247 | X10: =Benchmarking!P34 -> 0.20106708 | Y10: =V10/U10-1 -> -0.040873101 | Z10: =W10/V10-1 -> -0.05243195 | AB10: =$H10/I10 -> 4.0901424 | AC10: =$H10/J10 -> 3.6688151 | AD10: =$H10/K10 -> 3.3675429 | AE10: =$H10/O10 -> 13.786657 | AF10: =$H10/P10 -> 13.856997 | AG10: =$H10/Q10 -> 14.313959 | AH10: =$F10/U10 -> 20.287182 | AI10: =$F10/V10 -> 21.151718 | AJ10: =$F10/W10 -> 22.32211 | AM10: EV/EBITDA
B11: Torrent | D11: ='Comps Description'!B8 -> NSE: TORNTPHARM | E11: ='Comps Description'!G8 -> 3622 | F11: ='Comps Description'!C8 -> 122573 | G11: ='Comps Description'!H8 -> 3025 | H11: ='Comps Description'!F8 -> 125196 | I11: =Benchmarking!G24 -> 11516 | J11: =Benchmarking!H24 -> 14085 | K11: =Benchmarking!I24 -> 18861 | L11: =Benchmarking!G25 -> 0.073452647 | M11: =J11/I11-1 -> 0.22308093 | N11: =K11/J11-1 -> 0.33908413 | O11: =Benchmarking!G45 -> 3721 | P11: =Benchmarking!H45 -> 4677 | Q11: =Benchmarking!I45 -> 6143 | R11: =Benchmarking!G46 -> 0.32311567 | S11: =P11/O11-1 -> 0.25692018 | T11: =Q11/P11-1 -> 0.31344879 | U11: =Benchmarking!P24 -> 1911 | V11: =Benchmarking!Q24 -> 2383 | W11: =Benchmarking!R24 -> 2797 | X11: =Benchmarking!P25 -> 0.16594304 | Y11: =V11/U11-1 -> 0.2469911 | Z11: =W11/V11-1 -> 0.17373059 | AB11: =$H11/I11 -> 10.871483 | AC11: =$H11/J11 -> 8.8886049 | AD11: =$H11/K11 -> 6.6378241 | AE11: =$H11/O11 -> 33.645794 | AF11: =$H11/P11 -> 26.768441 | AG11: =$H11/Q11 -> 20.38027 | AH11: =$F11/U11 -> 64.140764 | AI11: =$F11/V11 -> 51.436425 | AJ11: =$F11/W11 -> 43.823025 | AM11: P/E
B13: High | AB13: =MAX(AB9:AB11) -> 10.871483 | AC13: =MAX(AC9:AC11) -> 8.8886049 | AD13: =MAX(AD9:AD11) -> 6.6378241 | AE13: =MAX(AE9:AE11) -> 33.645794 | AF13: =MAX(AF9:AF11) -> 26.768441 | AG13: =MAX(AG9:AG11) -> 20.38027 | AH13: =MAX(AH9:AH11) -> 64.140764 | AI13: =MAX(AI9:AI11) -> 51.436425 | AJ13: =MAX(AJ9:AJ11) -> 43.823025
B14: 75th Percentile | AB14: =QUARTILE(AB9:AB11,3) -> 7.6673736 | AC14: =QUARTILE(AC9:AC11,3) -> 6.5293995 | AD14: =QUARTILE(AD9:AD11,3) -> 5.190415 | AE14: =QUARTILE(AE9:AE11,3) -> 25.447616 | AF14: =QUARTILE(AF9:AF11,3) -> 21.87083 | AG14: =QUARTILE(AG9:AG11,3) -> 18.107328 | AH14: =QUARTILE(AH9:AH11,3) -> 43.772318 | AI14: =QUARTILE(AI9:AI11,3) -> 37.511919 | AJ14: =QUARTILE(AJ9:AJ11,3) -> 33.072567
B15: Average | AB15: =AVERAGE(AB9:AB11) -> 6.4749632 | AC15: =AVERAGE(AC9:AC11) -> 5.5758713 | AD15: =AVERAGE(AD9:AD11) -> 4.5827909 | AE15: =AVERAGE(AE9:AE11) -> 21.56063 | AF15: =AVERAGE(AF9:AF11) -> 19.199553 | AG15: =AVERAGE(AG9:AG11) -> 16.842871 | AH15: =AVERAGE(AH9:AH11) -> 35.943939 | AI15: =AVERAGE(AI9:AI11) -> 32.058519 | AJ15: =AVERAGE(AJ9:AJ11) -> 29.404319
B16: Median | AB16: =MEDIAN(AB9:AB11) -> 4.4632641 | AC16: =MEDIAN(AC9:AC11) -> 4.170194 | AD16: =MEDIAN(AD9:AD11) -> 3.7430059 | AE16: =MEDIAN(AE9:AE11) -> 17.249439 | AF16: =MEDIAN(AF9:AF11) -> 16.973219 | AG16: =MEDIAN(AG9:AG11) -> 15.834385 | AH16: =MEDIAN(AH9:AH11) -> 23.403872 | AI16: =MEDIAN(AI9:AI11) -> 23.587414 | AJ16: =MEDIAN(AJ9:AJ11) -> 22.32211
B17: 25th Percentile | AB17: =QUARTILE(AB9:AB11,1) -> 4.2767033 | AC17: =QUARTILE(AC9:AC11,1) -> 3.9195046 | AD17: =QUARTILE(AD9:AD11,1) -> 3.5552744 | AE17: =QUARTILE(AE9:AE11,1) -> 15.518048 | AF17: =QUARTILE(AF9:AF11,1) -> 15.415108 | AG17: =QUARTILE(AG9:AG11,1) -> 15.074172 | AH17: =QUARTILE(AH9:AH11,1) -> 21.845527 | AI17: =QUARTILE(AI9:AI11,1) -> 22.369566 | AJ17: =QUARTILE(AJ9:AJ11,1) -> 22.194967
B18: Low | AB18: =MIN(AB9:AB11) -> 4.0901424 | AC18: =MIN(AC9:AC11) -> 3.6688151 | AD18: =MIN(AD9:AD11) -> 3.3675429 | AE18: =MIN(AE9:AE11) -> 13.786657 | AF18: =MIN(AF9:AF11) -> 13.856997 | AG18: =MIN(AG9:AG11) -> 14.313959 | AH18: =MIN(AH9:AH11) -> 20.287182 | AI18: =MIN(AI9:AI11) -> 21.151718 | AJ18: =MIN(AJ9:AJ11) -> 22.067824
B20: Relative Valuation
B22: Revenue | D22: =I7 -> 12207
B23: EBITDA | D23: =O7 -> 2651.86
B24: Earnings | D24: =U7 -> 1616.27
B25: Valuation Multiple | D25: EV/EBITDA
B26: =D25 -> EV/EBITDA | D26: =IF(B26=AM9,AB16,IF(B26=AM10,AE16,AH16)) -> 17.249439
B27: =IF(D25=AM11,"Equity Value",IF(D25=AM10,"Enterprise Value","Enterprise Value")) -> Enterprise Value | D27: =IF(D25=AM9,D26*D22,IF(D25=AM10,D26*D23,D26*D24)) -> 45743.097
B28: Less: Debt | D28: =IF($D$25=$AM$11,0,'DCF Val'!C41) -> -8483.03
B29: ='DCF Val'!B42 -> Add: Cash | D29: =IF($D$25=$AM$11,0,'DCF Val'!C42) -> 554.5
B30: ='DCF Val'!B43 -> Less: Minority Interest | D30: =IF($D$25=$AM$11,0,'DCF Val'!C43) -> -235.79
B31: ='DCF Val'!B44 -> Add: Non Operating Asset | D31: =IF($D$25=$AM$11,0,'DCF Val'!C44) -> 360.57
B32: ='DCF Val'!B45 -> Equity Value | D32: =SUM(D27:D31) -> 37939.347
B33: ='DCF Val'!B46 -> Less: Value of Options | D33: =IF($D$25=$AM$11,0,'DCF Val'!C46) -> -191.2186
B34: ='DCF Val'!B47 -> Equity Value for Shareholders | D34: =D32+D33 -> 37748.128

Sheet Benchmarking
A2: # | B2: Summary
B3: in % | C3: 2021 | D3: =C3+1 -> 2022 | E3: =D3+1 -> 2023 | F3: =E3+1 -> 2024 | G3: =F3+1 -> 2025 | H3: =G3+1 -> 2026 | I3: =H3+1 -> 2027 | J3: Average
B4: ="Average "& B18 -> Average Revenue Growth | C4: =C36 -> 0 | D4: =D36 -> 0.1045859 | E4: =E36 -> 0.1347363 | F4: =F36 -> 0.12449301 | G4: =G36 -> 0.11616429 | H4: =H36 -> 0.10742784 | I4: =I36 -> 0.1377236 | J4: =AVERAGE(C4:J4) -> 0.10359013
B5: ="Average "& B39 -> Average EBITDA margin | C5: =C57 -> 0.23022024 | D5: =D57 -> 0.21544031 | E5: =E57 -> 0.24931517 | F5: =F57 -> 0.27621313 | G5: =G57 -> 0.28545729 | H5: =H57 -> 0.27825544 | I5: =I57 -> 0.27378623 | J5: =AVERAGE(C5:J5) -> 0.25838397
B6: ="Average "& B60 -> Average EBIT margin | C6: =C78 -> 0.1501915 | D6: =D78 -> 0.14870181 | E6: =E78 -> 0.19500412 | F6: =F78 -> 0.23407998 | G6: =G78 -> 0.24671153 | H6: =H78 -> 0.22953446 | I6: =I78 -> 0.22296569 | J6: =AVERAGE(C6:J6) -> 0.20388416
B7: ="Average "& K18 -> Average PAT margin | C7: =L36 -> 0.12201461 | D7: =M36 -> 0.1072246 | E7: =N36 -> 0.15039369 | F7: =O36 -> 0.18321587 | G7: =P36 -> 0.18843976 | H7: =Q36 -> 0.17812683 | I7: =R36 -> 0.17259335 | J7: =AVERAGE(C7:J7) -> 0.15742982
B8: ="Average "& K39 -> Average PBT margin | C8: =L57 -> 0.1545539 | D8: =M57 -> 0.15190748 | E8: =N57 -> 0.19692434 | F8: =O57 -> 0.23752125 | G8: =P57 -> 0.24937424 | H8: =Q57 -> 0.23719545 | I8: =R57 -> 0.2290087 | J8: =AVERAGE(C8:J8) -> 0.20806934
B10: ="Median "&B18 -> Median Revenue Growth | C10: =C37 -> 0 | D10: =D37 -> 0.11368078 | E10: =E37 -> 0.14084321 | F10: =F37 -> 0.1327737 | G10: =G37 -> 0.084160018 | H10: =H37 -> 0.09187423 | I10: =I37 -> 0.10606351 | J10: =AVERAGE(C10:J10) -> 0.095627921
B11: ="Median "&B39 -> Median EBITDA margin | C11: =C58 -> 0.21585781 | D11: =D58 -> 0.20408824 | E11: =E58 -> 0.25735711 | F11: =F58 -> 0.27129483 | G11: =G58 -> 0.28692391 | H11: =H58 -> 0.27001241 | I11: =I58 -> 0.27300875 | J11: =AVERAGE(C11:J11) -> 0.25407758
B12: ="Median "&B60 -> Median EBIT margin | C12: =C79 -> 0.16989516 | D12: =D79 -> 0.16093974 | E12: =E79 -> 0.20668829 | F12: =F79 -> 0.23073078 | G12: =G79 -> 0.25408128 | H12: =H79 -> 0.22547279 | I12: =I79 -> 0.21960573 | J12: =AVERAGE(C12:J12) -> 0.20963054
B13: ="Median "&K18 -> Median PAT margin | C13: =L37 -> 0.12580968 | D13: =M37 -> 0.10636638 | E13: =N37 -> 0.12941788 | F13: =O37 -> 0.198157 | G13: =P37 -> 0.19126615 | H13: =Q37 -> 0.1729834 | I13: =R37 -> 0.17011172 | J13: =AVERAGE(C13:J13) -> 0.15630175
B14: ="Median "&K39 -> Median PBT margin | C14: =L58 -> 0.16656252 | D14: =M58 -> 0.14921517 | E14: =N58 -> 0.19199584 | F14: =O58 -> 0.23807707 | G14: =P58 -> 0.24680558 | H14: =Q58 -> 0.23064454 | I14: =R58 -> 0.22743463 | J14: =AVERAGE(C14:J14) -> 0.20724791
A18: # | B18: Revenue Growth | K18: PAT margin
B19: in % | C19: 2021 | D19: =C19+1 -> 2022 | E19: =D19+1 -> 2023 | F19: =E19+1 -> 2024 | G19: =F19+1 -> 2025 | H19: =G19+1 -> 2026 | I19: =H19+1 -> 2027 | K19: in % | L19: 2021 | M19: =L19+1 -> 2022 | N19: =M19+1 -> 2023 | O19: =N19+1 -> 2024 | P19: =O19+1 -> 2025 | Q19: =P19+1 -> 2026 | R19: =Q19+1 -> 2027
B21: Sun Pharmaceutical Industries Ltd | C21: 33498.1 | D21: 38654.5 | E21: 43885.7 | F21: 48496.9 | G21: 52578.4 | H21: 57409 | I21: 63498 | K21: Sun Pharmaceutical Industries Ltd | L21: 2272 | M21: 3389 | N21: 8513 | O21: 9610 | P21: 10965 | Q21: 11453 | R21: 13979
B22: Growth YoY % | D22: =D21/C21-1 -> 0.15393112 | E22: =E21/D21-1 -> 0.13533224 | F22: =F21/E21-1 -> 0.10507295 | G22: =G21/F21-1 -> 0.084160018 | H22: =H21/G21-1 -> 0.09187423 | I22: =I21/H21-1 -> 0.10606351 | K22: % Revenue | L22: =L21/C$21 -> 0.067824742 | M22: =M21/D$21 -> 0.087674139 | N22: =N21/E$21 -> 0.19398118 | O22: =O21/F$21 -> 0.198157 | P22: =P21/G$21 -> 0.20854571 | Q22: =Q21/H$21 -> 0.19949834 | R22: =R21/I$21 -> 0.22014867
B24: Torrent Pharmaceuticals Ltd | C24: 7886 | D24: 8419 | E24: 9620 | F24: 10728 | G24: 11516 | H24: 14085 | I24: 18861 | K24: Torrent Pharmaceuticals Ltd | L24: 1252 | M24: 777 | N24: 1245 | O24: 1656 | P24: 1911 | Q24: 2383 | R24: 2797
B25: Growth YoY % | D25: =D24/C24-1 -> 0.067588131 | E25: =E24/D24-1 -> 0.14265352 | F25: =F24/E24-1 -> 0.11517672 | G25: =G24/F24-1 -> 0.073452647 | H25: =H24/G24-1 -> 0.22308093 | I25: =I24/H24-1 -> 0.33908413 | K25: % Revenue | L25: =L24/C$24 -> 0.15876236 | M25: =M24/D$24 -> 0.092291246 | N25: =N24/E$24 -> 0.12941788 | O25: =O24/F$24 -> 0.15436242 | P25: =P24/G$24 -> 0.16594304 | Q25: =Q24/H$24 -> 0.16918708 | R25: =R24/I$24 -> 0.14829542
B27: Cipla Ltd | C27: 18989 | D27: 21623 | E27: 22753 | F27: 25774 | G27: 27548 | H27: 29484 | I27: 32849 | K27: Cipla Ltd | L27: 2389 | M27: 2547 | N27: 2833 | O27: 4154 | P27: 5269 | Q27: 5228 | R27: 5588
B28: Growth YoY % | D28: =D27/C27-1 -> 0.13871189 | E28: =E27/D27-1 -> 0.052259168 | F28: =F27/E27-1 -> 0.1327737 | G28: =G27/F27-1 -> 0.068829053 | H28: =H27/G27-1 -> 0.070277334 | I28: =I27/H27-1 -> 0.1141297 | K28: % Revenue | L28: =L27/C$27 -> 0.12580968 | M28: =M27/D$27 -> 0.11779124 | N28: =N27/E$27 -> 0.12451105 | O28: =O27/F$27 -> 0.16117017 | P28: =P27/G$27 -> 0.19126615 | Q28: =Q27/H$27 -> 0.17731651 | R28: =R27/I$27 -> 0.17011172
B30: Dr. Reddy's Laboratories Ltd | C30: 18420 | D30: 20514 | E30: 24670 | F30: 28011 | G30: 32644 | H30: 33854 | I30: 35204 | K30: Dr. Reddy's Laboratories Ltd | L30: 1952 | M30: 2182 | N30: 4507 | O30: 5578 | P30: 5725 | Q30: 5811 | R30: 6124
B31: Growth YoY % | D31: =D30/C30-1 -> 0.11368078 | E31: =E30/D30-1 -> 0.20259335 | F31: =F30/E30-1 -> 0.13542764 | G31: =G30/F30-1 -> 0.16539931 | H31: =H30/G30-1 -> 0.037066536 | I31: =I30/H30-1 -> 0.039877119 | K31: % Revenue | L31: =L30/C$30 -> 0.10597177 | M31: =M30/D$30 -> 0.10636638 | N31: =N30/E$30 -> 0.18269153 | O31: =O30/F$30 -> 0.19913605 | P31: =P30/G$30 -> 0.17537679 | Q31: =Q30/H$30 -> 0.17164885 | R31: =R30/I$30 -> 0.1739575
B33: Zydus Lifesciences Ltd | C33: 14403 | D33: 15109 | E33: 17237 | F33: 19547 | G33: 23241 | H33: 25910 | I33: 28228 | K33: Zydus Lifesciences Ltd | L33: 2185 | M33: 1994.388 | N33: 2092 | O33: 3973 | P33: 4673 | Q33: 4482 | R33: 4247
B34: Growth YoY % | D34: =D33/C33-1 -> 0.049017566 | E34: =E33/D33-1 -> 0.14084321 | F34: =F33/E33-1 -> 0.13401404 | G34: =G33/F33-1 -> 0.18898041 | H34: =H33/G33-1 -> 0.11484015 | I34: =I33/H33-1 -> 0.089463528 | K34: % Revenue | L34: =L33/C$33 -> 0.15170451 | M34: =M33/D$33 -> 0.132 | N34: =N33/E$33 -> 0.12136683 | O34: =O33/F$33 -> 0.2032537 | P34: =P33/G$33 -> 0.20106708 | Q34: =Q33/H$33 -> 0.1729834 | R34: =R33/I$33 -> 0.15045345
B36: Mean | D36: =AVERAGE(D34,D31,D28,D25,D22) -> 0.1045859 | E36: =AVERAGE(E34,E31,E28,E25,E22) -> 0.1347363 | F36: =AVERAGE(F34,F31,F28,F25,F22) -> 0.12449301 | G36: =AVERAGE(G34,G31,G28,G25,G22) -> 0.11616429 | H36: =AVERAGE(H34,H31,H28,H25,H22) -> 0.10742784 | I36: =AVERAGE(I34,I31,I28,I25,I22) -> 0.1377236 | K36: Mean | L36: =AVERAGE(L34,L31,L28,L25,L22) -> 0.12201461 | M36: =AVERAGE(M34,M31,M28,M25,M22) -> 0.1072246 | N36: =AVERAGE(N34,N31,N28,N25,N22) -> 0.15039369 | O36: =AVERAGE(O34,O31,O28,O25,O22) -> 0.18321587 | P36: =AVERAGE(P34,P31,P28,P25,P22) -> 0.18843976 | Q36: =AVERAGE(Q34,Q31,Q28,Q25,Q22) -> 0.17812683 | R36: =AVERAGE(R34,R31,R28,R25,R22) -> 0.17259335
B37: Median | D37: =MEDIAN(D34,D31,D28,D25,D22) -> 0.11368078 | E37: =MEDIAN(E34,E31,E28,E25,E22) -> 0.14084321 | F37: =MEDIAN(F34,F31,F28,F25,F22) -> 0.1327737 | G37: =MEDIAN(G34,G31,G28,G25,G22) -> 0.084160018 | H37: =MEDIAN(H34,H31,H28,H25,H22) -> 0.09187423 | I37: =MEDIAN(I34,I31,I28,I25,I22) -> 0.10606351 | K37: Median | L37: =MEDIAN(L34,L31,L28,L25,L22) -> 0.12580968 | M37: =MEDIAN(M34,M31,M28,M25,M22) -> 0.10636638 | N37: =MEDIAN(N34,N31,N28,N25,N22) -> 0.12941788 | O37: =MEDIAN(O34,O31,O28,O25,O22) -> 0.198157 | P37: =MEDIAN(P34,P31,P28,P25,P22) -> 0.19126615 | Q37: =MEDIAN(Q34,Q31,Q28,Q25,Q22) -> 0.1729834 | R37: =MEDIAN(R34,R31,R28,R25,R22) -> 0.17011172
A39: # | B39: EBITDA margin | K39: PBT margin
B40: in % | C40: 2021 | D40: =C40+1 -> 2022 | E40: =D40+1 -> 2023 | F40: =E40+1 -> 2024 | G40: =F40+1 -> 2025 | H40: =G40+1 -> 2026 | I40: =H40+1 -> 2027 | K40: in % | L40: 2021 | M40: =L40+1 -> 2022 | N40: =M40+1 -> 2023 | O40: =N40+1 -> 2024 | P40: =O40+1 -> 2025 | Q40: =P40+1 -> 2026 | R40: =Q40+1 -> 2027
B42: Sun Pharmaceutical Industries Ltd | C42: 8203 | D42: 10016 | E42: 11647 | F42: 13023 | G42: 15086 | H42: 16003 | I42: 18959 | K42: Sun Pharmaceutical Industries Ltd | L42: 2799 | M42: 4481 | N42: 9408 | O42: 11546 | P42: 14244 | Q42: 15081 | R42: 18182
B43: % Revenue | C43: =C42/C$21 -> 0.24487956 | D43: =D42/D$21 -> 0.25911601 | E43: =E42/E$21 -> 0.26539397 | F43: =F42/F$21 -> 0.26853263 | G43: =G42/G$21 -> 0.28692391 | H43: =H42/H$21 -> 0.2787542 | I43: =I42/I$21 -> 0.29857633 | K43: % Revenue | L43: =L42/C$21 -> 0.083556978 | M43: =M42/D21 -> 0.11592441 | N43: =N42/E21 -> 0.21437507 | O43: =O42/F21 -> 0.23807707 | P43: =P42/G21 -> 0.27090973 | Q43: =Q42/H21 -> 0.262694 | R43: =R42/I21 -> 0.28633973
B45: Torrent Pharmaceuticals Ltd | C45: 2361 | D45: 2342 | E45: 2842 | F45: 3368 | G45: 3721 | H45: 4677 | I45: 6143 | K45: Torrent Pharmaceuticals Ltd | L45: 1526 | M45: 1226 | N45: 1847 | O45: 2352 | P45: 2673 | Q45: 3186 | R45: 3740
B46: % Revenue | C46: =C45/C$24 -> 0.29939133 | D46: =D45/D$24 -> 0.27818031 | E46: =E45/E$24 -> 0.2954262 | F46: =F45/F$24 -> 0.31394482 | G46: =G45/G$24 -> 0.32311567 | H46: =H45/H$24 -> 0.33205538 | I46: =I45/I$24 -> 0.32569853 | K46: % Revenue | L46: =L45/C$24 -> 0.19350748 | M46: =M45/D$24 -> 0.145623 | N46: =N45/E$24 -> 0.19199584 | O46: =O45/F$24 -> 0.21923937 | P46: =P45/G$24 -> 0.23211184 | Q46: =Q45/H$24 -> 0.22619808 | R46: =R45/I$24 -> 0.19829277
B48: Cipla Ltd | C48: 4081 | D48: 4413 | E48: 5027 | F48: 6291 | G48: 7128 | H48: 7244 | I48: 7765 | K48: Cipla Ltd | L48: 3277 | M48: 3480 | N48: 4036 | O48: 5700 | P48: 6799 | Q48: 6989 | R48: 7471
B49: % Revenue | C49: =C48/C$27 -> 0.2149139 | D49: =D48/D$27 -> 0.20408824 | E49: =E48/E$27 -> 0.2209379 | F49: =F48/F$27 -> 0.24408318 | G49: =G48/G$27 -> 0.25874837 | H49: =H48/H$27 -> 0.24569258 | I49: =I48/I$27 -> 0.23638467 | K49: % Revenue | L49: =L48/C$27 -> 0.1725736 | M49: =M48/D$27 -> 0.16093974 | N49: =N48/E$27 -> 0.1773832 | O49: =O48/F$27 -> 0.2211531 | P49: =P48/G$27 -> 0.24680558 | Q49: =Q48/H$27 -> 0.23704382 | R49: =R48/I$27 -> 0.22743463
B51: Dr. Reddy's Laboratories Ltd | C51: 3243 | D51: 2737 | E51: 6349 | F51: 7933 | G51: 8547 | H51: 9141 | I51: 9611 | K51: Dr. Reddy's Laboratories Ltd | L51: 2884 | M51: 3061 | N51: 6048 | O51: 7201 | P51: 7680 | Q51: 7766 | R51: 8180
B52: % Revenue | C52: =C51/C$30 -> 0.17605863 | D52: =D51/D$30 -> 0.13342108 | E52: =E51/E$30 -> 0.25735711 | F52: =F51/F$30 -> 0.28321017 | G52: =G51/G$30 -> 0.26182453 | H52: =H51/H$30 -> 0.27001241 | I52: =I51/I$30 -> 0.27300875 | K52: % Revenue | L52: =L51/C$30 -> 0.15656895 | M52: =M51/D$30 -> 0.14921517 | N52: =N51/E$30 -> 0.24515606 | O52: =O51/F$30 -> 0.25707758 | P52: =P51/G$30 -> 0.23526529 | Q52: =Q51/H$30 -> 0.22939682 | R52: =R51/I$30 -> 0.23235996
B54: Zydus Lifesciences Ltd | C54: 3109 | D54: 3058 | E54: 3576 | F54: 5303 | G54: 6895 | H54: 6860 | I54: 6641 | K54: Zydus Lifesciences Ltd | L54: 2399 | M54: 2838 | N54: 2684 | O54: 4927 | P54: 6084 | Q54: 5976 | R54: 5663
B55: % Revenue | C55: =C54/C$33 -> 0.21585781 | D55: =D54/D$33 -> 0.20239592 | E55: =E54/E$33 -> 0.2074607 | F55: =F54/F$33 -> 0.27129483 | G55: =G54/G$33 -> 0.29667398 | H55: =H54/H$33 -> 0.26476264 | I55: =I54/I$33 -> 0.23526286 | K55: % Revenue | L55: =L54/C$33 -> 0.16656252 | M55: =M54/D$33 -> 0.18783507 | N55: =N54/E$33 -> 0.15571155 | O55: =O54/F$33 -> 0.25205914 | P55: =P54/G$33 -> 0.26177875 | Q55: =Q54/H$33 -> 0.23064454 | R55: =R54/I$33 -> 0.20061641
B57: Mean | C57: =AVERAGE(C55,C52,C49,C46,C43) -> 0.23022024 | D57: =AVERAGE(D55,D52,D49,D46,D43) -> 0.21544031 | E57: =AVERAGE(E55,E52,E49,E46,E43) -> 0.24931517 | F57: =AVERAGE(F55,F52,F49,F46,F43) -> 0.27621313 | G57: =AVERAGE(G55,G52,G49,G46,G43) -> 0.28545729 | H57: =AVERAGE(H55,H52,H49,H46,H43) -> 0.27825544 | I57: =AVERAGE(I55,I52,I49,I46,I43) -> 0.27378623 | K57: Mean | L57: =AVERAGE(L55,L52,L49,L46,L43) -> 0.1545539 | M57: =AVERAGE(M55,M52,M49,M46,M43) -> 0.15190748 | N57: =AVERAGE(N55,N52,N49,N46,N43) -> 0.19692434 | O57: =AVERAGE(O55,O52,O49,O46,O43) -> 0.23752125 | P57: =AVERAGE(P55,P52,P49,P46,P43) -> 0.24937424 | Q57: =AVERAGE(Q55,Q52,Q49,Q46,Q43) -> 0.23719545 | R57: =AVERAGE(R55,R52,R49,R46,R43) -> 0.2290087
B58: Median | C58: =MEDIAN(C55,C52,C49,C46,C43) -> 0.21585781 | D58: =MEDIAN(D55,D52,D49,D46,D43) -> 0.20408824 | E58: =MEDIAN(E55,E52,E49,E46,E43) -> 0.25735711 | F58: =MEDIAN(F55,F52,F49,F46,F43) -> 0.27129483 | G58: =MEDIAN(G55,G52,G49,G46,G43) -> 0.28692391 | H58: =MEDIAN(H55,H52,H49,H46,H43) -> 0.27001241 | I58: =MEDIAN(I55,I52,I49,I46,I43) -> 0.27300875 | K58: Median | L58: =MEDIAN(L55,L52,L49,L46,L43) -> 0.16656252 | M58: =MEDIAN(M55,M52,M49,M46,M43) -> 0.14921517 | N58: =MEDIAN(N55,N52,N49,N46,N43) -> 0.19199584 | O58: =MEDIAN(O55,O52,O49,O46,O43) -> 0.23807707 | P58: =MEDIAN(P55,P52,P49,P46,P43) -> 0.24680558 | Q58: =MEDIAN(Q55,Q52,Q49,Q46,Q43) -> 0.23064454 | R58: =MEDIAN(R55,R52,R49,R46,R43) -> 0.22743463
A60: # | B60: EBIT margin
B61: in % | C61: 2021 | D61: =C61+1 -> 2022 | E61: =D61+1 -> 2023 | F61: =E61+1 -> 2024 | G61: =F61+1 -> 2025 | H61: =G61+1 -> 2026 | I61: =H61+1 -> 2027
B63: Sun Pharmaceutical Industries Ltd | C63: 2787 | D63: 4465 | E63: 9361 | F63: 11049 | G63: 13737 | H63: 13281 | I63: 16082
B64: % Revenue | C64: =C63/C$21 -> 0.083198749 | D64: =D63/D$21 -> 0.11551048 | E64: =E63/E$21 -> 0.21330411 | F64: =F63/F$21 -> 0.227829 | G64: =G63/G$21 -> 0.26126698 | H64: =H63/H$21 -> 0.23134003 | I64: =I63/I$21 -> 0.25326782
