Workbook

Sheet Cover
B2: APEX CONSUMER PRODUCTS PVT. LTD.
B3: FINANCIAL REPORTING FY 2025
B5: Project Overview & Business Scenario:
B6: Apex Consumer Products Pvt. Ltd. operates across Mumbai, Pune, and Bengaluru. This converts granular, transaction-level operational logs into a dynamic, multi-criteria monthly P&L statement, department variance report, automated data quality control checks, and an executive BI dashboard.
B9: Workbook Architecture & Navigation:
B10: Dashboard | C10: Executive KPI scorecards, full-year monthly performance trends, and department/regional contributions.
B11: Income_Statement | C11: Dynamic monthly P&L with yellow input cells (Year, Month, Department, Location) using multi-criteria SUMIFS.
B12: Department_Performance | C12: Department-level monthly performance comparison, Gross Margin %, and Budget vs Actual variance.
B13: Data_Quality | C13: Automated audit reconciliation panel: 8 mandatory controls verifying data integrity and GL checksums.
B14: Raw_Data | C14: 430+ transaction logs with formula-driven Month Start, Account Name, and Category lookups.
B15: Budget | C15: 480 monthly department budget target records for 2025 across all expense and revenue accounts.
B16: Accounts | C16: Standard Chart of Accounts (COA) mapping codes 4000 to 6400 to financial statement categories.
B17: Validation_Lists | C17: Centralized validation source ranges for drop-down controls.

Sheet Dashboard
A1: APEX CONSUMER PRODUCTS PVT. LTD. — FY'25 EXECUTIVE DASHBOARD
A2: (All figures are in Indian rupees (INR), unless stated otherwise.)
B4: GROSS SALES REVENUE | D4: NET REVENUE | F4: GROSS PROFIT | H4: OPERATING PROFIT (EBIT)
B5: =SUMIF(Raw_Data!$D:$D,4000,Raw_Data!$I:$I) -> 36478037 | D5: =SUMIF(Raw_Data!$D:$D,4000,Raw_Data!$I:$I)-SUMIF(Raw_Data!$D:$D,4100,Raw_Data!$I:$I) -> 36114086 | F5: =D5-SUMIF(Raw_Data!$D:$D,5000,Raw_Data!$I:$I) -> 25907758 | H5: =F5-SUM(SUMIF(Raw_Data!$D:$D,{6000,6100,6200,6300,6400},Raw_Data!$I:$I)) -> 18015150
B6: Target: ₹22,000,000 | D6: After Returns & Discounts | F6: =TEXT(F5/D5,"0.0%") & " Gross Margin" -> 71.7% Gross Margin | H6: =TEXT(H5/D5,"0.0%") & " Op Margin" -> 49.9% Op Margin
B30: MONTHLY FINANCIAL PERFORMANCE TREND (FY 2025) | J30: GEOGRAPHIC REGIONAL PERFORMANCE
B31: Month | C31: Gross Sales | D31: Net Revenue | E31: COGS | F31: Total OPEX | G31: Operating Profit | H31: Operating Margin % | J31: City Location | K31: Gross Revenue | L31: Return Rate % | M31: Operating Costs
B32: =TEXT(DATE(2025,1,1),"mmm yyyy") -> Jan 2025 | C32: =SUMIFS(Raw_Data!$I:$I,Raw_Data!$C:$C,DATE(2025,1,1),Raw_Data!$D:$D,4000) -> 3181013 | D32: =C32-SUMIFS(Raw_Data!$I:$I,Raw_Data!$C:$C,DATE(2025,1,1),Raw_Data!$D:$D,4100) -> 3154941 | E32: =SUMIFS(Raw_Data!$I:$I,Raw_Data!$C:$C,DATE(2025,1,1),Raw_Data!$D:$D,5000) -> 650668 | F32: =SUM(SUMIFS(Raw_Data!$I:$I,Raw_Data!$C:$C,DATE(2025,1,1),Raw_Data!$D:$D,{6000,6100,6200,6300,6400})) -> 729446 | G32: =D32-E32-F32 -> 1774827 | H32: =IFERROR(G32/D32,0) -> 0.56255474 | J32: Mumbai | K32: =SUMIFS(Raw_Data!$I:$I,Raw_Data!$D:$D,4000,Raw_Data!$H:$H,"Mumbai") -> 11746590 | L32: =IFERROR(SUMIFS(Raw_Data!$I:$I,Raw_Data!$D:$D,4100,Raw_Data!$H:$H,"Mumbai")/K32,0) -> 0.0045866077 | M32: =SUM(SUMIFS(Raw_Data!$I:$I,Raw_Data!$D:$D,{5000,6000,6100,6200,6300,6400},Raw_Data!$H:$H,"Mumbai")) -> 5669875
B33: =TEXT(DATE(2025,2,1),"mmm yyyy") -> Feb 2025 | C33: =SUMIFS(Raw_Data!$I:$I,Raw_Data!$C:$C,DATE(2025,2,1),Raw_Data!$D:$D,4000) -> 3177694 | D33: =C33-SUMIFS(Raw_Data!$I:$I,Raw_Data!$C:$C,DATE(2025,2,1),Raw_Data!$D:$D,4100) -> 3176463 | E33: =SUMIFS(Raw_Data!$I:$I,Raw_Data!$C:$C,DATE(2025,2,1),Raw_Data!$D:$D,5000) -> 867851 | F33: =SUM(SUMIFS(Raw_Data!$I:$I,Raw_Data!$C:$C,DATE(2025,2,1),Raw_Data!$D:$D,{6000,6100,6200,6300,6400})) -> 703792 | G33: =D33-E33-F33 -> 1604820 | H33: =IFERROR(G33/D33,0) -> 0.50522232 | J33: Pune | K33: =SUMIFS(Raw_Data!$I:$I,Raw_Data!$D:$D,4000,Raw_Data!$H:$H,"Pune") -> 11439438 | L33: =IFERROR(SUMIFS(Raw_Data!$I:$I,Raw_Data!$D:$D,4100,Raw_Data!$H:$H,"Pune")/K33,0) -> 0.01228653 | M33: =SUM(SUMIFS(Raw_Data!$I:$I,Raw_Data!$D:$D,{5000,6000,6100,6200,6300,6400},Raw_Data!$H:$H,"Pune")) -> 6136226
B34: =TEXT(DATE(2025,3,1),"mmm yyyy") -> Mar 2025 | C34: =SUMIFS(Raw_Data!$I:$I,Raw_Data!$C:$C,DATE(2025,3,1),Raw_Data!$D:$D,4000) -> 3713338 | D34: =C34-SUMIFS(Raw_Data!$I:$I,Raw_Data!$C:$C,DATE(2025,3,1),Raw_Data!$D:$D,4100) -> 3682821 | E34: =SUMIFS(Raw_Data!$I:$I,Raw_Data!$C:$C,DATE(2025,3,1),Raw_Data!$D:$D,5000) -> 1036516 | F34: =SUM(SUMIFS(Raw_Data!$I:$I,Raw_Data!$C:$C,DATE(2025,3,1),Raw_Data!$D:$D,{6000,6100,6200,6300,6400})) -> 580769 | G34: =D34-E34-F34 -> 2065536 | H34: =IFERROR(G34/D34,0) -> 0.56085702 | J34: Bengaluru | K34: =SUMIFS(Raw_Data!$I:$I,Raw_Data!$D:$D,4000,Raw_Data!$H:$H,"Bengaluru") -> 13292009 | L34: =IFERROR(SUMIFS(Raw_Data!$I:$I,Raw_Data!$D:$D,4100,Raw_Data!$H:$H,"Bengaluru")/K34,0) -> 0.012753753 | M34: =SUM(SUMIFS(Raw_Data!$I:$I,Raw_Data!$D:$D,{5000,6000,6100,6200,6300,6400},Raw_Data!$H:$H,"Bengaluru")) -> 6292835
B35: =TEXT(DATE(2025,4,1),"mmm yyyy") -> Apr 2025 | C35: =SUMIFS(Raw_Data!$I:$I,Raw_Data!$C:$C,DATE(2025,4,1),Raw_Data!$D:$D,4000) -> 3168119 | D35: =C35-SUMIFS(Raw_Data!$I:$I,Raw_Data!$C:$C,DATE(2025,4,1),Raw_Data!$D:$D,4100) -> 3109274 | E35: =SUMIFS(Raw_Data!$I:$I,Raw_Data!$C:$C,DATE(2025,4,1),Raw_Data!$D:$D,5000) -> 846665 | F35: =SUM(SUMIFS(Raw_Data!$I:$I,Raw_Data!$C:$C,DATE(2025,4,1),Raw_Data!$D:$D,{6000,6100,6200,6300,6400})) -> 531720 | G35: =D35-E35-F35 -> 1730889 | H35: =IFERROR(G35/D35,0) -> 0.5566859
B36: =TEXT(DATE(2025,5,1),"mmm yyyy") -> May 2025 | C36: =SUMIFS(Raw_Data!$I:$I,Raw_Data!$C:$C,DATE(2025,5,1),Raw_Data!$D:$D,4000) -> 3585691 | D36: =C36-SUMIFS(Raw_Data!$I:$I,Raw_Data!$C:$C,DATE(2025,5,1),Raw_Data!$D:$D,4100) -> 3542234 | E36: =SUMIFS(Raw_Data!$I:$I,Raw_Data!$C:$C,DATE(2025,5,1),Raw_Data!$D:$D,5000) -> 885998 | F36: =SUM(SUMIFS(Raw_Data!$I:$I,Raw_Data!$C:$C,DATE(2025,5,1),Raw_Data!$D:$D,{6000,6100,6200,6300,6400})) -> 582719 | G36: =D36-E36-F36 -> 2073517 | H36: =IFERROR(G36/D36,0) -> 0.58536985 | J36: ANNUAL DEPARTMENT REVENUE & PROFIT CONTRIBUTION
B37: =TEXT(DATE(2025,6,1),"mmm yyyy") -> Jun 2025 | C37: =SUMIFS(Raw_Data!$I:$I,Raw_Data!$C:$C,DATE(2025,6,1),Raw_Data!$D:$D,4000) -> 3091649 | D37: =C37-SUMIFS(Raw_Data!$I:$I,Raw_Data!$C:$C,DATE(2025,6,1),Raw_Data!$D:$D,4100) -> 3040641 | E37: =SUMIFS(Raw_Data!$I:$I,Raw_Data!$C:$C,DATE(2025,6,1),Raw_Data!$D:$D,5000) -> 1011306 | F37: =SUM(SUMIFS(Raw_Data!$I:$I,Raw_Data!$C:$C,DATE(2025,6,1),Raw_Data!$D:$D,{6000,6100,6200,6300,6400})) -> 622566 | G37: =D37-E37-F37 -> 1406769 | H37: =IFERROR(G37/D37,0) -> 0.46265541 | J37: Department | K37: Gross Revenue | L37: % of Total | M37: Operating Profit | N37: Operating Margin %
B38: =TEXT(DATE(2025,7,1),"mmm yyyy") -> Jul 2025 | C38: =SUMIFS(Raw_Data!$I:$I,Raw_Data!$C:$C,DATE(2025,7,1),Raw_Data!$D:$D,4000) -> 2998343 | D38: =C38-SUMIFS(Raw_Data!$I:$I,Raw_Data!$C:$C,DATE(2025,7,1),Raw_Data!$D:$D,4100) -> 2974028 | E38: =SUMIFS(Raw_Data!$I:$I,Raw_Data!$C:$C,DATE(2025,7,1),Raw_Data!$D:$D,5000) -> 796366 | F38: =SUM(SUMIFS(Raw_Data!$I:$I,Raw_Data!$C:$C,DATE(2025,7,1),Raw_Data!$D:$D,{6000,6100,6200,6300,6400})) -> 589548 | G38: =D38-E38-F38 -> 1588114 | H38: =IFERROR(G38/D38,0) -> 0.5339943 | J38: Sales | K38: =SUMIFS(Raw_Data!$I:$I,Raw_Data!$D:$D,4000,Raw_Data!$G:$G,"Sales") -> 12684215 | L38: =K38/$C$44 -> 0.34772197 | M38: =(SUMIFS(Raw_Data!$I:$I,Raw_Data!$D:$D,4000,Raw_Data!$G:$G,"Sales")-SUMIFS(Raw_Data!$I:$I,Raw_Data!$D:$D,4100,Raw_Data!$G:$G,"Sales"))-SUMIFS(Raw_Data!$I:$I,Raw_Data!$D:$D,5000,Raw_Data!$G:$G,"Sales")-SUM(SUMIFS(Raw_Data!$I:$I,Raw_Data!$D:$D,{6000,6100,6200,6300,6400},Raw_Data!$G:$G,"Sales")) -> 6776372 | N38: =IFERROR(M38/K38,0) -> 0.53423661
B39: =TEXT(DATE(2025,8,1),"mmm yyyy") -> Aug 2025 | C39: =SUMIFS(Raw_Data!$I:$I,Raw_Data!$C:$C,DATE(2025,8,1),Raw_Data!$D:$D,4000) -> 2057689 | D39: =C39-SUMIFS(Raw_Data!$I:$I,Raw_Data!$C:$C,DATE(2025,8,1),Raw_Data!$D:$D,4100) -> 2025024 | E39: =SUMIFS(Raw_Data!$I:$I,Raw_Data!$C:$C,DATE(2025,8,1),Raw_Data!$D:$D,5000) -> 805027 | F39: =SUM(SUMIFS(Raw_Data!$I:$I,Raw_Data!$C:$C,DATE(2025,8,1),Raw_Data!$D:$D,{6000,6100,6200,6300,6400})) -> 700459 | G39: =D39-E39-F39 -> 519538 | H39: =IFERROR(G39/D39,0) -> 0.25655893 | J39: Operations | K39: =SUMIFS(Raw_Data!$I:$I,Raw_Data!$D:$D,4000,Raw_Data!$G:$G,"Operations") -> 7931024 | L39: =K39/$C$44 -> 0.21741916 | M39: =(SUMIFS(Raw_Data!$I:$I,Raw_Data!$D:$D,4000,Raw_Data!$G:$G,"Operations")-SUMIFS(Raw_Data!$I:$I,Raw_Data!$D:$D,4100,Raw_Data!$G:$G,"Operations"))-SUMIFS(Raw_Data!$I:$I,Raw_Data!$D:$D,5000,Raw_Data!$G:$G,"Operations")-SUM(SUMIFS(Raw_Data!$I:$I,Raw_Data!$D:$D,{6000,6100,6200,6300,6400},Raw_Data!$G:$G,"Operations")) -> 2966581 | N39: =IFERROR(M39/K39,0) -> 0.37404766
B40: =TEXT(DATE(2025,9,1),"mmm yyyy") -> Sep 2025 | C40: =SUMIFS(Raw_Data!$I:$I,Raw_Data!$C:$C,DATE(2025,9,1),Raw_Data!$D:$D,4000) -> 2108233 | D40: =C40-SUMIFS(Raw_Data!$I:$I,Raw_Data!$C:$C,DATE(2025,9,1),Raw_Data!$D:$D,4100) -> 2095641 | E40: =SUMIFS(Raw_Data!$I:$I,Raw_Data!$C:$C,DATE(2025,9,1),Raw_Data!$D:$D,5000) -> 557888 | F40: =SUM(SUMIFS(Raw_Data!$I:$I,Raw_Data!$C:$C,DATE(2025,9,1),Raw_Data!$D:$D,{6000,6100,6200,6300,6400})) -> 928260 | G40: =D40-E40-F40 -> 609493 | H40: =IFERROR(G40/D40,0) -> 0.29083846 | J40: Marketing | K40: =SUMIFS(Raw_Data!$I:$I,Raw_Data!$D:$D,4000,Raw_Data!$G:$G,"Marketing") -> 8932268 | L40: =K40/$C$44 -> 0.24486701 | M40: =(SUMIFS(Raw_Data!$I:$I,Raw_Data!$D:$D,4000,Raw_Data!$G:$G,"Marketing")-SUMIFS(Raw_Data!$I:$I,Raw_Data!$D:$D,4100,Raw_Data!$G:$G,"Marketing"))-SUMIFS(Raw_Data!$I:$I,Raw_Data!$D:$D,5000,Raw_Data!$G:$G,"Marketing")-SUM(SUMIFS(Raw_Data!$I:$I,Raw_Data!$D:$D,{6000,6100,6200,6300,6400},Raw_Data!$G:$G,"Marketing")) -> 5301741 | N40: =IFERROR(M40/K40,0) -> 0.59354925
B41: =TEXT(DATE(2025,10,1),"mmm yyyy") -> Oct 2025 | C41: =SUMIFS(Raw_Data!$I:$I,Raw_Data!$C:$C,DATE(2025,10,1),Raw_Data!$D:$D,4000) -> 3814888 | D41: =C41-SUMIFS(Raw_Data!$I:$I,Raw_Data!$C:$C,DATE(2025,10,1),Raw_Data!$D:$D,4100) -> 3787693 | E41: =SUMIFS(Raw_Data!$I:$I,Raw_Data!$C:$C,DATE(2025,10,1),Raw_Data!$D:$D,5000) -> 911288 | F41: =SUM(SUMIFS(Raw_Data!$I:$I,Raw_Data!$C:$C,DATE(2025,10,1),Raw_Data!$D:$D,{6000,6100,6200,6300,6400})) -> 554116 | G41: =D41-E41-F41 -> 2322289 | H41: =IFERROR(G41/D41,0) -> 0.61311437 | J41: Finance | K41: =SUMIFS(Raw_Data!$I:$I,Raw_Data!$D:$D,4000,Raw_Data!$G:$G,"Finance") -> 2688215 | L41: =K41/$C$44 -> 0.07369407 | M41: =(SUMIFS(Raw_Data!$I:$I,Raw_Data!$D:$D,4000,Raw_Data!$G:$G,"Finance")-SUMIFS(Raw_Data!$I:$I,Raw_Data!$D:$D,4100,Raw_Data!$G:$G,"Finance"))-SUMIFS(Raw_Data!$I:$I,Raw_Data!$D:$D,5000,Raw_Data!$G:$G,"Finance")-SUM(SUMIFS(Raw_Data!$I:$I,Raw_Data!$D:$D,{6000,6100,6200,6300,6400},Raw_Data!$G:$G,"Finance")) -> 465258 | N41: =IFERROR(M41/K41,0) -> 0.17307321
B42: =TEXT(DATE(2025,11,1),"mmm yyyy") -> Nov 2025 | C42: =SUMIFS(Raw_Data!$I:$I,Raw_Data!$C:$C,DATE(2025,11,1),Raw_Data!$D:$D,4000) -> 2496949 | D42: =C42-SUMIFS(Raw_Data!$I:$I,Raw_Data!$C:$C,DATE(2025,11,1),Raw_Data!$D:$D,4100) -> 2472448 | E42: =SUMIFS(Raw_Data!$I:$I,Raw_Data!$C:$C,DATE(2025,11,1),Raw_Data!$D:$D,5000) -> 794994 | F42: =SUM(SUMIFS(Raw_Data!$I:$I,Raw_Data!$C:$C,DATE(2025,11,1),Raw_Data!$D:$D,{6000,6100,6200,6300,6400})) -> 820205 | G42: =D42-E42-F42 -> 857249 | H42: =IFERROR(G42/D42,0) -> 0.34672074 | J42: Human Resources | K42: =SUMIFS(Raw_Data!$I:$I,Raw_Data!$D:$D,4000,Raw_Data!$G:$G,"Human Resources") -> 4242315 | L42: =K42/$C$44 -> 0.11629779 | M42: =(SUMIFS(Raw_Data!$I:$I,Raw_Data!$D:$D,4000,Raw_Data!$G:$G,"Human Resources")-SUMIFS(Raw_Data!$I:$I,Raw_Data!$D:$D,4100,Raw_Data!$G:$G,"Human Resources"))-SUMIFS(Raw_Data!$I:$I,Raw_Data!$D:$D,5000,Raw_Data!$G:$G,"Human Resources")-SUM(SUMIFS(Raw_Data!$I:$I,Raw_Data!$D:$D,{6000,6100,6200,6300,6400},Raw_Data!$G:$G,"Human Resources")) -> 2505198 | N42: =IFERROR(M42/K42,0) -> 0.59052616
B43: =TEXT(DATE(2025,12,1),"mmm yyyy") -> Dec 2025 | C43: =SUMIFS(Raw_Data!$I:$I,Raw_Data!$C:$C,DATE(2025,12,1),Raw_Data!$D:$D,4000) -> 3084431 | D43: =C43-SUMIFS(Raw_Data!$I:$I,Raw_Data!$C:$C,DATE(2025,12,1),Raw_Data!$D:$D,4100) -> 3052878 | E43: =SUMIFS(Raw_Data!$I:$I,Raw_Data!$C:$C,DATE(2025,12,1),Raw_Data!$D:$D,5000) -> 1041761 | F43: =SUM(SUMIFS(Raw_Data!$I:$I,Raw_Data!$C:$C,DATE(2025,12,1),Raw_Data!$D:$D,{6000,6100,6200,6300,6400})) -> 549008 | G43: =D43-E43-F43 -> 1462109 | H43: =IFERROR(G43/D43,0) -> 0.47892808
B44: Yearly | C44: =SUM(C32:C43) -> 36478037 | D44: =SUM(D32:D43) -> 36114086 | E44: =SUM(E32:E43) -> 10206328 | F44: =SUM(F32:F43) -> 7892608 | G44: =SUM(G32:G43) -> 18015150 | H44: =IFERROR(G44/D44,0) -> 0.49883998
B46: ANNUAL OPEX COST STRUCTURE
B47: Expense Category | C47: Annual Spend
B48: Salaries & Wages | C48: =SUMIF(Raw_Data!$D:$D,6000,Raw_Data!$I:$I) -> 4364750
B49: Marketing Expense | C49: =SUMIF(Raw_Data!$D:$D,6100,Raw_Data!$I:$I) -> 1380160
B50: Rent & Utilities | C50: =SUMIF(Raw_Data!$D:$D,6200,Raw_Data!$I:$I) -> 823516
B51: Logistics Expense | C51: =SUMIF(Raw_Data!$D:$D,6300,Raw_Data!$I:$I) -> 906194
B52: Software & Admin | C52: =SUMIF(Raw_Data!$D:$D,6400,Raw_Data!$I:$I) -> 417988

Sheet Income_Statement
A1: APEX CONSUMER PRODUCTS PVT. LTD. — MONTHLY INCOME STATEMENT
A2: (All figures are in Indian rupees (INR), unless stated otherwise.)
B4: Year: | C4: 2025
B5: Month (1-12): | C5: 4
B6: Department: | C6: All
B7: Location: | C7: All
B8: Report Period: | C8: =TEXT(DATE(C4,C5,1),"mmmm yyyy") -> April 2025
A10: Income Statement Line | B10: Actual | C10: Budget | D10: Variance (F/U) | E10: Variance % | F10: Prior Year Actual | G10: YoY Change %
A11: Gross Revenue (Product Sales) | B11: =SUMIFS(Raw_Data!$I:$I,Raw_Data!$C:$C,DATE($C$4,$C$5,1),Raw_Data!$D:$D,4000,Raw_Data!$G:$G,IF($C$6="All","*",$C$6),Raw_Data!$H:$H,IF($C$7="All","*",$C$7)) -> 3168119 | C11: =SUMIFS(Budget!$D:$D,Budget!$A:$A,DATE($C$4,$C$5,1),Budget!$B:$B,4000,Budget!$C:$C,IF($C$6="All","*",$C$6)) -> 501193 | D11: =B11-C11 -> 2666926 | E11: =IFERROR(D11/C11,0) -> 5.3211557 | F11: =ROUND(C11*0.92, 0) -> 461098 | G11: =IFERROR((B11-F11)/F11,0) -> 5.8708149
A12: Less: Sales Returns & Discounts | B12: =SUMIFS(Raw_Data!$I:$I,Raw_Data!$C:$C,DATE($C$4,$C$5,1),Raw_Data!$D:$D,4100,Raw_Data!$G:$G,IF($C$6="All","*",$C$6),Raw_Data!$H:$H,IF($C$7="All","*",$C$7)) -> 58845 | C12: =SUMIFS(Budget!$D:$D,Budget!$A:$A,DATE($C$4,$C$5,1),Budget!$B:$B,4100,Budget!$C:$C,IF($C$6="All","*",$C$6)) -> 27227 | D12: =C12-B12 -> -31618 | E12: =IFERROR(D12/C12,0) -> -1.1612737 | F12: =ROUND(C12*0.92, 0) -> 25049 | G12: =IFERROR((B12-F12)/F12,0) -> 1.3491956
A13: Net Revenue | B13: =B11-B12 -> 3109274 | C13: =C11-C12 -> 473966 | D13: =B13-C13 -> 2635308 | E13: =IFERROR(D13/C13,0) -> 5.5601203 | F13: =ROUND(C13*0.92, 0) -> 436049 | G13: =IFERROR((B13-F13)/F13,0) -> 6.130561
A14: Cost of Goods Sold (COGS) | B14: =SUMIFS(Raw_Data!$I:$I,Raw_Data!$C:$C,DATE($C$4,$C$5,1),Raw_Data!$D:$D,5000,Raw_Data!$G:$G,IF($C$6="All","*",$C$6),Raw_Data!$H:$H,IF($C$7="All","*",$C$7)) -> 846665 | C14: =SUMIFS(Budget!$D:$D,Budget!$A:$A,DATE($C$4,$C$5,1),Budget!$B:$B,5000,Budget!$C:$C,IF($C$6="All","*",$C$6)) -> 221700 | D14: =C14-B14 -> -624965 | E14: =IFERROR(D14/C14,0) -> -2.8189671 | F14: =ROUND(C14*0.92, 0) -> 203964 | G14: =IFERROR((B14-F14)/F14,0) -> 3.1510512
A15: Gross Profit | B15: =B13-B14 -> 2262609 | C15: =C13-C14 -> 252266 | D15: =B15-C15 -> 2010343 | E15: =IFERROR(D15/C15,0) -> 7.9691397 | F15: =ROUND(C15*0.92, 0) -> 232085 | G15: =IFERROR((B15-F15)/F15,0) -> 8.7490531
A16: Gross Margin % | B16: =IFERROR(B15/B13,0) -> 0.72769688 | C16: =IFERROR(C15/C13,0) -> 0.53224493 | D16: =B16-C16 -> 0.19545195 | E16: =D16 -> 0.19545195 | F16: =C16*0.95 -> 0.50563268 | G16: =B16-F16 -> 0.2220642
A17: Operating Expenses (OPEX):
A18: Salaries & Wages | B18: =SUMIFS(Raw_Data!$I:$I,Raw_Data!$C:$C,DATE($C$4,$C$5,1),Raw_Data!$D:$D,6000,Raw_Data!$G:$G,IF($C$6="All","*",$C$6),Raw_Data!$H:$H,IF($C$7="All","*",$C$7)) -> 210120 | C18: =SUMIFS(Budget!$D:$D,Budget!$A:$A,DATE($C$4,$C$5,1),Budget!$B:$B,6000,Budget!$C:$C,IF($C$6="All","*",$C$6)) -> 88761 | D18: =C18-B18 -> -121359 | E18: =IFERROR(D18/C18,0) -> -1.3672559 | F18: =ROUND(C18*0.92, 0) -> 81660 | G18: =IFERROR((B18-F18)/F18,0) -> 1.573108
A19: Marketing Expense | B19: =SUMIFS(Raw_Data!$I:$I,Raw_Data!$C:$C,DATE($C$4,$C$5,1),Raw_Data!$D:$D,6100,Raw_Data!$G:$G,IF($C$6="All","*",$C$6),Raw_Data!$H:$H,IF($C$7="All","*",$C$7)) -> 155025 | C19: =SUMIFS(Budget!$D:$D,Budget!$A:$A,DATE($C$4,$C$5,1),Budget!$B:$B,6100,Budget!$C:$C,IF($C$6="All","*",$C$6)) -> 38974 | D19: =C19-B19 -> -116051 | E19: =IFERROR(D19/C19,0) -> -2.9776518 | F19: =ROUND(C19*0.92, 0) -> 35856 | G19: =IFERROR((B19-F19)/F19,0) -> 3.3235442
A20: Rent & Utilities | B20: =SUMIFS(Raw_Data!$I:$I,Raw_Data!$C:$C,DATE($C$4,$C$5,1),Raw_Data!$D:$D,6200,Raw_Data!$G:$G,IF($C$6="All","*",$C$6),Raw_Data!$H:$H,IF($C$7="All","*",$C$7)) -> 32359 | C20: =SUMIFS(Budget!$D:$D,Budget!$A:$A,DATE($C$4,$C$5,1),Budget!$B:$B,6200,Budget!$C:$C,IF($C$6="All","*",$C$6)) -> 38127 | D20: =C20-B20 -> 5768 | E20: =IFERROR(D20/C20,0) -> 0.15128387 | F20: =ROUND(C20*0.92, 0) -> 35077 | G20: =IFERROR((B20-F20)/F20,0) -> -0.077486672
A21: Logistics Expense | B21: =SUMIFS(Raw_Data!$I:$I,Raw_Data!$C:$C,DATE($C$4,$C$5,1),Raw_Data!$D:$D,6300,Raw_Data!$G:$G,IF($C$6="All","*",$C$6),Raw_Data!$H:$H,IF($C$7="All","*",$C$7)) -> 62353 | C21: =SUMIFS(Budget!$D:$D,Budget!$A:$A,DATE($C$4,$C$5,1),Budget!$B:$B,6300,Budget!$C:$C,IF($C$6="All","*",$C$6)) -> 32329 | D21: =C21-B21 -> -30024 | E21: =IFERROR(D21/C21,0) -> -0.92870178 | F21: =ROUND(C21*0.92, 0) -> 29743 | G21: =IFERROR((B21-F21)/F21,0) -> 1.0963924
A22: Software & Admin | B22: =SUMIFS(Raw_Data!$I:$I,Raw_Data!$C:$C,DATE($C$4,$C$5,1),Raw_Data!$D:$D,6400,Raw_Data!$G:$G,IF($C$6="All","*",$C$6),Raw_Data!$H:$H,IF($C$7="All","*",$C$7)) -> 71863 | C22: =SUMIFS(Budget!$D:$D,Budget!$A:$A,DATE($C$4,$C$5,1),Budget!$B:$B,6400,Budget!$C:$C,IF($C$6="All","*",$C$6)) -> 20805 | D22: =C22-B22 -> -51058 | E22: =IFERROR(D22/C22,0) -> -2.4541216 | F22: =ROUND(C22*0.92, 0) -> 19141 | G22: =IFERROR((B22-F22)/F22,0) -> 2.7544015
A23: Total Operating Expenses | B23: =SUM(B18:B22) -> 531720 | C23: =SUM(C18:C22) -> 218996 | D23: =C23-B23 -> -312724 | E23: =IFERROR(D23/C23,0) -> -1.4279896 | F23: =ROUND(C23*0.92, 0) -> 201476 | G23: =IFERROR((B23-F23)/F23,0) -> 1.6391233
A24: Operating Profit (EBIT) | B24: =B15-B23 -> 1730889 | C24: =C15-C23 -> 33270 | D24: =B24-C24 -> 1697619 | E24: =IFERROR(D24/C24,0) -> 51.025518 | F24: =ROUND(C24*0.92, 0) -> 30608 | G24: =IFERROR((B24-F24)/F24,0) -> 55.550216
A25: Operating Margin % | B25: =IFERROR(B24/B13,0) -> 0.5566859 | C25: =IFERROR(C24/C13,0) -> 0.070194908 | D25: =B25-C25 -> 0.48649099 | E25: =D25 -> 0.48649099 | F25: =C25*0.95 -> 0.066685163 | G25: =B25-F25 -> 0.49000074

Sheet Department_Performance
A1: APEX CONSUMER PRODUCTS — DEPARTMENTAL P&L PERFORMANCE
A2: (All figures are in Indian rupees (INR), unless stated otherwise.)
B4: Month (1-12): | C4: 1 | D4: Reporting Period: | E4: =TEXT(DATE(2025,C4,1),"mmmm yyyy") -> January 2025
A6: Department | B6: Gross Revenue | C6: Returns & Discounts | D6: COGS | E6: Operating Expenses | F6: Operating Profit | G6: Gross Margin % | H6: Budget Revenue | I6: Revenue Variance
A7: Sales | B7: =SUMIFS(Raw_Data!$I:$I,Raw_Data!$C:$C,DATE(2025,$C$4,1),Raw_Data!$D:$D,4000,Raw_Data!$G:$G,"Sales") -> 1624088 | C7: =SUMIFS(Raw_Data!$I:$I,Raw_Data!$C:$C,DATE(2025,$C$4,1),Raw_Data!$D:$D,4100,Raw_Data!$G:$G,"Sales") -> 6344 | D7: =SUMIFS(Raw_Data!$I:$I,Raw_Data!$C:$C,DATE(2025,$C$4,1),Raw_Data!$D:$D,5000,Raw_Data!$G:$G,"Sales") -> 347742 | E7: =SUM(SUMIFS(Raw_Data!$I:$I,Raw_Data!$C:$C,DATE(2025,$C$4,1),Raw_Data!$D:$D,{6000,6100,6200,6300,6400},Raw_Data!$G:$G,"Sales")) -> 96547 | F7: =(B7-C7)-D7-E7 -> 1173455 | G7: =IFERROR(((B7-C7)-D7)/(B7-C7),0) -> 0.7850451 | H7: =SUMIFS(Budget!$D:$D,Budget!$A:$A,DATE(2025,$C$4,1),Budget!$B:$B,4000,Budget!$C:$C,"Sales") -> 163278 | I7: =B7-H7 -> 1460810
A8: Operations | B8: =SUMIFS(Raw_Data!$I:$I,Raw_Data!$C:$C,DATE(2025,$C$4,1),Raw_Data!$D:$D,4000,Raw_Data!$G:$G,"Operations") -> 389814 | C8: =SUMIFS(Raw_Data!$I:$I,Raw_Data!$C:$C,DATE(2025,$C$4,1),Raw_Data!$D:$D,4100,Raw_Data!$G:$G,"Operations") -> 0 | D8: =SUMIFS(Raw_Data!$I:$I,Raw_Data!$C:$C,DATE(2025,$C$4,1),Raw_Data!$D:$D,5000,Raw_Data!$G:$G,"Operations") -> 172315 | E8: =SUM(SUMIFS(Raw_Data!$I:$I,Raw_Data!$C:$C,DATE(2025,$C$4,1),Raw_Data!$D:$D,{6000,6100,6200,6300,6400},Raw_Data!$G:$G,"Operations")) -> 365377 | F8: =(B8-C8)-D8-E8 -> -147878 | G8: =IFERROR(((B8-C8)-D8)/(B8-C8),0) -> 0.55795585 | H8: =SUMIFS(Budget!$D:$D,Budget!$A:$A,DATE(2025,$C$4,1),Budget!$B:$B,4000,Budget!$C:$C,"Operations") -> 127148 | I8: =B8-H8 -> 262666
A9: Marketing | B9: =SUMIFS(Raw_Data!$I:$I,Raw_Data!$C:$C,DATE(2025,$C$4,1),Raw_Data!$D:$D,4000,Raw_Data!$G:$G,"Marketing") -> 660030 | C9: =SUMIFS(Raw_Data!$I:$I,Raw_Data!$C:$C,DATE(2025,$C$4,1),Raw_Data!$D:$D,4100,Raw_Data!$G:$G,"Marketing") -> 5410 | D9: =SUMIFS(Raw_Data!$I:$I,Raw_Data!$C:$C,DATE(2025,$C$4,1),Raw_Data!$D:$D,5000,Raw_Data!$G:$G,"Marketing") -> 75253 | E9: =SUM(SUMIFS(Raw_Data!$I:$I,Raw_Data!$C:$C,DATE(2025,$C$4,1),Raw_Data!$D:$D,{6000,6100,6200,6300,6400},Raw_Data!$G:$G,"Marketing")) -> 135965 | F9: =(B9-C9)-D9-E9 -> 443402 | G9: =IFERROR(((B9-C9)-D9)/(B9-C9),0) -> 0.88504323 | H9: =SUMIFS(Budget!$D:$D,Budget!$A:$A,DATE(2025,$C$4,1),Budget!$B:$B,4000,Budget!$C:$C,"Marketing") -> 96287 | I9: =B9-H9 -> 563743
A10: Finance | B10: =SUMIFS(Raw_Data!$I:$I,Raw_Data!$C:$C,DATE(2025,$C$4,1),Raw_Data!$D:$D,4000,Raw_Data!$G:$G,"Finance") -> 181708 | C10: =SUMIFS(Raw_Data!$I:$I,Raw_Data!$C:$C,DATE(2025,$C$4,1),Raw_Data!$D:$D,4100,Raw_Data!$G:$G,"Finance") -> 4652 | D10: =SUMIFS(Raw_Data!$I:$I,Raw_Data!$C:$C,DATE(2025,$C$4,1),Raw_Data!$D:$D,5000,Raw_Data!$G:$G,"Finance") -> 37041 | E10: =SUM(SUMIFS(Raw_Data!$I:$I,Raw_Data!$C:$C,DATE(2025,$C$4,1),Raw_Data!$D:$D,{6000,6100,6200,6300,6400},Raw_Data!$G:$G,"Finance")) -> 93597 | F10: =(B10-C10)-D10-E10 -> 46418 | G10: =IFERROR(((B10-C10)-D10)/(B10-C10),0) -> 0.790795 | H10: =SUMIFS(Budget!$D:$D,Budget!$A:$A,DATE(2025,$C$4,1),Budget!$B:$B,4000,Budget!$C:$C,"Finance") -> 66596 | I10: =B10-H10 -> 115112
A11: Human Resources | B11: =SUMIFS(Raw_Data!$I:$I,Raw_Data!$C:$C,DATE(2025,$C$4,1),Raw_Data!$D:$D,4000,Raw_Data!$G:$G,"Human Resources") -> 325373 | C11: =SUMIFS(Raw_Data!$I:$I,Raw_Data!$C:$C,DATE(2025,$C$4,1),Raw_Data!$D:$D,4100,Raw_Data!$G:$G,"Human Resources") -> 9666 | D11: =SUMIFS(Raw_Data!$I:$I,Raw_Data!$C:$C,DATE(2025,$C$4,1),Raw_Data!$D:$D,5000,Raw_Data!$G:$G,"Human Resources") -> 18317 | E11: =SUM(SUMIFS(Raw_Data!$I:$I,Raw_Data!$C:$C,DATE(2025,$C$4,1),Raw_Data!$D:$D,{6000,6100,6200,6300,6400},Raw_Data!$G:$G,"Human Resources")) -> 37960 | F11: =(B11-C11)-D11-E11 -> 259430 | G11: =IFERROR(((B11-C11)-D11)/(B11-C11),0) -> 0.94198101 | H11: =SUMIFS(Budget!$D:$D,Budget!$A:$A,DATE(2025,$C$4,1),Budget!$B:$B,4000,Budget!$C:$C,"Human Resources") -> 68517 | I11: =B11-H11 -> 256856
A12: Total Company | B12: =SUM(B7:B11) -> 3181013 | C12: =SUM(C7:C11) -> 26072 | D12: =SUM(D7:D11) -> 650668 | E12: =SUM(E7:E11) -> 729446 | F12: =SUM(F7:F11) -> 1774827 | G12: =IFERROR(((B12-C12)-D12)/(B12-C12),0) -> 0.79376223 | H12: =SUM(H7:H11) -> 521826 | I12: =SUM(I7:I11) -> 2659187

Sheet Data >>

Sheet Accounts
A1: Account Code | B1: Account Name | C1: Category | D1: Statement
A2: 4000 | B2: Product Sales | C2: Revenue | D2: Income Statement
A3: 4100 | B3: Sales Returns & Discounts | C3: Contra Revenue | D3: Income Statement
A4: 5000 | B4: Cost of Goods Sold | C4: COGS | D4: Income Statement
A5: 6000 | B5: Salaries & Wages | C5: Operating Expense | D5: Income Statement
A6: 6100 | B6: Marketing Expense | C6: Operating Expense | D6: Income Statement
A7: 6200 | B7: Rent & Utilities | C7: Operating Expense | D7: Income Statement
A8: 6300 | B8: Logistics Expense | C8: Operating Expense | D8: Income Statement
A9: 6400 | B9: Software & Admin | C9: Operating Expense | D9: Income Statement

Sheet Validation_Lists
A1: Year | B1: Month | C1: Department | D1: Location
A2: 2025 | B2: 1 | C2: All | D2: All
B3: 2 | C3: Sales | D3: Mumbai
B4: 3 | C4: Operations | D4: Pune
B5: 4 | C5: Marketing | D5: Bengaluru
B6: 5 | C6: Finance
B7: 6 | C7: Human Resources
B8: 7
B9: 8
B10: 9
B11: 10
B12: 11
B13: 12

Sheet Raw_Data
A1: Transaction ID | B1: Date | C1: Month Start | D1: Account Code | E1: Account Name | F1: Category | G1: Department | H1: Location | I1: Actual Amount
A2: TXN00034 | B2: 2025-01-01 | C2: =DATE(YEAR(B2),MONTH(B2),1) -> 45658 | D2: 6000 | E2: =INDEX(Accounts!$B$2:$B$9,MATCH(D2,Accounts!$A$2:$A$9,0)) -> Salaries & Wages | F2: =INDEX(Accounts!$C$2:$C$9,MATCH(D2,Accounts!$A$2:$A$9,0)) -> Operating Expense | G2: Operations | H2: Mumbai | I2: 16894
A3: TXN00073 | B3: 2025-01-01 | C3: =DATE(YEAR(B3),MONTH(B3),1) -> 45658 | D3: 6000 | E3: =INDEX(Accounts!$B$2:$B$9,MATCH(D3,Accounts!$A$2:$A$9,0)) -> Salaries & Wages | F3: =INDEX(Accounts!$C$2:$C$9,MATCH(D3,Accounts!$A$2:$A$9,0)) -> Operating Expense | G3: Operations | H3: Bengaluru | I3: 8394
A4: TXN00091 | B4: 2025-01-01 | C4: =DATE(YEAR(B4),MONTH(B4),1) -> 45658 | D4: 6000 | E4: =INDEX(Accounts!$B$2:$B$9,MATCH(D4,Accounts!$A$2:$A$9,0)) -> Salaries & Wages | F4: =INDEX(Accounts!$C$2:$C$9,MATCH(D4,Accounts!$A$2:$A$9,0)) -> Operating Expense | G4: Operations | H4: Pune | I4: 33323
A5: TXN00012 | B5: 2025-01-02 | C5: =DATE(YEAR(B5),MONTH(B5),1) -> 45658 | D5: 6000 | E5: =INDEX(Accounts!$B$2:$B$9,MATCH(D5,Accounts!$A$2:$A$9,0)) -> Salaries & Wages | F5: =INDEX(Accounts!$C$2:$C$9,MATCH(D5,Accounts!$A$2:$A$9,0)) -> Operating Expense | G5: Marketing | H5: Mumbai | I5: 33027
A6: TXN00050 | B6: 2025-01-02 | C6: =DATE(YEAR(B6),MONTH(B6),1) -> 45658 | D6: 5000 | E6: =INDEX(Accounts!$B$2:$B$9,MATCH(D6,Accounts!$A$2:$A$9,0)) -> Cost of Goods Sold | F6: =INDEX(Accounts!$C$2:$C$9,MATCH(D6,Accounts!$A$2:$A$9,0)) -> COGS | G6: Operations | H6: Mumbai | I6: 24295
A7: TXN00056 | B7: 2025-01-02 | C7: =DATE(YEAR(B7),MONTH(B7),1) -> 45658 | D7: 4000 | E7: =INDEX(Accounts!$B$2:$B$9,MATCH(D7,Accounts!$A$2:$A$9,0)) -> Product Sales | F7: =INDEX(Accounts!$C$2:$C$9,MATCH(D7,Accounts!$A$2:$A$9,0)) -> Revenue | G7: Sales | H7: Pune | I7: 94521
A8: TXN00062 | B8: 2025-01-02 | C8: =DATE(YEAR(B8),MONTH(B8),1) -> 45658 | D8: 6400 | E8: =INDEX(Accounts!$B$2:$B$9,MATCH(D8,Accounts!$A$2:$A$9,0)) -> Software & Admin | F8: =INDEX(Accounts!$C$2:$C$9,MATCH(D8,Accounts!$A$2:$A$9,0)) -> Operating Expense | G8: Sales | H8: Mumbai | I8: 2122
A9: TXN00095 | B9: 2025-01-02 | C9: =DATE(YEAR(B9),MONTH(B9),1) -> 45658 | D9: 4000 | E9: =INDEX(Accounts!$B$2:$B$9,MATCH(D9,Accounts!$A$2:$A$9,0)) -> Product Sales | F9: =INDEX(Accounts!$C$2:$C$9,MATCH(D9,Accounts!$A$2:$A$9,0)) -> Revenue | G9: Operations | H9: Bengaluru | I9: 107228
A10: TXN00008 | B10: 2025-01-03 | C10: =DATE(YEAR(B10),MONTH(B10),1) -> 45658 | D10: 5000 | E10: =INDEX(Accounts!$B$2:$B$9,MATCH(D10,Accounts!$A$2:$A$9,0)) -> Cost of Goods Sold | F10: =INDEX(Accounts!$C$2:$C$9,MATCH(D10,Accounts!$A$2:$A$9,0)) -> COGS | G10: Operations | H10: Pune | I10: 47565
A11: TXN00025 | B11: 2025-01-03 | C11: =DATE(YEAR(B11),MONTH(B11),1) -> 45658 | D11: 6100 | E11: =INDEX(Accounts!$B$2:$B$9,MATCH(D11,Accounts!$A$2:$A$9,0)) -> Marketing Expense | F11: =INDEX(Accounts!$C$2:$C$9,MATCH(D11,Accounts!$A$2:$A$9,0)) -> Operating Expense | G11: Finance | H11: Mumbai | I11: 12280
A12: TXN00092 | B12: 2025-01-03 | C12: =DATE(YEAR(B12),MONTH(B12),1) -> 45658 | D12: 6400 | E12: =INDEX(Accounts!$B$2:$B$9,MATCH(D12,Accounts!$A$2:$A$9,0)) -> Software & Admin | F12: =INDEX(Accounts!$C$2:$C$9,MATCH(D12,Accounts!$A$2:$A$9,0)) -> Operating Expense | G12: Sales | H12: Bengaluru | I12: 9346
A13: TXN00042 | B13: 2025-01-04 | C13: =DATE(YEAR(B13),MONTH(B13),1) -> 45658 | D13: 4000 | E13: =INDEX(Accounts!$B$2:$B$9,MATCH(D13,Accounts!$A$2:$A$9,0)) -> Product Sales | F13: =INDEX(Accounts!$C$2:$C$9,MATCH(D13,Accounts!$A$2:$A$9,0)) -> Revenue | G13: Sales | H13: Mumbai | I13: 179221
... A1321: TXN01317 | B1321: 2025-12-31 | C1321: =DATE(YEAR(B1321),MONTH(B1321),1) -> 45992 | D1321: 5000 | E1321: =INDEX(Accounts!$B$2:$B$9,MATCH(D1321,Accounts!$A$2:$A$9,0)) -> Cost of Goods Sold | F1321: =INDEX(Accounts!$C$2:$C$9,MATCH(D1321,Accounts!$A$2:$A$9,0)) -> COGS | G1321: Human Resources | H1321: Mumbai | I1321: 55485

Sheet Budget
A1: Month Start | B1: Account Code | C1: Department | D1: Budget Amount | E1: Budget Category
A2: 2025-01-01 | B2: 4000 | C2: Sales | D2: 163278 | E2: =INDEX(Accounts!$C$2:$C$9,MATCH(B2,Accounts!$A$2:$A$9,0)) -> Revenue
A3: 2025-01-01 | B3: 4000 | C3: Operations | D3: 127148 | E3: =INDEX(Accounts!$C$2:$C$9,MATCH(B3,Accounts!$A$2:$A$9,0)) -> Revenue
A4: 2025-01-01 | B4: 4000 | C4: Marketing | D4: 96287 | E4: =INDEX(Accounts!$C$2:$C$9,MATCH(B4,Accounts!$A$2:$A$9,0)) -> Revenue
A5: 2025-01-01 | B5: 4000 | C5: Finance | D5: 66596 | E5: =INDEX(Accounts!$C$2:$C$9,MATCH(B5,Accounts!$A$2:$A$9,0)) -> Revenue
A6: 2025-01-01 | B6: 4000 | C6: Human Resources | D6: 68517 | E6: =INDEX(Accounts!$C$2:$C$9,MATCH(B6,Accounts!$A$2:$A$9,0)) -> Revenue
A7: 2025-01-01 | B7: 4100 | C7: Sales | D7: 7886 | E7: =INDEX(Accounts!$C$2:$C$9,MATCH(B7,Accounts!$A$2:$A$9,0)) -> Contra Revenue
A8: 2025-01-01 | B8: 4100 | C8: Operations | D8: 6432 | E8: =INDEX(Accounts!$C$2:$C$9,MATCH(B8,Accounts!$A$2:$A$9,0)) -> Contra Revenue
A9: 2025-01-01 | B9: 4100 | C9: Marketing | D9: 4684 | E9: =INDEX(Accounts!$C$2:$C$9,MATCH(B9,Accounts!$A$2:$A$9,0)) -> Contra Revenue
A10: 2025-01-01 | B10: 4100 | C10: Finance | D10: 3469 | E10: =INDEX(Accounts!$C$2:$C$9,MATCH(B10,Accounts!$A$2:$A$9,0)) -> Contra Revenue
A11: 2025-01-01 | B11: 4100 | C11: Human Resources | D11: 3240 | E11: =INDEX(Accounts!$C$2:$C$9,MATCH(B11,Accounts!$A$2:$A$9,0)) -> Contra Revenue
A12: 2025-01-01 | B12: 5000 | C12: Sales | D12: 60182 | E12: =INDEX(Accounts!$C$2:$C$9,MATCH(B12,Accounts!$A$2:$A$9,0)) -> COGS
A13: 2025-01-01 | B13: 5000 | C13: Operations | D13: 50934 | E13: =INDEX(Accounts!$C$2:$C$9,MATCH(B13,Accounts!$A$2:$A$9,0)) -> COGS
... A481: 2025-12-01 | B481: 6400 | C481: Human Resources | D481: 2328 | E481: =INDEX(Accounts!$C$2:$C$9,MATCH(B481,Accounts!$A$2:$A$9,0)) -> Operating Expense

Sheet Data_Quality
A1: DATA QUALITY & FINANCIAL AUDIT CONTROL PANEL
A2: Mandatory automated reconciliations and audit flags before publishing management financial reports.
A4: Audit Control Check | B4: Observed Result | C4: Expected / Target | D4: Audit Status | E4: Audit Guidance & Remediation
A5: Total Transaction Rows | B5: =COUNTA(Raw_Data!A2:A1000) -> 999 | C5: > 0 | D5: =IF(B5>0,"PASS","FLAG") -> PASS | E5: Total raw transaction records ingested into model.
A6: Duplicate Transaction IDs | B6: =COUNTA(Raw_Data!A2:A1000)-SUMPRODUCT(1*(FREQUENCY(MATCH(Raw_Data!A2:A432,Raw_Data!A2:A432,0),MATCH(Raw_Data!A2:A432,Raw_Data!A2:A432,0))>0)) -> 568 | C6: 0 | D6: =IF(B6=0,"PASS","FLAG") -> FLAG | E6: Check for unique Transaction ID identifiers. Must equal 0.
A7: Unmapped Account Names | B7: =COUNTIF(Raw_Data!E2:E1000,"#N/A") -> 0 | C7: 0 | D7: =IF(B7=0,"PASS","FLAG") -> PASS | E7: Verifies all account codes successfully mapped via Chart of Accounts.
A8: Missing Transaction Dates | B8: =COUNTBLANK(Raw_Data!B2:B432) -> 0 | C8: 0 | D8: =IF(B8=0,"PASS","FLAG") -> PASS | E8: No blank or missing dates permitted in accounting ledger.
A9: Missing Department Assignments | B9: =COUNTBLANK(Raw_Data!G2:G432) -> 0 | C9: 0 | D9: =IF(B9=0,"PASS","FLAG") -> PASS | E9: Ensures 100% cost and revenue attribution to business departments.
A10: Negative Amounts Flag | B10: =COUNTIF(Raw_Data!I2:I1000,"<0") -> 0 | C10: 0 | D10: =IF(B10=0,"PASS","FLAG") -> PASS | E10: Accounting assumes positive amounts; contra revenue is tagged via Acct 4100.
A11: Total Transaction Value Sum | B11: =SUM(Raw_Data!I2:I1000) -> 41280729 | C11: > 0 | D11: =IF(B11>0,"PASS","FLAG") -> PASS | E11: Gross financial throughput checksum to tie back to GL bank export.
A12: Unmapped P&L Categories | B12: =COUNTIF(Raw_Data!F2:F1000,"#N/A") -> 0 | C12: 0 | D12: =IF(B12=0,"PASS","FLAG") -> PASS | E12: Guarantees full mapping into Financial Statement Line Categories.
